Workbook

Sheet Início
B2: RELATÓRIO FINANCEIRO 2026 — LOJA PLANETA ÁGUA
B3: Clique no nome de qualquer aba abaixo para ir direto até ela. Em toda aba há um link "← Início" para voltar.
B5: NÚMEROS DO ANO
B6: ENTRADAS (ANO) | C6: SAÍDAS DA LOJA (ANO) | D6: SOBRA FINAL (DEPOIS DO PRÓ-LABORE) | E6: A RECEBER | F6: DÍVIDA BB | G6: MARGEM FINAL DO ANO
B7: =Dashboard!A5 | C7: =Dashboard!C5 | D7: =Dashboard!E5 | E7: =Dashboard!I5 | F7: =Dashboard!K5 | G7: =Dashboard!G5
B9: SAÚDE FINANCEIRA DA LOJA (MÉDIA MENSAL)
B10: CUSTO FIXO MÉDIO/MÊS | C10: CUSTO VARIÁVEL MÉDIO/MÊS | D10: PRÓ-LABORE EDILÂNIA (ANO) | E10: PONTO DE EQUILÍBRIO (FAT. MÍN./MÊS) | F10: PRÓ-LABORE COMBINADO/MÊS | G10: SOBRA MÉDIA/MÊS DEPOIS DO PRÓ-LABORE
B11: ='DRE Simplificado'!O23 | C11: ='DRE Simplificado'!O10 | D11: =Dashboard!B53 | E11: ='Ponto de Equilíbrio'!B12 | F11: ='Ponto de Equilíbrio'!$B$10 | G11: ='Ponto de Equilíbrio'!B14
B13: COMECE AQUI — visão geral
B14: Dashboard | C14: Resumo do ano: entradas, saídas, lucro, insights automáticos e ranking de produtos.
B15: DRE Simplificado | C15: O resultado mês a mês, separando custo variável de custo fixo. Mostra se a operação se paga.
B17: DINHEIRO A ENTRAR E A SAIR
B18: Contas a Pagar e Receber | C18: Quem ainda deve para a loja e o que a loja ainda deve. Totais automáticos.
B19: Capital de Giro (BB) | C19: Contas da loja pagas com o empréstimo do Banco do Brasil e quanto falta devolver.
B21: PLANEJAMENTO
B22: Ponto de Equilíbrio | C22: Quanto precisa faturar por mês só para não ter prejuízo — e para lucrar o que quiser.
B23: Fluxo de Caixa Projetado | C23: Projeção do saldo de setembro a dezembro no ritmo atual.
B24: Reserva e Impostos
B25: Orçado vs Realizado | C25: Meta do mês contra o que realmente aconteceu, categoria por categoria.
B26: Precificação e Margem | C26: Quanto sobra de verdade em cada produto depois de custo, comissão, taxa e imposto.
B28: APOIO
B29: Conciliação Bancária | C29: Confere lançamento por lançamento contra o extrato do banco.
B30: Cadastro Clientes-Fornec | C30: Base única de nomes, documentos e contatos.
B32: LANÇAMENTOS MÊS A MÊS
B33: Jan 2026 | C33: Entradas pelas notas fiscais (XML do DigiSat) com cliente e produto · saídas do Livro Caixa
B34: Fev 2026 | C34: Entradas pelas notas fiscais (XML do DigiSat) com cliente e produto · saídas do Livro Caixa
B35: Mar 2026 | C35: Entradas pelas notas fiscais (XML do DigiSat) com cliente e produto · saídas do Livro Caixa
B36: Abr 2026 | C36: Entradas pelas notas fiscais (XML do DigiSat) com cliente e produto · saídas do Livro Caixa
B37: Mai 2026 | C37: Entradas pelas notas fiscais (XML do DigiSat) com cliente e produto · saídas do Livro Caixa
B38: Jun 2026 | C38: Entradas pelas notas fiscais (XML do DigiSat) com cliente e produto · saídas do Livro Caixa
B39: Jul 2026 | C39: Entradas pelas notas fiscais (XML do DigiSat) com cliente e produto · saídas do Livro Caixa
B40: Ago 2026 | C40: Lançamento manual, com forma de pagamento e taxa da máquina
B41: Set 2026 | C41: MÊS ATUAL — lançamento manual, com forma de pagamento e taxa da máquina
B42: Out 2026 | C42: Pronto para lançar
B43: Nov 2026 | C43: Pronto para lançar
B44: Dez 2026 | C44: Pronto para lançar
B46: Como usar no dia a dia
B47: 1. Lance cada venda e cada despesa na aba do mês (ex.: "Ago 2026") — uma linha por lançamento.
B48: 2. Venda ainda não paga: escolha "Aguardando Pagamento" na coluna Forma de Pagamento. Ela aparece sozinha no cartão A RECEBER e na aba Contas a Pagar e Receber.
B49: 3. Quando o cliente pagar, troque a forma de pagamento pelo método real. Todo o resto recalcula sozinho.
B50: 4. Tudo o que a Edilânia gasta do dinheiro da loja (contas da casa, Pix pessoais, mercado, diarista...): categoria "Pro Labore Edilânia". Isso é o pró-labore dela — combinado em R$ 4.000,00/mês (valor na aba Ponto de Equilíbrio, B10). Cada mês mostra quanto ela já gastou, quanto ainda pode gastar e a SOBRA FINAL da loja.
B51: 5. Dashboard e DRE não precisam ser preenchidos: puxam tudo das abas dos meses.

Sheet Dashboard
A1: DASHBOARD FINANCEIRO — LOJA DE FILTROS | 2026
A2: Jan–Dez: lançamentos das abas dos meses. Entradas = faturamento recebido (líquido de taxa de máquina e sem vendas pendentes); saídas = despesas da loja (sem o pró-labore e sem as contas pagas pelo Capital de Giro do BB). O pró-labore da Edilânia aparece separado e é descontado na coluna "Sobra final". Vendas ainda não recebidas ficam na tabela "Contas a Receber".
A3: ← Início
A4: ENTRADAS (ANO) | C4: SAÍDAS (ANO) | E4: SOBRA FINAL (DEPOIS DO PRÓ-LABORE) | G4: MARGEM FINAL DO ANO | I4: A RECEBER (ANO) | K4: DÍVIDA — CAPITAL DE GIRO (BB)
A5: =SUM(B24:B35) | C5: =SUM(C24:C35) | E5: =SUM(G24:G35) | G5: =IF(B36=0,0,G36/B36) | I5: =H46 | K5: ='Capital de Giro (BB)'!C5
A8: INSIGHTS AUTOMÁTICOS
A9: ="Melhor mês (sobra final, depois do pró-labore): "&INDEX(A24:A35,MATCH(MAX(G24:G35),G24:G35,0))&" ("&TEXT(MAX(G24:G35),"R$ #,##0.00")&")"
A10: ="Mês mais fraco (sobra final, depois do pró-labore): "&INDEX(A24:A35,MATCH(_xlfn.MINIFS(G24:G35,B24:B35,"<>0"),G24:G35,0))&" ("&TEXT(_xlfn.MINIFS(G24:G35,B24:B35,"<>0"),"R$ #,##0.00")&")"
A11: ="Meses que fecharam no negativo depois do pró-labore: "&COUNTIF(G24:G35,"<0")&" de "&COUNTIF(B24:B35,"<>0")&" meses com dados · pró-labore do ano: "&TEXT(F36,"R$ #,##0.00")&" (combinado: "&TEXT('Ponto de Equilíbrio'!$B$10,"R$ #,##0.00")&"/mês)"
A12: ="Total a receber (vendas pendentes Ago–Dez): "&TEXT(H46,"R$ #,##0.00")
A13: ="Atenção em Agosto: "&TEXT('Ago 2026'!L19,"R$ #,##0.00")&" de despesas da loja foram pagas com o empréstimo do Banco do Brasil e por isso NÃO entram nas Saídas acima. Sem esse alívio, o lucro de agosto seria "&TEXT(D31-'Ago 2026'!L19,"R$ #,##0.00")&". "&IF('Capital de Giro (BB)'!C5=0,"Esse valor já foi devolvido integralmente.","Esse valor ainda precisa ser devolvido.")
A14: ⚠ Limitações dos dados de origem (relatórios DigiSat/G6, não planilhas de fluxo de caixa):
A15: • O Livro Caixa não registra a forma de pagamento (dinheiro/cartão/Pix) de cada venda — por isso não há aba de 'Entradas por Forma de Pagamento' neste arquivo.
A16: • O relatório 'Itens vendidos' traz apenas totais agregados de Jan–Jul/2026 por produto, sem data nem cliente — não é possível vincular cada item a uma venda ou mês específico. Por isso os produtos aparecem apenas como referência anual no Dashboard, não em cada aba mensal.
A17: • 'Contas a pagar pendentes' vêm da Lista de Pagamentos (situação 'Pendente') e ainda não aparecem como saída no Livro Caixa, pois não foram pagas até 27/07/2026.
A18: • O saldo acumulado do Livro Caixa foi ignorado, conforme solicitado — os totais aqui são apenas de entradas e saídas de cada mês.
A19: • Este Dashboard é CAIXA (dinheiro que entrou e saiu de fato). A aba "DRE Simplificado" é COMPETÊNCIA (considera a despesa no mês em que ela ocorreu, inclusive as pagas pelo Capital de Giro). Por isso o lucro das duas abas não é igual — as duas estão certas, medem coisas diferentes.
A23: Mês | B23: Entradas (R$) | C23: Saídas (R$) | D23: Lucro da loja (R$) | E23: Margem da loja (%) | F23: Pró-labore Edilânia (R$) | G23: Sobra final (R$)
A24: Janeiro | B24: =SUMIF('Jan 2026'!A5:A500,"<>",'Jan 2026'!D5:D500)-SUMIF('Jan 2026'!A5:A500,"<>",'Jan 2026'!F5:F500)-'Jan 2026'!T5 | C24: ='Jan 2026'!L18-'Jan 2026'!L19 | D24: =B24-C24 | E24: =IF(B24=0,0,D24/B24) | F24: ='Jan 2026'!L17 | G24: =D24-F24
A25: Fevereiro | B25: =SUMIF('Fev 2026'!A5:A500,"<>",'Fev 2026'!D5:D500)-SUMIF('Fev 2026'!A5:A500,"<>",'Fev 2026'!F5:F500)-'Fev 2026'!T5 | C25: ='Fev 2026'!L18-'Fev 2026'!L19 | D25: =B25-C25 | E25: =IF(B25=0,0,D25/B25) | F25: ='Fev 2026'!L17 | G25: =D25-F25
A26: Março | B26: =SUMIF('Mar 2026'!A5:A500,"<>",'Mar 2026'!D5:D500)-SUMIF('Mar 2026'!A5:A500,"<>",'Mar 2026'!F5:F500)-'Mar 2026'!T5 | C26: ='Mar 2026'!L18-'Mar 2026'!L19 | D26: =B26-C26 | E26: =IF(B26=0,0,D26/B26) | F26: ='Mar 2026'!L17 | G26: =D26-F26
A27: Abril | B27: =SUMIF('Abr 2026'!A5:A500,"<>",'Abr 2026'!D5:D500)-SUMIF('Abr 2026'!A5:A500,"<>",'Abr 2026'!F5:F500)-'Abr 2026'!T5 | C27: ='Abr 2026'!L18-'Abr 2026'!L19 | D27: =B27-C27 | E27: =IF(B27=0,0,D27/B27) | F27: ='Abr 2026'!L17 | G27: =D27-F27
A28: Maio | B28: =SUMIF('Mai 2026'!A5:A500,"<>",'Mai 2026'!D5:D500)-SUMIF('Mai 2026'!A5:A500,"<>",'Mai 2026'!F5:F500)-'Mai 2026'!T5 | C28: ='Mai 2026'!L18-'Mai 2026'!L19 | D28: =B28-C28 | E28: =IF(B28=0,0,D28/B28) | F28: ='Mai 2026'!L17 | G28: =D28-F28
A29: Junho | B29: =SUMIF('Jun 2026'!A5:A500,"<>",'Jun 2026'!D5:D500)-SUMIF('Jun 2026'!A5:A500,"<>",'Jun 2026'!F5:F500)-'Jun 2026'!T5 | C29: ='Jun 2026'!L18-'Jun 2026'!L19 | D29: =B29-C29 | E29: =IF(B29=0,0,D29/B29) | F29: ='Jun 2026'!L17 | G29: =D29-F29
A30: Julho | B30: =SUMIF('Jul 2026'!A5:A500,"<>",'Jul 2026'!D5:D500)-SUMIF('Jul 2026'!A5:A500,"<>",'Jul 2026'!F5:F500)-'Jul 2026'!T5 | C30: ='Jul 2026'!L18-'Jul 2026'!L19 | D30: =B30-C30 | E30: =IF(B30=0,0,D30/B30) | F30: ='Jul 2026'!L17 | G30: =D30-F30
A31: Agosto | B31: =SUMIF('Ago 2026'!E5:E500,"<>",'Ago 2026'!D5:D500)-SUMIF('Ago 2026'!E5:E500,"<>",'Ago 2026'!F5:F500)-SUMIF('Ago 2026'!E5:E500,"Aguardando Pagamento",'Ago 2026'!D5:D500) | C31: ='Ago 2026'!L18-'Ago 2026'!L19 | D31: =B31-C31 | E31: =IF(B31=0,0,D31/B31) | F31: ='Ago 2026'!L17 | G31: =D31-F31
A32: Setembro | B32: =SUMIF('Set 2026'!E5:E500,"<>",'Set 2026'!D5:D500)-SUMIF('Set 2026'!E5:E500,"<>",'Set 2026'!F5:F500)-SUMIF('Set 2026'!E5:E500,"Aguardando Pagamento",'Set 2026'!D5:D500) | C32: ='Set 2026'!L18-'Set 2026'!L19 | D32: =B32-C32 | E32: =IF(B32=0,0,D32/B32) | F32: ='Set 2026'!L17 | G32: =D32-F32
A33: Outubro | B33: =SUMIF('Out 2026'!E5:E500,"<>",'Out 2026'!D5:D500)-SUMIF('Out 2026'!E5:E500,"<>",'Out 2026'!F5:F500)-SUMIF('Out 2026'!E5:E500,"Aguardando Pagamento",'Out 2026'!D5:D500) | C33: ='Out 2026'!L18-'Out 2026'!L19 | D33: =B33-C33 | E33: =IF(B33=0,0,D33/B33) | F33: ='Out 2026'!L17 | G33: =D33-F33
A34: Novembro | B34: =SUMIF('Nov 2026'!E5:E500,"<>",'Nov 2026'!D5:D500)-SUMIF('Nov 2026'!E5:E500,"<>",'Nov 2026'!F5:F500)-SUMIF('Nov 2026'!E5:E500,"Aguardando Pagamento",'Nov 2026'!D5:D500) | C34: ='Nov 2026'!L18-'Nov 2026'!L19 | D34: =B34-C34 | E34: =IF(B34=0,0,D34/B34) | F34: ='Nov 2026'!L17 | G34: =D34-F34
A35: Dezembro | B35: =SUMIF('Dez 2026'!E5:E500,"<>",'Dez 2026'!D5:D500)-SUMIF('Dez 2026'!E5:E500,"<>",'Dez 2026'!F5:F500)-SUMIF('Dez 2026'!E5:E500,"Aguardando Pagamento",'Dez 2026'!D5:D500) | C35: ='Dez 2026'!L18-'Dez 2026'!L19 | D35: =B35-C35 | E35: =IF(B35=0,0,D35/B35) | F35: ='Dez 2026'!L17 | G35: =D35-F35
A36: TOTAL / MÉDIA | B36: =SUM(B24:B35) | C36: =SUM(C24:C35) | D36: =SUM(D24:D35) | E36: =IF(B36=0,0,D36/B36) | F36: =SUM(F24:F35) | G36: =SUM(G24:G35)
A39: Saídas por Categoria (Ano 2026) | F39: Contas a Receber — Vendas Pendentes (Ago–Dez/2026)
A40: Categoria | B40: Valor (R$) | C40: % do Total | F40: Mês | H40: Valor (R$)
A41: Fornecedores / Mercadoria | B41: =SUMIF('Jan 2026'!H5:H500,$A41,'Jan 2026'!G5:G500)+SUMIF('Fev 2026'!H5:H500,$A41,'Fev 2026'!G5:G500)+SUMIF('Mar 2026'!H5:H500,$A41,'Mar 2026'!G5:G500)+SUMIF('Abr 2026'!H5:H500,$A41,'Abr 2026'!G5:G500)+SUMIF('Mai 2026'!H5:H500,$A41,'Mai 2026'!G5:G500)+SUMIF('Jun 2026'!H5:H500,$A41,'Jun 2026'!G5:G500)+SUMIF('Jul 2026'!H5:H500,$A41,'Jul 2026'!G5:G500)+SUMIF('Ago 2026'!H5:H500,$A41,'Ago 2026'!G5:G500)+SUMIF('Set 2026'!H5:H500,$A41,'Set 2026'!G5:G500)+SUMIF('Out 2026'!H5:H500,$A41,'Out 2026'!G5:G500)+SUMIF('Nov 2026'!H5:H500,$A41,'Nov 2026'!G5:G500)+SUMIF('Dez 2026'!H5:H500,$A41,'Dez 2026'!G5:G500) | C41: =IF($B$54=0,0,B41/$B$54) | F41: Agosto | H41: =SUMIF('Ago 2026'!E5:E500,"Aguardando Pagamento",'Ago 2026'!D5:D500)
A42: Aluguel | B42: =SUMIF('Jan 2026'!H5:H500,$A42,'Jan 2026'!G5:G500)+SUMIF('Fev 2026'!H5:H500,$A42,'Fev 2026'!G5:G500)+SUMIF('Mar 2026'!H5:H500,$A42,'Mar 2026'!G5:G500)+SUMIF('Abr 2026'!H5:H500,$A42,'Abr 2026'!G5:G500)+SUMIF('Mai 2026'!H5:H500,$A42,'Mai 2026'!G5:G500)+SUMIF('Jun 2026'!H5:H500,$A42,'Jun 2026'!G5:G500)+SUMIF('Jul 2026'!H5:H500,$A42,'Jul 2026'!G5:G500)+SUMIF('Ago 2026'!H5:H500,$A42,'Ago 2026'!G5:G500)+SUMIF('Set 2026'!H5:H500,$A42,'Set 2026'!G5:G500)+SUMIF('Out 2026'!H5:H500,$A42,'Out 2026'!G5:G500)+SUMIF('Nov 2026'!H5:H500,$A42,'Nov 2026'!G5:G500)+SUMIF('Dez 2026'!H5:H500,$A42,'Dez 2026'!G5:G500) | C42: =IF($B$54=0,0,B42/$B$54) | F42: Setembro | H42: =SUMIF('Set 2026'!E5:E500,"Aguardando Pagamento",'Set 2026'!D5:D500)
A43: Água, Energia e Internet | B43: =SUMIF('Jan 2026'!H5:H500,$A43,'Jan 2026'!G5:G500)+SUMIF('Fev 2026'!H5:H500,$A43,'Fev 2026'!G5:G500)+SUMIF('Mar 2026'!H5:H500,$A43,'Mar 2026'!G5:G500)+SUMIF('Abr 2026'!H5:H500,$A43,'Abr 2026'!G5:G500)+SUMIF('Mai 2026'!H5:H500,$A43,'Mai 2026'!G5:G500)+SUMIF('Jun 2026'!H5:H500,$A43,'Jun 2026'!G5:G500)+SUMIF('Jul 2026'!H5:H500,$A43,'Jul 2026'!G5:G500)+SUMIF('Ago 2026'!H5:H500,$A43,'Ago 2026'!G5:G500)+SUMIF('Set 2026'!H5:H500,$A43,'Set 2026'!G5:G500)+SUMIF('Out 2026'!H5:H500,$A43,'Out 2026'!G5:G500)+SUMIF('Nov 2026'!H5:H500,$A43,'Nov 2026'!G5:G500)+SUMIF('Dez 2026'!H5:H500,$A43,'Dez 2026'!G5:G500) | C43: =IF($B$54=0,0,B43/$B$54) | F43: Outubro | H43: =SUMIF('Out 2026'!E5:E500,"Aguardando Pagamento",'Out 2026'!D5:D500)
A44: Impostos e Taxas | B44: =SUMIF('Jan 2026'!H5:H500,$A44,'Jan 2026'!G5:G500)+SUMIF('Fev 2026'!H5:H500,$A44,'Fev 2026'!G5:G500)+SUMIF('Mar 2026'!H5:H500,$A44,'Mar 2026'!G5:G500)+SUMIF('Abr 2026'!H5:H500,$A44,'Abr 2026'!G5:G500)+SUMIF('Mai 2026'!H5:H500,$A44,'Mai 2026'!G5:G500)+SUMIF('Jun 2026'!H5:H500,$A44,'Jun 2026'!G5:G500)+SUMIF('Jul 2026'!H5:H500,$A44,'Jul 2026'!G5:G500)+SUMIF('Ago 2026'!H5:H500,$A44,'Ago 2026'!G5:G500)+SUMIF('Set 2026'!H5:H500,$A44,'Set 2026'!G5:G500)+SUMIF('Out 2026'!H5:H500,$A44,'Out 2026'!G5:G500)+SUMIF('Nov 2026'!H5:H500,$A44,'Nov 2026'!G5:G500)+SUMIF('Dez 2026'!H5:H500,$A44,'Dez 2026'!G5:G500) | C44: =IF($B$54=0,0,B44/$B$54) | F44: Novembro | H44: =SUMIF('Nov 2026'!E5:E500,"Aguardando Pagamento",'Nov 2026'!D5:D500)
A45: Tarifas Bancárias e Cartão | B45: =SUMIF('Jan 2026'!H5:H500,$A45,'Jan 2026'!G5:G500)+SUMIF('Fev 2026'!H5:H500,$A45,'Fev 2026'!G5:G500)+SUMIF('Mar 2026'!H5:H500,$A45,'Mar 2026'!G5:G500)+SUMIF('Abr 2026'!H5:H500,$A45,'Abr 2026'!G5:G500)+SUMIF('Mai 2026'!H5:H500,$A45,'Mai 2026'!G5:G500)+SUMIF('Jun 2026'!H5:H500,$A45,'Jun 2026'!G5:G500)+SUMIF('Jul 2026'!H5:H500,$A45,'Jul 2026'!G5:G500)+SUMIF('Ago 2026'!H5:H500,$A45,'Ago 2026'!G5:G500)+SUMIF('Set 2026'!H5:H500,$A45,'Set 2026'!G5:G500)+SUMIF('Out 2026'!H5:H500,$A45,'Out 2026'!G5:G500)+SUMIF('Nov 2026'!H5:H500,$A45,'Nov 2026'!G5:G500)+SUMIF('Dez 2026'!H5:H500,$A45,'Dez 2026'!G5:G500) | C45: =IF($B$54=0,0,B45/$B$54) | F45: Dezembro | H45: =SUMIF('Dez 2026'!E5:E500,"Aguardando Pagamento",'Dez 2026'!D5:D500)
A46: Transporte e Entregas | B46: =SUMIF('Jan 2026'!H5:H500,$A46,'Jan 2026'!G5:G500)+SUMIF('Fev 2026'!H5:H500,$A46,'Fev 2026'!G5:G500)+SUMIF('Mar 2026'!H5:H500,$A46,'Mar 2026'!G5:G500)+SUMIF('Abr 2026'!H5:H500,$A46,'Abr 2026'!G5:G500)+SUMIF('Mai 2026'!H5:H500,$A46,'Mai 2026'!G5:G500)+SUMIF('Jun 2026'!H5:H500,$A46,'Jun 2026'!G5:G500)+SUMIF('Jul 2026'!H5:H500,$A46,'Jul 2026'!G5:G500)+SUMIF('Ago 2026'!H5:H500,$A46,'Ago 2026'!G5:G500)+SUMIF('Set 2026'!H5:H500,$A46,'Set 2026'!G5:G500)+SUMIF('Out 2026'!H5:H500,$A46,'Out 2026'!G5:G500)+SUMIF('Nov 2026'!H5:H500,$A46,'Nov 2026'!G5:G500)+SUMIF('Dez 2026'!H5:H500,$A46,'Dez 2026'!G5:G500) | C46: =IF($B$54=0,0,B46/$B$54) | F46: Total a Receber | H46: =SUM(H41:H45)
A47: Salários, Comissões e Encargos | B47: =SUMIF('Jan 2026'!H5:H500,$A47,'Jan 2026'!G5:G500)+SUMIF('Fev 2026'!H5:H500,$A47,'Fev 2026'!G5:G500)+SUMIF('Mar 2026'!H5:H500,$A47,'Mar 2026'!G5:G500)+SUMIF('Abr 2026'!H5:H500,$A47,'Abr 2026'!G5:G500)+SUMIF('Mai 2026'!H5:H500,$A47,'Mai 2026'!G5:G500)+SUMIF('Jun 2026'!H5:H500,$A47,'Jun 2026'!G5:G500)+SUMIF('Jul 2026'!H5:H500,$A47,'Jul 2026'!G5:G500)+SUMIF('Ago 2026'!H5:H500,$A47,'Ago 2026'!G5:G500)+SUMIF('Set 2026'!H5:H500,$A47,'Set 2026'!G5:G500)+SUMIF('Out 2026'!H5:H500,$A47,'Out 2026'!G5:G500)+SUMIF('Nov 2026'!H5:H500,$A47,'Nov 2026'!G5:G500)+SUMIF('Dez 2026'!H5:H500,$A47,'Dez 2026'!G5:G500) | C47: =IF($B$54=0,0,B47/$B$54)
A48: Contabilidade | B48: =SUMIF('Jan 2026'!H5:H500,$A48,'Jan 2026'!G5:G500)+SUMIF('Fev 2026'!H5:H500,$A48,'Fev 2026'!G5:G500)+SUMIF('Mar 2026'!H5:H500,$A48,'Mar 2026'!G5:G500)+SUMIF('Abr 2026'!H5:H500,$A48,'Abr 2026'!G5:G500)+SUMIF('Mai 2026'!H5:H500,$A48,'Mai 2026'!G5:G500)+SUMIF('Jun 2026'!H5:H500,$A48,'Jun 2026'!G5:G500)+SUMIF('Jul 2026'!H5:H500,$A48,'Jul 2026'!G5:G500)+SUMIF('Ago 2026'!H5:H500,$A48,'Ago 2026'!G5:G500)+SUMIF('Set 2026'!H5:H500,$A48,'Set 2026'!G5:G500)+SUMIF('Out 2026'!H5:H500,$A48,'Out 2026'!G5:G500)+SUMIF('Nov 2026'!H5:H500,$A48,'Nov 2026'!G5:G500)+SUMIF('Dez 2026'!H5:H500,$A48,'Dez 2026'!G5:G500) | C48: =IF($B$54=0,0,B48/$B$54)
A49: Manutenção e Reparos | B49: =SUMIF('Jan 2026'!H5:H500,$A49,'Jan 2026'!G5:G500)+SUMIF('Fev 2026'!H5:H500,$A49,'Fev 2026'!G5:G500)+SUMIF('Mar 2026'!H5:H500,$A49,'Mar 2026'!G5:G500)+SUMIF('Abr 2026'!H5:H500,$A49,'Abr 2026'!G5:G500)+SUMIF('Mai 2026'!H5:H500,$A49,'Mai 2026'!G5:G500)+SUMIF('Jun 2026'!H5:H500,$A49,'Jun 2026'!G5:G500)+SUMIF('Jul 2026'!H5:H500,$A49,'Jul 2026'!G5:G500)+SUMIF('Ago 2026'!H5:H500,$A49,'Ago 2026'!G5:G500)+SUMIF('Set 2026'!H5:H500,$A49,'Set 2026'!G5:G500)+SUMIF('Out 2026'!H5:H500,$A49,'Out 2026'!G5:G500)+SUMIF('Nov 2026'!H5:H500,$A49,'Nov 2026'!G5:G500)+SUMIF('Dez 2026'!H5:H500,$A49,'Dez 2026'!G5:G500) | C49: =IF($B$54=0,0,B49/$B$54)
A50: Material de Limpeza e Escritório | B50: =SUMIF('Jan 2026'!H5:H500,$A50,'Jan 2026'!G5:G500)+SUMIF('Fev 2026'!H5:H500,$A50,'Fev 2026'!G5:G500)+SUMIF('Mar 2026'!H5:H500,$A50,'Mar 2026'!G5:G500)+SUMIF('Abr 2026'!H5:H500,$A50,'Abr 2026'!G5:G500)+SUMIF('Mai 2026'!H5:H500,$A50,'Mai 2026'!G5:G500)+SUMIF('Jun 2026'!H5:H500,$A50,'Jun 2026'!G5:G500)+SUMIF('Jul 2026'!H5:H500,$A50,'Jul 2026'!G5:G500)+SUMIF('Ago 2026'!H5:H500,$A50,'Ago 2026'!G5:G500)+SUMIF('Set 2026'!H5:H500,$A50,'Set 2026'!G5:G500)+SUMIF('Out 2026'!H5:H500,$A50,'Out 2026'!G5:G500)+SUMIF('Nov 2026'!H5:H500,$A50,'Nov 2026'!G5:G500)+SUMIF('Dez 2026'!H5:H500,$A50,'Dez 2026'!G5:G500) | C50: =IF($B$54=0,0,B50/$B$54)
A51: Estornos de Vendas (Cancelamentos) | B51: =SUMIF('Jan 2026'!H5:H500,$A51,'Jan 2026'!G5:G500)+SUMIF('Fev 2026'!H5:H500,$A51,'Fev 2026'!G5:G500)+SUMIF('Mar 2026'!H5:H500,$A51,'Mar 2026'!G5:G500)+SUMIF('Abr 2026'!H5:H500,$A51,'Abr 2026'!G5:G500)+SUMIF('Mai 2026'!H5:H500,$A51,'Mai 2026'!G5:G500)+SUMIF('Jun 2026'!H5:H500,$A51,'Jun 2026'!G5:G500)+SUMIF('Jul 2026'!H5:H500,$A51,'Jul 2026'!G5:G500)+SUMIF('Ago 2026'!H5:H500,$A51,'Ago 2026'!G5:G500)+SUMIF('Set 2026'!H5:H500,$A51,'Set 2026'!G5:G500)+SUMIF('Out 2026'!H5:H500,$A51,'Out 2026'!G5:G500)+SUMIF('Nov 2026'!H5:H500,$A51,'Nov 2026'!G5:G500)+SUMIF('Dez 2026'!H5:H500,$A51,'Dez 2026'!G5:G500) | C51: =IF($B$54=0,0,B51/$B$54)
A52: Outras Despesas | B52: =SUMIF('Jan 2026'!H5:H500,$A52,'Jan 2026'!G5:G500)+SUMIF('Fev 2026'!H5:H500,$A52,'Fev 2026'!G5:G500)+SUMIF('Mar 2026'!H5:H500,$A52,'Mar 2026'!G5:G500)+SUMIF('Abr 2026'!H5:H500,$A52,'Abr 2026'!G5:G500)+SUMIF('Mai 2026'!H5:H500,$A52,'Mai 2026'!G5:G500)+SUMIF('Jun 2026'!H5:H500,$A52,'Jun 2026'!G5:G500)+SUMIF('Jul 2026'!H5:H500,$A52,'Jul 2026'!G5:G500)+SUMIF('Ago 2026'!H5:H500,$A52,'Ago 2026'!G5:G500)+SUMIF('Set 2026'!H5:H500,$A52,'Set 2026'!G5:G500)+SUMIF('Out 2026'!H5:H500,$A52,'Out 2026'!G5:G500)+SUMIF('Nov 2026'!H5:H500,$A52,'Nov 2026'!G5:G500)+SUMIF('Dez 2026'!H5:H500,$A52,'Dez 2026'!G5:G500) | C52: =IF($B$54=0,0,B52/$B$54)
A53: Pro Labore Edilânia | B53: =SUMIF('Jan 2026'!H5:H500,$A53,'Jan 2026'!G5:G500)+SUMIF('Fev 2026'!H5:H500,$A53,'Fev 2026'!G5:G500)+SUMIF('Mar 2026'!H5:H500,$A53,'Mar 2026'!G5:G500)+SUMIF('Abr 2026'!H5:H500,$A53,'Abr 2026'!G5:G500)+SUMIF('Mai 2026'!H5:H500,$A53,'Mai 2026'!G5:G500)+SUMIF('Jun 2026'!H5:H500,$A53,'Jun 2026'!G5:G500)+SUMIF('Jul 2026'!H5:H500,$A53,'Jul 2026'!G5:G500)+SUMIF('Ago 2026'!H5:H500,$A53,'Ago 2026'!G5:G500)+SUMIF('Set 2026'!H5:H500,$A53,'Set 2026'!G5:G500)+SUMIF('Out 2026'!H5:H500,$A53,'Out 2026'!G5:G500)+SUMIF('Nov 2026'!H5:H500,$A53,'Nov 2026'!G5:G500)+SUMIF('Dez 2026'!H5:H500,$A53,'Dez 2026'!G5:G500) | C53: =IF($B$54=0,0,B53/$B$54)
A54: Total | B54: =SUM(B41:B52) | C54: 1
A56: Top 15 Produtos Mais Vendidos (Jan–Jul/2026, agregado — sem detalhamento por mês/cliente)
A57: Código | B57: Descrição | C57: Qtd. Vendida | D57: Nº Vendas | E57: Total (R$)
A58: 51750 | B58: REFIL ORIGINAL EVEREST | C58: 382 | D58: 285 | E58: 48297.42
A59: 1013A | B59: REFIL PRO LIFE ESPECIAL OC | C59: 97 | D59: 91 | E59: 13379.01
A60: 51606 | B60: PURIFICADOR DE AGUA EVEREST STAR 220V/60HZ BRANCO | C60: 7 | D60: 7 | E60: 9322
A61: 51624 | B61: PURIFICADOR DE AGUA EVEREST PLUS 220V/60HZ PRATA | C61: 4 | D61: 4 | E61: 5839.56
A62: 1100A | B62: REFIL IBBL/PREC+3 | C62: 42 | D62: 5 | E62: 5800
A63: 51679 | B63: PURIFICADOR DE AGUA EVEREST FIT 220V/60HZ BRANCO | C63: 4 | D63: 4 | E63: 5296
A64: 51647 | B64: PURIFICADOR DE AGUA EVEREST SLIM 220V/60HZ BRANCO | C64: 4 | D64: 4 | E64: 5294
A65: 51750 | B65: Filtro para bebedouro Soft by everest 2 em 1 | C65: 91 | D65: 12 | E65: 5241.91
A66: 51810 | B66: PRE FILTRO | C66: 87 | D66: 78 | E66: 5051.19
A67: 51669 | B67: PURIFICADOR DE AGUA EVEREST PLUS 220V/60HZ BRANCO | C67: 3 | D67: 3 | E67: 4496
A68: 51639 | B68: PURIFICADOR DE AGUA EVEREST FIT 220V/60HZ PRETO | C68: 3 | D68: 3 | E68: 4346
A69: 51618 | B69: PURIFICADOR DE AGUA EVEREST SLIM 220V/60HZ PRATA | C69: 3 | D69: 3 | E69: 4246
... A72: 51622 | B72: PURIFICADOR DE AGUA EVEREST FIT 220V/60HZ PRATA | C72: 3 | D72: 3 | E72: 4098

Sheet DRE Simplificado
A1: DRE SIMPLIFICADO — 2026
A2: Receita − Custos Variáveis = Margem de Contribuição. Margem − Custos Fixos = Resultado da loja. Resultado da loja − Pró-labore da Edilânia = SOBRA FINAL. Puxa tudo das abas mensais, sem digitação.
A3: ← Início | B3: =SUM(B38:M38) | C3: ← meses já fechados (o mês em andamento fica fora); é a base da coluna "Média/mês"
A4: Conta | B4: Janeiro | C4: Fevereiro | D4: Março | E4: Abril | F4: Maio | G4: Junho | H4: Julho | I4: Agosto | J4: Setembro | K4: Outubro | L4: Novembro | M4: Dezembro | N4: Total | O4: Média/mês
A5: RECEITA LÍQUIDA (vendas recebidas) | B5: =SUMIF('Jan 2026'!A5:A500,"<>",'Jan 2026'!D5:D500)-SUMIF('Jan 2026'!A5:A500,"<>",'Jan 2026'!F5:F500)-'Jan 2026'!T5 | C5: =SUMIF('Fev 2026'!A5:A500,"<>",'Fev 2026'!D5:D500)-SUMIF('Fev 2026'!A5:A500,"<>",'Fev 2026'!F5:F500)-'Fev 2026'!T5 | D5: =SUMIF('Mar 2026'!A5:A500,"<>",'Mar 2026'!D5:D500)-SUMIF('Mar 2026'!A5:A500,"<>",'Mar 2026'!F5:F500)-'Mar 2026'!T5 | E5: =SUMIF('Abr 2026'!A5:A500,"<>",'Abr 2026'!D5:D500)-SUMIF('Abr 2026'!A5:A500,"<>",'Abr 2026'!F5:F500)-'Abr 2026'!T5 | F5: =SUMIF('Mai 2026'!A5:A500,"<>",'Mai 2026'!D5:D500)-SUMIF('Mai 2026'!A5:A500,"<>",'Mai 2026'!F5:F500)-'Mai 2026'!T5 | G5: =SUMIF('Jun 2026'!A5:A500,"<>",'Jun 2026'!D5:D500)-SUMIF('Jun 2026'!A5:A500,"<>",'Jun 2026'!F5:F500)-'Jun 2026'!T5 | H5: =SUMIF('Jul 2026'!A5:A500,"<>",'Jul 2026'!D5:D500)-SUMIF('Jul 2026'!A5:A500,"<>",'Jul 2026'!F5:F500)-'Jul 2026'!T5 | I5: =SUMIF('Ago 2026'!E5:E500,"<>",'Ago 2026'!D5:D500)-SUMIF('Ago 2026'!E5:E500,"<>",'Ago 2026'!F5:F500)-'Ago 2026'!T5 | J5: =SUMIF('Set 2026'!E5:E500,"<>",'Set 2026'!D5:D500)-SUMIF('Set 2026'!E5:E500,"<>",'Set 2026'!F5:F500)-'Set 2026'!T5 | K5: =SUMIF('Out 2026'!E5:E500,"<>",'Out 2026'!D5:D500)-SUMIF('Out 2026'!E5:E500,"<>",'Out 2026'!F5:F500)-'Out 2026'!T5 | L5: =SUMIF('Nov 2026'!E5:E500,"<>",'Nov 2026'!D5:D500)-SUMIF('Nov 2026'!E5:E500,"<>",'Nov 2026'!F5:F500)-'Nov 2026'!T5 | M5: =SUMIF('Dez 2026'!E5:E500,"<>",'Dez 2026'!D5:D500)-SUMIF('Dez 2026'!E5:E500,"<>",'Dez 2026'!F5:F500)-'Dez 2026'!T5 | N5: =SUM(B5:M5) | O5: =IF($B$3=0,0,SUMPRODUCT(B5:M5,$B$38:$M$38)/$B$3)
A6: (−) Fornecedores / Mercadoria | B6: ='Jan 2026'!L5 | C6: ='Fev 2026'!L5 | D6: ='Mar 2026'!L5 | E6: ='Abr 2026'!L5 | F6: ='Mai 2026'!L5 | G6: ='Jun 2026'!L5 | H6: ='Jul 2026'!L5 | I6: ='Ago 2026'!L5 | J6: ='Set 2026'!L5 | K6: ='Out 2026'!L5 | L6: ='Nov 2026'!L5 | M6: ='Dez 2026'!L5 | N6: =SUM(B6:M6) | O6: =IF($B$3=0,0,SUMPRODUCT(B6:M6,$B$38:$M$38)/$B$3)
A7: (−) Impostos e Taxas | B7: ='Jan 2026'!L8 | C7: ='Fev 2026'!L8 | D7: ='Mar 2026'!L8 | E7: ='Abr 2026'!L8 | F7: ='Mai 2026'!L8 | G7: ='Jun 2026'!L8 | H7: ='Jul 2026'!L8 | I7: ='Ago 2026'!L8 | J7: ='Set 2026'!L8 | K7: ='Out 2026'!L8 | L7: ='Nov 2026'!L8 | M7: ='Dez 2026'!L8 | N7: =SUM(B7:M7) | O7: =IF($B$3=0,0,SUMPRODUCT(B7:M7,$B$38:$M$38)/$B$3)
A8: (−) Transporte e Entregas (frete, gasolina, moto táxi) | B8: ='Jan 2026'!L10-B21 | C8: ='Fev 2026'!L10-C21 | D8: ='Mar 2026'!L10-D21 | E8: ='Abr 2026'!L10-E21 | F8: ='Mai 2026'!L10-F21 | G8: ='Jun 2026'!L10-G21 | H8: ='Jul 2026'!L10-H21 | I8: ='Ago 2026'!L10-I21 | J8: ='Set 2026'!L10-J21 | K8: ='Out 2026'!L10-K21 | L8: ='Nov 2026'!L10-L21 | M8: ='Dez 2026'!L10-M21 | N8: =SUM(B8:M8) | O8: =IF($B$3=0,0,SUMPRODUCT(B8:M8,$B$38:$M$38)/$B$3)
A9: (−) Comissões (Wiliam — por troca/instalação) | B9: =SUMIFS('Jan 2026'!G5:G500,'Jan 2026'!B5:B500,"Comissão*",'Jan 2026'!H5:H500,"Salários, Comissões e Encargos") | C9: =SUMIFS('Fev 2026'!G5:G500,'Fev 2026'!B5:B500,"Comissão*",'Fev 2026'!H5:H500,"Salários, Comissões e Encargos") | D9: =SUMIFS('Mar 2026'!G5:G500,'Mar 2026'!B5:B500,"Comissão*",'Mar 2026'!H5:H500,"Salários, Comissões e Encargos") | E9: =SUMIFS('Abr 2026'!G5:G500,'Abr 2026'!B5:B500,"Comissão*",'Abr 2026'!H5:H500,"Salários, Comissões e Encargos") | F9: =SUMIFS('Mai 2026'!G5:G500,'Mai 2026'!B5:B500,"Comissão*",'Mai 2026'!H5:H500,"Salários, Comissões e Encargos") | G9: =SUMIFS('Jun 2026'!G5:G500,'Jun 2026'!B5:B500,"Comissão*",'Jun 2026'!H5:H500,"Salários, Comissões e Encargos") | H9: =SUMIFS('Jul 2026'!G5:G500,'Jul 2026'!B5:B500,"Comissão*",'Jul 2026'!H5:H500,"Salários, Comissões e Encargos") | I9: =SUMIFS('Ago 2026'!G5:G500,'Ago 2026'!B5:B500,"Comissão*",'Ago 2026'!H5:H500,"Salários, Comissões e Encargos") | J9: =SUMIFS('Set 2026'!G5:G500,'Set 2026'!B5:B500,"Comissão*",'Set 2026'!H5:H500,"Salários, Comissões e Encargos") | K9: =SUMIFS('Out 2026'!G5:G500,'Out 2026'!B5:B500,"Comissão*",'Out 2026'!H5:H500,"Salários, Comissões e Encargos") | L9: =SUMIFS('Nov 2026'!G5:G500,'Nov 2026'!B5:B500,"Comissão*",'Nov 2026'!H5:H500,"Salários, Comissões e Encargos") | M9: =SUMIFS('Dez 2026'!G5:G500,'Dez 2026'!B5:B500,"Comissão*",'Dez 2026'!H5:H500,"Salários, Comissões e Encargos") | N9: =SUM(B9:M9) | O9: =IF($B$3=0,0,SUMPRODUCT(B9:M9,$B$38:$M$38)/$B$3)
A10: (=) CUSTOS VARIÁVEIS | B10: =SUM(B6:B9) | C10: =SUM(C6:C9) | D10: =SUM(D6:D9) | E10: =SUM(E6:E9) | F10: =SUM(F6:F9) | G10: =SUM(G6:G9) | H10: =SUM(H6:H9) | I10: =SUM(I6:I9) | ... M10: =SUM(M6:M9) | N10: =SUM(B10:M10) | O10: =IF($B$3=0,0,SUMPRODUCT(B10:M10,$B$38:$M$38)/$B$3)
A11: (=) MARGEM DE CONTRIBUIÇÃO | B11: =B5-B10 | C11: =C5-C10 | D11: =D5-D10 | E11: =E5-E10 | F11: =F5-F10 | G11: =G5-G10 | H11: =H5-H10 | I11: =I5-I10 | ... M11: =M5-M10 | N11: =SUM(B11:M11) | O11: =IF($B$3=0,0,SUMPRODUCT(B11:M11,$B$38:$M$38)/$B$3)
A12: Margem de Contribuição (%) | B12: =IF(B5=0,"",B11/B5) | C12: =IF(C5=0,"",C11/C5) | D12: =IF(D5=0,"",D11/D5) | E12: =IF(E5=0,"",E11/E5) | F12: =IF(F5=0,"",F11/F5) | G12: =IF(G5=0,"",G11/G5) | H12: =IF(H5=0,"",H11/H5) | I12: =IF(I5=0,"",I11/I5) | ... O12: =IF(O5=0,"",O11/O5)
A13: (−) Aluguel | B13: ='Jan 2026'!L6 | C13: ='Fev 2026'!L6 | D13: ='Mar 2026'!L6 | E13: ='Abr 2026'!L6 | F13: ='Mai 2026'!L6 | G13: ='Jun 2026'!L6 | H13: ='Jul 2026'!L6 | I13: ='Ago 2026'!L6 | J13: ='Set 2026'!L6 | K13: ='Out 2026'!L6 | L13: ='Nov 2026'!L6 | M13: ='Dez 2026'!L6 | N13: =SUM(B13:M13) | O13: =IF($B$3=0,0,SUMPRODUCT(B13:M13,$B$38:$M$38)/$B$3)
A14: (−) Água, Energia e Internet | B14: ='Jan 2026'!L7 | C14: ='Fev 2026'!L7 | D14: ='Mar 2026'!L7 | E14: ='Abr 2026'!L7 | F14: ='Mai 2026'!L7 | G14: ='Jun 2026'!L7 | H14: ='Jul 2026'!L7 | I14: ='Ago 2026'!L7 | J14: ='Set 2026'!L7 | K14: ='Out 2026'!L7 | L14: ='Nov 2026'!L7 | M14: ='Dez 2026'!L7 | N14: =SUM(B14:M14) | O14: =IF($B$3=0,0,SUMPRODUCT(B14:M14,$B$38:$M$38)/$B$3)
A15: (−) Tarifas Bancárias e Cartão | B15: ='Jan 2026'!L9 | C15: ='Fev 2026'!L9 | D15: ='Mar 2026'!L9 | E15: ='Abr 2026'!L9 | F15: ='Mai 2026'!L9 | G15: ='Jun 2026'!L9 | H15: ='Jul 2026'!L9 | I15: ='Ago 2026'!L9 | J15: ='Set 2026'!L9 | K15: ='Out 2026'!L9 | L15: ='Nov 2026'!L9 | M15: ='Dez 2026'!L9 | N15: =SUM(B15:M15) | O15: =IF($B$3=0,0,SUMPRODUCT(B15:M15,$B$38:$M$38)/$B$3)
A16: (−) Salários e Encargos (sem as comissões) | B16: ='Jan 2026'!L11-B9 | C16: ='Fev 2026'!L11-C9 | D16: ='Mar 2026'!L11-D9 | E16: ='Abr 2026'!L11-E9 | F16: ='Mai 2026'!L11-F9 | G16: ='Jun 2026'!L11-G9 | H16: ='Jul 2026'!L11-H9 | I16: ='Ago 2026'!L11-I9 | J16: ='Set 2026'!L11-J9 | K16: ='Out 2026'!L11-K9 | L16: ='Nov 2026'!L11-L9 | M16: ='Dez 2026'!L11-M9 | N16: =SUM(B16:M16) | O16: =IF($B$3=0,0,SUMPRODUCT(B16:M16,$B$38:$M$38)/$B$3)
A17: (−) Contabilidade | B17: ='Jan 2026'!L12 | C17: ='Fev 2026'!L12 | D17: ='Mar 2026'!L12 | E17: ='Abr 2026'!L12 | F17: ='Mai 2026'!L12 | G17: ='Jun 2026'!L12 | H17: ='Jul 2026'!L12 | I17: ='Ago 2026'!L12 | J17: ='Set 2026'!L12 | K17: ='Out 2026'!L12 | L17: ='Nov 2026'!L12 | M17: ='Dez 2026'!L12 | N17: =SUM(B17:M17) | O17: =IF($B$3=0,0,SUMPRODUCT(B17:M17,$B$38:$M$38)/$B$3)
A18: (−) Manutenção e Reparos | B18: ='Jan 2026'!L13 | C18: ='Fev 2026'!L13 | D18: ='Mar 2026'!L13 | E18: ='Abr 2026'!L13 | F18: ='Mai 2026'!L13 | G18: ='Jun 2026'!L13 | H18: ='Jul 2026'!L13 | I18: ='Ago 2026'!L13 | J18: ='Set 2026'!L13 | K18: ='Out 2026'!L13 | L18: ='Nov 2026'!L13 | M18: ='Dez 2026'!L13 | N18: =SUM(B18:M18) | O18: =IF($B$3=0,0,SUMPRODUCT(B18:M18,$B$38:$M$38)/$B$3)
A19: (−) Material de Limpeza e Escritório | B19: ='Jan 2026'!L14 | C19: ='Fev 2026'!L14 | D19: ='Mar 2026'!L14 | E19: ='Abr 2026'!L14 | F19: ='Mai 2026'!L14 | G19: ='Jun 2026'!L14 | H19: ='Jul 2026'!L14 | I19: ='Ago 2026'!L14 | J19: ='Set 2026'!L14 | K19: ='Out 2026'!L14 | L19: ='Nov 2026'!L14 | M19: ='Dez 2026'!L14 | N19: =SUM(B19:M19) | O19: =IF($B$3=0,0,SUMPRODUCT(B19:M19,$B$38:$M$38)/$B$3)
A20: (−) Estornos de Vendas (Cancelamentos) | B20: ='Jan 2026'!L15 | C20: ='Fev 2026'!L15 | D20: ='Mar 2026'!L15 | E20: ='Abr 2026'!L15 | F20: ='Mai 2026'!L15 | G20: ='Jun 2026'!L15 | H20: ='Jul 2026'!L15 | I20: ='Ago 2026'!L15 | J20: ='Set 2026'!L15 | K20: ='Out 2026'!L15 | L20: ='Nov 2026'!L15 | M20: ='Dez 2026'!L15 | N20: =SUM(B20:M20) | O20: =IF($B$3=0,0,SUMPRODUCT(B20:M20,$B$38:$M$38)/$B$3)
A21: (−) Estacionamento (dentro de Transporte e Entregas) | B21: =SUMIF('Jan 2026'!B5:B500,"Estacionamento*",'Jan 2026'!G5:G500) | C21: =SUMIF('Fev 2026'!B5:B500,"Estacionamento*",'Fev 2026'!G5:G500) | D21: =SUMIF('Mar 2026'!B5:B500,"Estacionamento*",'Mar 2026'!G5:G500) | E21: =SUMIF('Abr 2026'!B5:B500,"Estacionamento*",'Abr 2026'!G5:G500) | F21: =SUMIF('Mai 2026'!B5:B500,"Estacionamento*",'Mai 2026'!G5:G500) | G21: =SUMIF('Jun 2026'!B5:B500,"Estacionamento*",'Jun 2026'!G5:G500) | H21: =SUMIF('Jul 2026'!B5:B500,"Estacionamento*",'Jul 2026'!G5:G500) | I21: =SUMIF('Ago 2026'!B5:B500,"Estacionamento*",'Ago 2026'!G5:G500) | J21: =SUMIF('Set 2026'!B5:B500,"Estacionamento*",'Set 2026'!G5:G500) | K21: =SUMIF('Out 2026'!B5:B500,"Estacionamento*",'Out 2026'!G5:G500) | L21: =SUMIF('Nov 2026'!B5:B500,"Estacionamento*",'Nov 2026'!G5:G500) | M21: =SUMIF('Dez 2026'!B5:B500,"Estacionamento*",'Dez 2026'!G5:G500) | N21: =SUM(B21:M21) | O21: =IF($B$3=0,0,SUMPRODUCT(B21:M21,$B$38:$M$38)/$B$3)
A22: (−) Outras Despesas | B22: ='Jan 2026'!L16 | C22: ='Fev 2026'!L16 | D22: ='Mar 2026'!L16 | E22: ='Abr 2026'!L16 | F22: ='Mai 2026'!L16 | G22: ='Jun 2026'!L16 | H22: ='Jul 2026'!L16 | I22: ='Ago 2026'!L16 | J22: ='Set 2026'!L16 | K22: ='Out 2026'!L16 | L22: ='Nov 2026'!L16 | M22: ='Dez 2026'!L16 | N22: =SUM(B22:M22) | O22: =IF($B$3=0,0,SUMPRODUCT(B22:M22,$B$38:$M$38)/$B$3)
A23: (=) CUSTOS FIXOS | B23: =SUM(B13:B22) | C23: =SUM(C13:C22) | D23: =SUM(D13:D22) | E23: =SUM(E13:E22) | F23: =SUM(F13:F22) | G23: =SUM(G13:G22) | H23: =SUM(H13:H22) | I23: =SUM(I13:I22) | ... M23: =SUM(M13:M22) | N23: =SUM(B23:M23) | O23: =IF($B$3=0,0,SUMPRODUCT(B23:M23,$B$38:$M$38)/$B$3)
A24: (=) RESULTADO DA LOJA (antes do pró-labore) | B24: =B11-B23 | C24: =C11-C23 | D24: =D11-D23 | E24: =E11-E23 | F24: =F11-F23 | G24: =G11-G23 | H24: =H11-H23 | I24: =I11-I23 | ... M24: =M11-M23 | N24: =SUM(B24:M24) | O24: =IF($B$3=0,0,SUMPRODUCT(B24:M24,$B$38:$M$38)/$B$3)
A25: Margem Líquida (%) | B25: =IF(B5=0,"",B24/B5) | C25: =IF(C5=0,"",C24/C5) | D25: =IF(D5=0,"",D24/D5) | E25: =IF(E5=0,"",E24/E5) | F25: =IF(F5=0,"",F24/F5) | G25: =IF(G5=0,"",G24/G5) | H25: =IF(H5=0,"",H24/H5) | I25: =IF(I5=0,"",I24/I5) | ... O25: =IF(O5=0,"",O24/O5)
A26: (−) Pró-labore Edilânia (tudo o que ela gastou do dinheiro da loja) | B26: ='Jan 2026'!L17 | C26: ='Fev 2026'!L17 | D26: ='Mar 2026'!L17 | E26: ='Abr 2026'!L17 | F26: ='Mai 2026'!L17 | G26: ='Jun 2026'!L17 | H26: ='Jul 2026'!L17 | I26: ='Ago 2026'!L17 | J26: ='Set 2026'!L17 | K26: ='Out 2026'!L17 | L26: ='Nov 2026'!L17 | M26: ='Dez 2026'!L17 | N26: =SUM(B26:M26) | O26: =IF($B$3=0,0,SUMPRODUCT(B26:M26,$B$38:$M$38)/$B$3)
A27: (=) SOBRA FINAL (depois do pró-labore) | B27: =B24-B26 | C27: =C24-C26 | D27: =D24-D26 | E27: =E24-E26 | F27: =F24-F26 | G27: =G24-G26 | H27: =H24-H26 | I27: =I24-I26 | ... M27: =M24-M26 | N27: =SUM(B27:M27) | O27: =IF($B$3=0,0,SUMPRODUCT(B27:M27,$B$38:$M$38)/$B$3)
A28: Combinado com ela: sobrou (+) ou passou (−) do combinado | B28: =IF(B5=0,"",'Ponto de Equilíbrio'!$B$10-B26) | C28: =IF(C5=0,"",'Ponto de Equilíbrio'!$B$10-C26) | D28: =IF(D5=0,"",'Ponto de Equilíbrio'!$B$10-D26) | E28: =IF(E5=0,"",'Ponto de Equilíbrio'!$B$10-E26) | F28: =IF(F5=0,"",'Ponto de Equilíbrio'!$B$10-F26) | G28: =IF(G5=0,"",'Ponto de Equilíbrio'!$B$10-G26) | H28: =IF(H5=0,"",'Ponto de Equilíbrio'!$B$10-H26) | I28: =IF(I5=0,"",'Ponto de Equilíbrio'!$B$10-I26) | ... M28: =IF(M5=0,"",'Ponto de Equilíbrio'!$B$10-M26) | N28: =SUM(B28:M28) | O28: =IF($B$3=0,0,SUMPRODUCT(B28:M28,$B$38:$M$38)/$B$3)
A30: MEMÓRIA (não entra no resultado)
A31: Despesas da loja pagas com Capital de Giro (BB) — dívida a devolver | B31: ='Jan 2026'!L19 | C31: ='Fev 2026'!L19 | D31: ='Mar 2026'!L19 | E31: ='Abr 2026'!L19 | F31: ='Mai 2026'!L19 | G31: ='Jun 2026'!L19 | H31: ='Jul 2026'!L19 | I31: ='Ago 2026'!L19 | J31: ='Set 2026'!L19 | K31: ='Out 2026'!L19 | L31: ='Nov 2026'!L19 | M31: ='Dez 2026'!L19 | N31: =SUM(B31:M31) | O31: =IF($B$3=0,0,SUMPRODUCT(B31:M31,$B$38:$M$38)/$B$3)
A33: Custos Variáveis = sobem/descem com o volume vendido: mercadoria, imposto sobre faturamento (DAS), transporte ligado ao serviço e as comissões do Wiliam (só existem quando tem troca/instalação). Custos Fixos = o que a loja paga mesmo vendendo pouco (aluguel, energia, salários, contabilidade, tarifas e o estacionamento, contratado no mês).
A34: A Receita de Ago–Dez já está líquida: descontadas as taxas de máquina e as vendas ainda não recebidas (A Receber).
A35: A "Média/mês" divide só pelos meses JÁ FECHADOS (linha 38 = 1). O mês em andamento fica fora da média até terminar, para um mês pela metade não puxar o número para baixo.
A36: ATENÇÃO — este DRE é por COMPETÊNCIA: considera a despesa no mês em que ela aconteceu, mesmo que tenha sido paga pelo Capital de Giro do BB. Por isso o Resultado aqui é menor que o cartão SALDO da aba do mês e que o Lucro do Dashboard, que são CAIXA puro. A diferença está na linha 28.
A37: PRÓ-LABORE: tudo o que a Edilânia gasta do dinheiro da loja (contas da casa, Pix pessoais, mercado, diarista...) é o pró-labore dela. O combinado é o valor da célula B10 da aba "Ponto de Equilíbrio" (R$ 4.000,00/mês desde 05/10/2026). A linha 28 mostra, mês a mês, se sobrou ou se passou do combinado.
A38: Entra na média? (1 = mês já fechado e com movimento) | B38: =IF(AND(B5>0,1<IF(YEAR(TODAY())>2026,13,MONTH(TODAY()))),1,0) | C38: =IF(AND(C5>0,2<IF(YEAR(TODAY())>2026,13,MONTH(TODAY()))),1,0) | D38: =IF(AND(D5>0,3<IF(YEAR(TODAY())>2026,13,MONTH(TODAY()))),1,0) | E38: =IF(AND(E5>0,4<IF(YEAR(TODAY())>2026,13,MONTH(TODAY()))),1,0) | F38: =IF(AND(F5>0,5<IF(YEAR(TODAY())>2026,13,MONTH(TODAY()))),1,0) | G38: =IF(AND(G5>0,6<IF(YEAR(TODAY())>2026,13,MONTH(TODAY()))),1,0) | H38: =IF(AND(H5>0,7<IF(YEAR(TODAY())>2026,13,MONTH(TODAY()))),1,0) | I38: =IF(AND(I5>0,8<IF(YEAR(TODAY())>2026,13,MONTH(TODAY()))),1,0) | J38: =IF(AND(J5>0,9<IF(YEAR(TODAY())>2026,13,MONTH(TODAY()))),1,0) | K38: =IF(AND(K5>0,10<IF(YEAR(TODAY())>2026,13,MONTH(TODAY()))),1,0) | L38: =IF(AND(L5>0,11<IF(YEAR(TODAY())>2026,13,MONTH(TODAY()))),1,0) | M38: =IF(AND(M5>0,12<IF(YEAR(TODAY())>2026,13,MONTH(TODAY()))),1,0)

Sheet Contas a Pagar e Receber
A1: CONTAS A PAGAR E A RECEBER
A2: Compromissos em aberto e vendas ainda não recebidas. "Dias em Atraso" é calculado sozinho. O total a receber é puxado automaticamente das abas dos meses — não precisa somar à mão.
A3: ← Início
A4: TOTAL A PAGAR (EM ABERTO) | C4: TOTAL A RECEBER (AUTOMÁTICO) | E4: SALDO (RECEBER − PAGAR)
A5: =D97 | C5: ='Jan 2026'!T5+'Fev 2026'!T5+'Mar 2026'!T5+'Abr 2026'!T5+'Mai 2026'!T5+'Jun 2026'!T5+'Jul 2026'!T5+'Ago 2026'!T5+'Set 2026'!T5+'Out 2026'!T5+'Nov 2026'!T5+'Dez 2026'!T5 | E5: =C5-A5
A9: CONTAS A PAGAR — o que a loja ainda deve
A10: Fornecedor / Pessoa | B10: Descrição | C10: Vencimento | D10: Valor (R$) | E10: Status | F10: Dias em Atraso | G10: Observações
A11: Capital de Giro (BB) — saldo a devolver à reserva | B11: Dinheiro da reserva (Banco do Brasil) usado para pagar contas da loja | D11: ='Capital de Giro (BB)'!C5 | E11: Pendente | F11: =IF(OR($E11="Pago",$C11=""),"",MAX(0,TODAY()-$C11)) | G11: Detalhe na aba Capital de Giro (BB). Ago/2026 quitado em 31/08/2026. Em 30/09/2026 a reserva pagou R$ 3.272,00 à Knox (2 bebedouros industriais) — a devolver.
A12: Eversoft Ind e Com de Plasticos Ltda | B12: Mercadoria — doc. 72153 (emissão 02/04/2026) | C12: 46264 | D12: 878.93 | E12: Pago | F12: =IF(OR($E12="Pago",$C12=""),"",MAX(0,TODAY()-$C12)) | G12: Categoria: Fornecedores / Mercadoria. Pago em 31/08/2026 — lançado em "Ago 2026" como "Eversoft" (R$ 878,93).
A13: Empresa Baiana de Aguas e Saneamento SA (Embasa) | B13: Conta de água — despesa pessoal do dono (não é da loja) | C13: 46266 | D13: 50.08 | E13: Pago | F13: =IF(OR($E13="Pago",$C13=""),"",MAX(0,TODAY()-$C13)) | G13: Categoria: Pro Labore Edilânia. Pago em 01/09/2026 — lançado em Set 2026 como "Conta de Água Adriano".
A14: Vitoria Maria F Santos | B14: Aluguel da loja — setembro/2026 | C14: 46266 | D14: 880 | E14: Pago | F14: =IF(OR($E14="Pago",$C14=""),"",MAX(0,TODAY()-$C14)) | G14: Categoria: Aluguel. Pago em 01/09/2026 — lançado em Set 2026 como "Vitoria Maria F Santos".
A15: Wiliam Pinto Bispo | B15: Salário + comissões | C15: 46266 | D15: 1571.32 | E15: Pago | F15: =IF(OR($E15="Pago",$C15=""),"",MAX(0,TODAY()-$C15)) | G15: Categoria: Salários, Comissões e Encargos. Pago em 31/08/2026 (segunda-feira) — lançado em "Ago 2026" como "Salário Wiliam".
A16: Erick Feitosa Evangelista | B16: Salário do estagiário | C16: 46266 | D16: 600 | E16: Pago | F16: =IF(OR($E16="Pago",$C16=""),"",MAX(0,TODAY()-$C16)) | G16: Categoria: Salários, Comissões e Encargos. Pago em 31/08/2026 — lançado em "Ago 2026" como "Salário Erick (Estagiário)".
A17: Filtros Planeta Agua Ind e Com Ltda | B17: Mercadoria — doc. 131997 (emissão 08/07/2026) | C17: 46267 | D17: 1385.85 | E17: Pago | F17: =IF(OR($E17="Pago",$C17=""),"",MAX(0,TODAY()-$C17)) | G17: Categoria: Fornecedores / Mercadoria. Pago em 02/09/2026 — lançado em "Set 2026" como "Filtros Planeta Água".
A18: Everest Refrigeracao e Industria | B18: Mercadoria — doc. 374271 (emissão 06/04/2026) | C18: 46268 | D18: 706.67 | E18: Pago | F18: =IF(OR($E18="Pago",$C18=""),"",MAX(0,TODAY()-$C18)) | G18: Categoria: Fornecedores / Mercadoria. Pago em 03/09/2026 — lançado em "Set 2026" como "Everest Refrigeração".
A19: Eversoft Ind e Com de Plasticos Ltda | B19: Mercadoria — doc. 72869 (emissão 07/05/2026) | C19: 46269 | D19: 980.83 | E19: Pago | F19: =IF(OR($E19="Pago",$C19=""),"",MAX(0,TODAY()-$C19)) | G19: Categoria: Fornecedores / Mercadoria. Pago em 04/09/2026 pelo Banco do Nordeste (DOC 5301) — lançado em "Set 2026" como "Eversoft" (R$ 980,83).
A20: Neoenergia Coelba | B20: Energia elétrica da loja — REF 08/2026 (fatura em nome de Vitória Maria / Planeta Água) | C20: 46273 | D20: 150.06 | E20: Pago | F20: =IF(OR($E20="Pago",$C20=""),"",MAX(0,TODAY()-$C20)) | G20: Categoria: Água, Energia e Internet. Pago em 08/09/2026 — lançado em Set 2026 como "Conta de Energia Loja".
A21: Eversoft Ind e Com de Plasticos Ltda | B21: Mercadoria — doc. 73636 (emissão 10/06/2026) | C21: 46273 | D21: 878.92 | E21: Pago | F21: =IF(OR($E21="Pago",$C21=""),"",MAX(0,TODAY()-$C21)) | G21: Categoria: Fornecedores / Mercadoria. Pago em 08/09/2026 — lançado em Set 2026 como "Eversoft".
A22: Filtros Planeta Agua Ind e Com Ltda | B22: Mercadoria — doc. 133138/1 (emissão 12/08/2026) | C22: 46274 | D22: 649.83 | E22: Pago | F22: =IF(OR($E22="Pago",$C22=""),"",MAX(0,TODAY()-$C22)) | G22: Categoria: Fornecedores / Mercadoria. Boleto Itaú 341-7, nosso número 109/00257849-8. Pago em 09/09/2026 — lançado em "Set 2026" como "Filtros Planeta Água".
A23: Sindicato dos Empregados no Comércio de Jacobina | B23: Contribuição assistencial — competência junho/2026 | C23: 46275 | D23: 59.5 | E23: Pago | F23: =IF(OR($E23="Pago",$C23=""),"",MAX(0,TODAY()-$C23)) | G23: Categoria: Impostos e Taxas. Pago em 09/09/2026 (antecipado, venc. 10/09) — lançado em "Set 2026" como "Sindicato dos Empregados no Comércio de Jacobina".
... A94: Proxxima Telecomunicacoes S.A. | B94: Internet da loja — plano Turbinados 700 MB, contrato 578646 | C94: 46310 | D94: 69.99 | E94: Pago | F94: =IF(OR($E94="Pago",$C94=""),"",MAX(0,TODAY()-$C94)) | G94: Categoria quando pagar: Água, Energia e Internet. Fatura FAT26091809010676 (emissão 18/09/2026), NFCom 410732, boleto Bradesco 237. Linha digitável 23790.49303 90000.443094 56025.103005 3 16000000006999. Nosso número 09000044309567. Após o vencimento: multa de 2% + mora de 1,20% a.m. A fatura sai em nome do sócio, mas o serviço é da loja. Pago em 15/10/2026 — lançado em "Out 2026" como "Proxxima Telecomunicações".
A95: TOTAL A PAGAR — COM BOLETO EM MÃOS | D95: =SUMIF(E11:E94,"Pendente",D11:D94)
A96: PREVISTO — compromisso certo que ainda não está documentado | D96: =SUMIF(E11:E94,"Previsto",D11:D94)
A97: TOTAL GERAL A PAGAR (boletos + previsão) | D97: =D95+D96
A99: CONTAS A RECEBER — vendas feitas e ainda não pagas
A100: Espelho das vendas marcadas como "Aguardando Pagamento" nas abas dos meses. Ao receber, mude a Forma de Pagamento na aba do mês E o Status aqui. A linha de conferência avisa se os dois deixarem de bater.
A101: Cliente | B101: Produto / Referência | C101: Data da Venda | D101: Valor (R$) | E101: Status | F101: Dias em Atraso | G101: Observações
A102: Centro de Especialidades Odontomédicas | B102: Refil Everest | C102: 46239 | D102: 140 | E102: Pendente | F102: =IF(OR($E102="Recebido",$C102=""),"",MAX(0,TODAY()-$C102))
A103: Supermercado Brasil | B103: 2x Refil Pro Life | C103: 46239 | D103: 280 | E103: Pendente | F103: =IF(OR($E103="Recebido",$C103=""),"",MAX(0,TODAY()-$C103))
A104: Tropical Motos LTDA | B104: 3x Refil Everest + Refil Pro Life + 3x Pré Filtro + Válvula Reguladora de Pressão | C104: 46245 | D104: 820 | E104: Recebido | F104: =IF(OR($E104="Recebido",$C104=""),"",MAX(0,TODAY()-$C104)) | G104: Recebido via TED em 25/08/2026. NF conferida: valor correto é R$820 (faltava a válvula no lançamento original de R$740).
A105: Free Way | B105: 5x Refil Everest | C105: 46251 | D105: 700 | E105: Recebido | F105: =IF(OR($E105="Recebido",$C105=""),"",MAX(0,TODAY()-$C105)) | G105: Recebido via TED em 02/09/2026.
A106: Neli Sena Rego | B106: Refil Pro Life | C106: 46254 | D106: 140 | E106: Recebido | F106: =IF(OR($E106="Recebido",$C106=""),"",MAX(0,TODAY()-$C106)) | G106: Recebido em dinheiro em 01/09/2026 (R$ 170,00 pelas duas vendas)
A107: Neli Sena Rego | B107: Conexão + Mangueira | C107: 46255 | D107: 40 | E107: Recebido | F107: =IF(OR($E107="Recebido",$C107=""),"",MAX(0,TODAY()-$C107)) | G107: Recebido em dinheiro em 01/09/2026 (R$ 170,00 pelas duas vendas)
A108: Lapec | B108: 4x Refil Everest | C108: 46258 | D108: 480 | E108: Recebido | F108: =IF(OR($E108="Recebido",$C108=""),"",MAX(0,TODAY()-$C108)) | G108: Recebido em dinheiro em 08/09/2026 — lançado em "Set 2026".
A109: Cícero Lima | B109: Refil Everest | C109: 46261 | D109: 140 | E109: Recebido | F109: =IF(OR($E109="Recebido",$C109=""),"",MAX(0,TODAY()-$C109)) | G109: Recebido via Pix em 27/08/2026
A110: Promotoria Regional de Jacobina | B110: 2x Carcaça 9" + 2x Refil Plissado 9" + Conexão Reta Rosca | C110: 46261 | D110: 470 | E110: Recebido | F110: =IF(OR($E110="Recebido",$C110=""),"",MAX(0,TODAY()-$C110)) | G110: Pago em 28/08/2026 em duas formas: R$ 270,00 Pix + R$ 200,00 crédito 2x
A111: Lucas Souza | B111: Refil Everest + Pré Filtro | C111: 46261 | D111: 200 | E111: Recebido | F111: =IF(OR($E111="Recebido",$C111=""),"",MAX(0,TODAY()-$C111)) | G111: Recebido em dinheiro em 03/09/2026 — lançado em "Set 2026".
A112: FG Boa Vista (Recife/PE) | B112: Refis — troca de julho/2026 | C112: 46261 | D112: 1008.8 | E112: Recebido | F112: =IF(OR($E112="Recebido",$C112=""),"",MAX(0,TODAY()-$C112)) | G112: Grupo Ânima — NF 000.004.280 · recebido em 30/08/2026 (Nota Paga no portal V360)
A113: UNIFG Guanambi (Guanambi/BA) | B113: Refis — troca de julho/2026 | C113: 46261 | D113: 4534.75 | E113: Recebido | F113: =IF(OR($E113="Recebido",$C113=""),"",MAX(0,TODAY()-$C113)) | G113: Grupo Ânima — NF 000.004.281 · recebido em 30/08/2026 (Nota Paga no portal V360)
A114: UNP Zona Norte (Natal/RN) | B114: Refis — troca de julho/2026 | C114: 46261 | D114: 870 | E114: Recebido | F114: =IF(OR($E114="Recebido",$C114=""),"",MAX(0,TODAY()-$C114)) | G114: Grupo Ânima — NF 000.004.282 · recebido em 30/08/2026 (Nota Paga no portal V360)
A115: UNP Caicó (Caicó/RN) | B115: Refis — troca de julho/2026 | C115: 46261 | D115: 440 | E115: Recebido | F115: =IF(OR($E115="Recebido",$C115=""),"",MAX(0,TODAY()-$C115)) | G115: Grupo Ânima — NF 000.004.283 · recebido via Pix em 27/08/2026
... A162: Contabilidade Abreu | B162: Termostato | C162: 46311 | D162: 170 | E162: Pendente | F162: =IF(OR($E162="Recebido",$C162=""),"",MAX(0,TODAY()-$C162)) | G162: Troca de termostato do dia 16/10/2026.
A163: TOTAL EM ABERTO A RECEBER (detalhe) | D163: =SUMIF(E102:E162,"Pendente",D102:D162)
A164: CONFERÊNCIA COM AS ABAS DOS MESES
A165: =IF(ROUND(D163-C5,2)=0,"OK — o detalhe acima bate com as vendas marcadas como Aguardando Pagamento nas abas dos meses.","ATENÇÃO: diferença de R$ "&TEXT(ABS(D163-C5),"#,##0.00")&" entre este detalhe e as abas dos meses — alguma venda mudou de status em um lado só.")
A166: As contas a pagar do DigiSat (pendentes até 27/07/2026) foram todas quitadas — confirmado em 19/08/2026. A única dívida em aberto hoje é o Capital de Giro do Banco do Brasil. Lance aqui novos compromissos conforme surgirem.

Sheet Capital de Giro (BB)
A1: CAPITAL DE GIRO — BANCO DO BRASIL (Empréstimo de Reserva)
A2: Controle de contas da loja pagas pela reserva do Banco do Brasil (não contam como venda/faturamento) e das devoluções feitas pela Planeta Água até quitar o valor.
A3: ← Início
A4: SALDO DEVEDOR (A DEVOLVER) | E4: TOTAL JÁ RETIRADO (HISTÓRICO)
C5: =SUMIF(E9:E200,"A Devolver",D9:D200) | E5: =SUM(D9:D200)
A8: Data | B8: Conta Paga | C8: Categoria Original | D8: Valor (R$) | E8: Status | F8: Data da Devolução | G8: Observações
A9: 46237 | B9: Fracione Transportes | C9: Transporte e Entregas | D9: 1420 | E9: Devolvido | F9: 46265 | G9: Pago via Banco do Brasil — referente Ago 2026
A10: 46237 | B10: Aluguel da Loja | C10: Aluguel | D10: 880 | E10: Devolvido | F10: 46265 | G10: Pago via Banco do Brasil — referente Ago 2026
A11: 46237 | B11: Salário Erick (Estagiário) | C11: Salários, Comissões e Encargos | D11: 600 | E11: Devolvido | F11: 46265 | G11: Pago via Banco do Brasil — referente Ago 2026
A12: 46239 | B12: Filtros Planeta Água | C12: Fornecedores / Mercadoria | D12: 1674.12 | E12: Devolvido | F12: 46265 | G12: Pago via Banco do Brasil — referente Ago 2026
A13: 46238 | B13: Eversoft | C13: Fornecedores / Mercadoria | D13: 980.83 | E13: Devolvido | F13: 46265 | G13: Pago via Banco do Brasil — referente Ago 2026
A14: 46251 | B14: Despesas do dia 17/08/2026 (complemento) | C14: Diversas | D14: 250 | E14: Devolvido | F14: 46265 | G14: Retirada de R$ 250,00 para completar o pagamento das despesas de 17/08 — não corresponde a uma conta específica
A15: 46254 | B15: DAS — Documento de Arrecadação do Simples Nacional | C15: Impostos e Taxas | D15: 2330.53 | E15: Devolvido | F15: 46265 | G15: Pago via Banco do Brasil — referente Ago 2026
A16: 46295 | B16: Knox Produtos Refrigerados (2 bebedouros industriais) | C16: Fornecedores / Mercadoria | D16: 3272 | E16: Devolvido | F16: 46300 | G16: Pago pelo Adriano via Pix do Banco do Brasil com dinheiro da reserva — 30/09/2026. Devolvido em 05/10/2026: a loja transferiu R$ 6.000,00 (conta Ton/Stone → Adriano → Banco do Brasil), sendo R$ 3.272,00 desta devolução e R$ 2.728,00 para a reserva.
A18: Como registrar uma devolução:
A19: 1. Trocar "Status" da linha para "Devolvido" e preencher a "Data da Devolução".
A20: 2. Só isso. NÃO lançar a devolução como Saída na aba do mês — a despesa já foi lançada uma vez lá. Enquanto o status for "A Devolver", o valor é descontado do total de Despesas do mês (linha "Capital de Giro (BB) — ainda a devolver" do pivô); ao virar "Devolvido", passa a contar normalmente.

Sheet Ponto de Equilíbrio
A1: PONTO DE EQUILÍBRIO
A2: Quanto a loja precisa faturar por mês para pagar todas as contas E o pró-labore da Edilânia, sem prejuízo. Base: média dos meses já fechados em 2026 (o mês em andamento só entra na média quando terminar).
A3: ← Início
A4: Indicador | B4: Valor
A5: Receita média mensal | B5: ='DRE Simplificado'!O5
A6: Custos variáveis médios | B6: ='DRE Simplificado'!O10
A7: Margem de contribuição média (R$) | B7: ='DRE Simplificado'!O11
A8: Margem de contribuição (%) | B8: =IF(B5=0,"",B7/B5)
A9: Custos fixos da loja (média por mês) | B9: ='DRE Simplificado'!O23
A10: Pró-labore combinado da Edilânia (por mês) | B10: 4000 | C10: ← valor combinado em 05/10/2026. Se o combinado mudar, troque só aqui — a planilha e o site usam este número.
A11: Total a pagar por mês (custos fixos + pró-labore) | B11: =B9+B10
A12: PONTO DE EQUILÍBRIO (faturamento mínimo/mês, já pagando o pró-labore) | B12: =IF(B8<=0,"",B11/B8)
A13: Sobra média da loja ANTES do pró-labore | B13: ='DRE Simplificado'!O24
A14: Sobra média DEPOIS do pró-labore combinado | B14: =B13-B10
A16: Ticket médio da loja (preencha) | B16: 140 | C16: ← valor médio de uma venda. Serve para converter R$ em nº de vendas.
A18: QUANTO PRECISO VENDER PARA...
A19: Objetivo | B19: Lucro desejado (R$) — além do pró-labore | C19: Faturamento necessário (R$) | D19: Nº de vendas no mês | E19: Vendas por dia útil (26 dias)
A20: Pagar tudo e a Edilânia (sem prejuízo) | B20: 0 | C20: =IF($B$8<=0,"",($B$11+B20)/$B$8) | D20: =IF(OR($B$8<=0,$B$16=0),"",ROUNDUP(C20/$B$16,0)) | E20: =IF(D20="","",ROUND(D20/26,1))
A21: Lucrar R$ 500 | B21: 500 | C21: =IF($B$8<=0,"",($B$11+B21)/$B$8) | D21: =IF(OR($B$8<=0,$B$16=0),"",ROUNDUP(C21/$B$16,0)) | E21: =IF(D21="","",ROUND(D21/26,1))
A22: Lucrar R$ 1.000 | B22: 1000 | C22: =IF($B$8<=0,"",($B$11+B22)/$B$8) | D22: =IF(OR($B$8<=0,$B$16=0),"",ROUNDUP(C22/$B$16,0)) | E22: =IF(D22="","",ROUND(D22/26,1))
A23: Lucrar R$ 2.000 | B23: 2000 | C23: =IF($B$8<=0,"",($B$11+B23)/$B$8) | D23: =IF(OR($B$8<=0,$B$16=0),"",ROUNDUP(C23/$B$16,0)) | E23: =IF(D23="","",ROUND(D23/26,1))
A24: Lucrar R$ 3.000 | B24: 3000 | C24: =IF($B$8<=0,"",($B$11+B24)/$B$8) | D24: =IF(OR($B$8<=0,$B$16=0),"",ROUNDUP(C24/$B$16,0)) | E24: =IF(D24="","",ROUND(D24/26,1))
A25: Lucrar R$ 5.000 | B25: 5000 | C25: =IF($B$8<=0,"",($B$11+B25)/$B$8) | D25: =IF(OR($B$8<=0,$B$16=0),"",ROUNDUP(C25/$B$16,0)) | E25: =IF(D25="","",ROUND(D25/26,1))
A27: =IF(B8<=0,"⚠ ATENÇÃO: a margem de contribuição está negativa ou zerada — os custos variáveis estão consumindo toda a receita. Enquanto isso não for corrigido (preço, frete ou custo de compra), não existe ponto de equilíbrio possível.","✔ Margem de contribuição positiva: cada R$ 100 vendidos deixam R$ "&TEXT(B8*100,"0.00")&" para pagar os custos fixos, o pró-labore e gerar lucro.")
A28: O pró-labore da Edilânia é tudo o que ela gasta do dinheiro da loja (categoria "Pro Labore Edilânia" nas abas dos meses). Por isso ele entra aqui como uma conta fixa: a loja só está "no zero a zero" quando paga todas as despesas E os R$ combinados com ela.

Sheet Fluxo de Caixa Projetado
A1: FLUXO DE CAIXA PROJETADO
A2: Projeção do saldo dos próximos meses. As previsões vêm da média dos meses já fechados; edite as células amarelas com o que você já sabe que vai entrar ou sair.
A3: ← Início
A4: Saldo de caixa hoje (preencha) | B4: 0 | C4: ← quanto existe de dinheiro em caixa + banco nesta data
A6: Mês | B6: Entradas Previstas (R$) | C6: Recebimentos de Contas a Receber (R$) | D6: Saídas Previstas (R$) | E6: Resultado do Mês (R$) | F6: Saldo Acumulado (R$)
A7: Setembro/2026 | B7: ='DRE Simplificado'!O5 | C7: ='Contas a Pagar e Receber'!C5 | D7: =('DRE Simplificado'!O10+'DRE Simplificado'!O23+'Ponto de Equilíbrio'!$B$10) | E7: =B7+C7-D7 | F7: =$B$4+E7
A8: Outubro/2026 | B8: ='DRE Simplificado'!O5 | C8: 0 | D8: =('DRE Simplificado'!O10+'DRE Simplificado'!O23+'Ponto de Equilíbrio'!$B$10) | E8: =B8+C8-D8 | F8: =F7+E8
A9: Novembro/2026 | B9: ='DRE Simplificado'!O5 | C9: 0 | D9: =('DRE Simplificado'!O10+'DRE Simplificado'!O23+'Ponto de Equilíbrio'!$B$10) | E9: =B9+C9-D9 | F9: =F8+E9
A10: Dezembro/2026 | B10: ='DRE Simplificado'!O5 | C10: 0 | D10: =('DRE Simplificado'!O10+'DRE Simplificado'!O23+'Ponto de Equilíbrio'!$B$10) | E10: =B10+C10-D10 | F10: =F9+E10
A12: TOTAL PROJETADO | B12: =SUM(B7:B10) | C12: =SUM(C7:C10) | D12: =SUM(D7:D10) | E12: =SUM(E7:E10) | F12: =F10
A14: =IF(F10<0,"⚠ Pelo ritmo atual, o caixa fica NEGATIVO até dezembro. Reveja despesas fixas ou acelere a cobrança do que está a receber.","✔ Pelo ritmo atual, o caixa se mantém positivo até dezembro.")
A16: Saídas previstas = custos variáveis médios + custos fixos médios (aba DRE) + pró-labore combinado da Edilânia. As contas a receber pendentes entram uma única vez, em setembro, pois são vendas já feitas.

Sheet Reserva e Impostos
A1: RESERVA DE EMERGÊNCIA E IMPOSTOS
A2: Quanto a loja precisa ter guardado para aguentar meses ruins, e quanto sai de imposto por mês.
A3: ← Início
A4: RESERVA DE EMERGÊNCIA
A5: Indicador | B5: Valor
A6: Custo fixo médio mensal + pró-labore combinado da Edilânia | B6: ='DRE Simplificado'!O23+'Ponto de Equilíbrio'!$B$10
A7: Meses de cobertura desejados | B7: 3 | C7: ← 3 meses é o padrão recomendado para pequeno comércio
A8: RESERVA IDEAL | B8: =B6*B7
A9: Reserva que já existe hoje | B9: 28728 | C9: Aporte de Adriano em 03/09/2026: R$ 17.000,00 (R$ 8.135,48 desse valor quitou o saldo devedor do Capital de Giro (BB) — como o Capital de Giro É a reserva do Banco do Brasil, esse dinheiro voltou para a própria reserva ao quitar a dívida). Em 09/09/2026, retirada de R$ 6.500,00 do caixa da loja para a reserva — transferência entre contas da empresa, por isso não foi lançada como saída nas abas mensais. Pix do BNB para Adriano guardados como reserva (confirmado pela Edilânia em 30/09/2026): R$ 500,00 em 11/09 e R$ 2.000,00 em 25/09. Em 30/09/2026 saíram R$ 3.272,00 da reserva para pagar 2 bebedouros industriais da Knox (a loja deve devolver — ver aba Capital de Giro (BB)). Em 05/10/2026 a loja transferiu R$ 6.000,00 para a reserva no Banco do Brasil (via Pix para o Adriano): R$ 3.272,00 devolvendo o que a reserva pagou à Knox + R$ 2.728,00 a mais guardados. Total guardado: R$ 28.728,00. Em aberto: Pix de R$ 2.000,00 para Adriano em 09/09 — confirmar se já faz parte dos R$ 6.500,00 do mesmo dia.
A10: Falta guardar | B10: =MAX(0,B8-B9)
A11: Meses de cobertura que você tem hoje | B11: =IF(B6=0,"",B9/B6)
A14: IMPOSTOS
A15: Item | B15: Valor
A16: Regime tributário | B16: Simples Nacional
A17: Alíquota efetiva (%) | B17: 0.06
A18: Faturamento médio mensal | B18: ='DRE Simplificado'!O5
A19: Imposto estimado por mês | B19: =B18*B17
A20: Imposto estimado no ano (12 meses) | B20: =B19*12
A21: Dia de vencimento da guia (DAS) | B21: 20
A23: Regime e alíquota são um chute inicial — confirme com seu contador. O imposto já pago aparece nas abas mensais na categoria 'Impostos e Taxas'.
A24: A reserva ideal cobre os custos fixos E o pró-labore da Edilânia. Se quiser cobrir também a compra de mercadoria, aumente os meses de cobertura.

Sheet Orçado vs Realizado
A1: ORÇADO vs REALIZADO — AGOSTO/2026
A2: Defina a meta (amarelo) e compare com o que realmente aconteceu. O realizado é puxado automaticamente da aba do mês.
A3: ← Início
A4: Item | B4: Orçado (R$) | C4: Realizado (R$) | D4: Diferença (R$) | E4: % da Meta | F4: Situação
A5: FATURAMENTO | B5: 15000 | C5: =SUMIF('Ago 2026'!E5:E500,"<>",'Ago 2026'!D5:D500)-SUMIF('Ago 2026'!E5:E500,"<>",'Ago 2026'!F5:F500)-'Ago 2026'!T5 | D5: =C5-B5 | E5: =IF(B5=0,"",C5/B5) | F5: =IF(B5=0,"",IF(C5>=B5,"✔ Meta atingida","Faltam "&TEXT(B5-C5,"R$ #,##0.00")))
A7: DESPESAS POR CATEGORIA
A8: Categoria | B8: Orçado (R$) | C8: Realizado (R$) | D8: Diferença (R$) | E8: % da Meta | F8: Situação
A9: Fornecedores / Mercadoria | C9: ='Ago 2026'!L5 | D9: =C9-B9 | E9: =IF(B9=0,"",C9/B9) | F9: =IF(B9=0,"",IF(C9<=B9,"✔ Dentro do orçado","Estourou "&TEXT(C9-B9,"R$ #,##0.00")))
A10: Aluguel | C10: ='Ago 2026'!L6 | D10: =C10-B10 | E10: =IF(B10=0,"",C10/B10) | F10: =IF(B10=0,"",IF(C10<=B10,"✔ Dentro do orçado","Estourou "&TEXT(C10-B10,"R$ #,##0.00")))
A11: Água, Energia e Internet | C11: ='Ago 2026'!L7 | D11: =C11-B11 | E11: =IF(B11=0,"",C11/B11) | F11: =IF(B11=0,"",IF(C11<=B11,"✔ Dentro do orçado","Estourou "&TEXT(C11-B11,"R$ #,##0.00")))
A12: Impostos e Taxas | C12: ='Ago 2026'!L8 | D12: =C12-B12 | E12: =IF(B12=0,"",C12/B12) | F12: =IF(B12=0,"",IF(C12<=B12,"✔ Dentro do orçado","Estourou "&TEXT(C12-B12,"R$ #,##0.00")))
A13: Tarifas Bancárias e Cartão | C13: ='Ago 2026'!L9 | D13: =C13-B13 | E13: =IF(B13=0,"",C13/B13) | F13: =IF(B13=0,"",IF(C13<=B13,"✔ Dentro do orçado","Estourou "&TEXT(C13-B13,"R$ #,##0.00")))
A14: Transporte e Entregas | C14: ='Ago 2026'!L10 | D14: =C14-B14 | E14: =IF(B14=0,"",C14/B14) | F14: =IF(B14=0,"",IF(C14<=B14,"✔ Dentro do orçado","Estourou "&TEXT(C14-B14,"R$ #,##0.00")))
A15: Salários, Comissões e Encargos | C15: ='Ago 2026'!L11 | D15: =C15-B15 | E15: =IF(B15=0,"",C15/B15) | F15: =IF(B15=0,"",IF(C15<=B15,"✔ Dentro do orçado","Estourou "&TEXT(C15-B15,"R$ #,##0.00")))
A16: Contabilidade | C16: ='Ago 2026'!L12 | D16: =C16-B16 | E16: =IF(B16=0,"",C16/B16) | F16: =IF(B16=0,"",IF(C16<=B16,"✔ Dentro do orçado","Estourou "&TEXT(C16-B16,"R$ #,##0.00")))
A17: Manutenção e Reparos | C17: ='Ago 2026'!L13 | D17: =C17-B17 | E17: =IF(B17=0,"",C17/B17) | F17: =IF(B17=0,"",IF(C17<=B17,"✔ Dentro do orçado","Estourou "&TEXT(C17-B17,"R$ #,##0.00")))
A18: Material de Limpeza e Escritório | C18: ='Ago 2026'!L14 | D18: =C18-B18 | E18: =IF(B18=0,"",C18/B18) | F18: =IF(B18=0,"",IF(C18<=B18,"✔ Dentro do orçado","Estourou "&TEXT(C18-B18,"R$ #,##0.00")))
A19: Estornos de Vendas (Cancelamentos) | C19: ='Ago 2026'!L15 | D19: =C19-B19 | E19: =IF(B19=0,"",C19/B19) | F19: =IF(B19=0,"",IF(C19<=B19,"✔ Dentro do orçado","Estourou "&TEXT(C19-B19,"R$ #,##0.00")))
A20: Outras Despesas | C20: ='Ago 2026'!L16 | D20: =C20-B20 | E20: =IF(B20=0,"",C20/B20) | F20: =IF(B20=0,"",IF(C20<=B20,"✔ Dentro do orçado","Estourou "&TEXT(C20-B20,"R$ #,##0.00")))
A21: TOTAL DESPESAS | B21: =SUM(B9:B20) | C21: =SUM(C9:C20) | D21: =C21-B21 | E21: =IF(B21=0,"",C21/B21)
A22: Pró-labore Edilânia (combinado) | B22: ='Ponto de Equilíbrio'!$B$10 | C22: ='Ago 2026'!L17 | D22: =C22-B22 | E22: =IF(B22=0,"",C22/B22) | F22: =IF(B22=0,"",IF(C22<=B22,"✔ Dentro do combinado","Passou "&TEXT(C22-B22,"R$ #,##0.00")))
A23: RESULTADO (Faturamento − Despesas − Pró-labore) | B23: =B5-B21-B22 | C23: =C5-C21-C22 | D23: =C23-B23
A25: Preencha as metas nas células amarelas. Para usar em outro mês, troque as referências 'Ago 2026' pelas do mês desejado (ex.: 'Set 2026'), mantendo as mesmas linhas do quadro Saídas por Categoria.

Sheet Precificação e Margem
A1: PRECIFICAÇÃO E MARGEM POR PRODUTO
A2: Quanto sobra de verdade em cada item vendido. Custo = última compra de 2026 (IPI incluso, Simples não recupera) + 6,4% de frete de entrada nos itens da Everest e Eversoft, que são FOB. Filtros Planeta Água, Culligan e Knox são CIF: frete já vem no preço.
A3: ← Início
A4: Taxa média de cartão | B4: 0.07 | C4: Alíquota de imposto | D4: 0.06 | E4: ← taxa dos itens de balcão. Purificadores usam 13,99% (crédito 10x) direto na fórmula; Baby usa 11% (6x).
A5: COMISSÃO: só entra quando o Wiliam faz a troca/instalação. Venda de balcão sem serviço = margem R$ 10 (ou R$ 30) maior. Refis de outras marcas ficam sem comissão porque raramente são trocados por ele. A tabela lista só o que é comprado e revendido — serviços avulsos (instalação por fora, limpeza de refil) saíram daqui em 10/09/2026 por serem raros.
A6: Produto / Serviço | B6: Preço de Venda (R$) | C6: Custo de Aquisição (R$) | D6: Comissão (R$) | E6: Taxa de Cartão (R$) | F6: Imposto (R$) | G6: Custo Total (R$) | H6: Margem Líquida (R$) | I6: Margem (%) | J6: Taxa aplicada
A7: Refil Everest | B7: 140 | C7: 46.76 | D7: 10 | E7: =IF(B7="","",B7*IF($J7="",$B$4,$J7)) | F7: =IF(B7="","",B7*$D$4) | G7: =IF(B7="","",SUM(C7:F7)) | H7: =IF(B7="","",B7-G7) | I7: =IF(B7=0,"",H7/B7)
A8: Refil Pro Life | B8: 140 | C8: 24.2 | D8: 10 | E8: =IF(B8="","",B8*IF($J8="",$B$4,$J8)) | F8: =IF(B8="","",B8*$D$4) | G8: =IF(B8="","",SUM(C8:F8)) | H8: =IF(B8="","",B8-G8) | I8: =IF(B8=0,"",H8/B8)
A9: Refil Carbon Tech 9" | B9: 85 | C9: 32.48 | D9: 0 | E9: =IF(B9="","",B9*IF($J9="",$B$4,$J9)) | F9: =IF(B9="","",B9*$D$4) | G9: =IF(B9="","",SUM(C9:F9)) | H9: =IF(B9="","",B9-G9) | I9: =IF(B9=0,"",H9/B9)
A10: Refil Carbon Tech 5" | B10: 60 | C10: 34.41 | D10: 0 | E10: =IF(B10="","",B10*IF($J10="",$B$4,$J10)) | F10: =IF(B10="","",B10*$D$4) | G10: =IF(B10="","",SUM(C10:F10)) | H10: =IF(B10="","",B10-G10) | I10: =IF(B10=0,"",H10/B10)
A11: Refil E3 | B11: 110 | C11: 20.17 | D11: 0 | E11: =IF(B11="","",B11*IF($J11="",$B$4,$J11)) | F11: =IF(B11="","",B11*$D$4) | G11: =IF(B11="","",SUM(C11:F11)) | H11: =IF(B11="","",B11-G11) | I11: =IF(B11=0,"",H11/B11)
A12: Refil Plissado | B12: 80 | C12: 20.26 | D12: 0 | E12: =IF(B12="","",B12*IF($J12="",$B$4,$J12)) | F12: =IF(B12="","",B12*$D$4) | G12: =IF(B12="","",SUM(C12:F12)) | H12: =IF(B12="","",B12-G12) | I12: =IF(B12=0,"",H12/B12)
A13: Refil C+3 (IBBL) | B13: 115 | C13: 24 | D13: 0 | E13: =IF(B13="","",B13*IF($J13="",$B$4,$J13)) | F13: =IF(B13="","",B13*$D$4) | G13: =IF(B13="","",SUM(C13:F13)) | H13: =IF(B13="","",B13-G13) | I13: =IF(B13=0,"",H13/B13)
A14: Pré Filtro | B14: 60 | C14: 10.84 | D14: 0 | E14: =IF(B14="","",B14*IF($J14="",$B$4,$J14)) | F14: =IF(B14="","",B14*$D$4) | G14: =IF(B14="","",SUM(C14:F14)) | H14: =IF(B14="","",B14-G14) | I14: =IF(B14=0,"",H14/B14)
A15: Mangueira (por metro) | B15: 10 | C15: 1.72 | D15: 0 | E15: =IF(B15="","",B15*IF($J15="",$B$4,$J15)) | F15: =IF(B15="","",B15*$D$4) | G15: =IF(B15="","",SUM(C15:F15)) | H15: =IF(B15="","",B15-G15) | I15: =IF(B15=0,"",H15/B15)
A16: Registro | B16: 30 | C16: 5.19 | D16: 0 | E16: =IF(B16="","",B16*IF($J16="",$B$4,$J16)) | F16: =IF(B16="","",B16*$D$4) | G16: =IF(B16="","",SUM(C16:F16)) | H16: =IF(B16="","",B16-G16) | I16: =IF(B16=0,"",H16/B16)
A17: Termostato | B17: 170 | C17: 45 | D17: 30 | E17: =IF(B17="","",B17*IF($J17="",$B$4,$J17)) | F17: =IF(B17="","",B17*$D$4) | G17: =IF(B17="","",SUM(C17:F17)) | H17: =IF(B17="","",B17-G17) | I17: =IF(B17=0,"",H17/B17)
A18: Purificador Everest Slim Branco | B18: 1429 | C18: 715.02 | D18: 30 | E18: =IF(B18="","",B18*IF($J18="",$B$4,$J18)) | F18: =IF(B18="","",B18*$D$4) | G18: =IF(B18="","",SUM(C18:F18)) | H18: =IF(B18="","",B18-G18) | I18: =IF(B18=0,"",H18/B18) | J18: 0.1399
A19: Purificador Everest Slim Prata | B19: 1486 | C19: 784.97 | D19: 30 | E19: =IF(B19="","",B19*IF($J19="",$B$4,$J19)) | F19: =IF(B19="","",B19*$D$4) | G19: =IF(B19="","",SUM(C19:F19)) | H19: =IF(B19="","",B19-G19) | I19: =IF(B19=0,"",H19/B19) | J19: 0.1399
A20: Purificador Everest Star Branco | B20: 1429 | C20: 756.73 | D20: 30 | E20: =IF(B20="","",B20*IF($J20="",$B$4,$J20)) | F20: =IF(B20="","",B20*$D$4) | G20: =IF(B20="","",SUM(C20:F20)) | H20: =IF(B20="","",B20-G20) | I20: =IF(B20=0,"",H20/B20) | J20: 0.1399
A21: Purificador Everest Plus Branco | B21: 1529 | C21: 820.73 | D21: 30 | E21: =IF(B21="","",B21*IF($J21="",$B$4,$J21)) | F21: =IF(B21="","",B21*$D$4) | G21: =IF(B21="","",SUM(C21:F21)) | H21: =IF(B21="","",B21-G21) | I21: =IF(B21=0,"",H21/B21) | J21: 0.1399
A22: Purificador Everest Plus Prata | B22: 1569 | C22: 906.93 | D22: 30 | E22: =IF(B22="","",B22*IF($J22="",$B$4,$J22)) | F22: =IF(B22="","",B22*$D$4) | G22: =IF(B22="","",SUM(C22:F22)) | H22: =IF(B22="","",B22-G22) | I22: =IF(B22=0,"",H22/B22) | J22: 0.1399
A23: Purificador Everest Fit Branco | B23: 1429 | C23: 756.73 | D23: 30 | E23: =IF(B23="","",B23*IF($J23="",$B$4,$J23)) | F23: =IF(B23="","",B23*$D$4) | G23: =IF(B23="","",SUM(C23:F23)) | H23: =IF(B23="","",B23-G23) | I23: =IF(B23=0,"",H23/B23) | J23: 0.1399
A24: Purificador Everest Fit Preto | B24: 1486 | C24: 784.96 | D24: 30 | E24: =IF(B24="","",B24*IF($J24="",$B$4,$J24)) | F24: =IF(B24="","",B24*$D$4) | G24: =IF(B24="","",SUM(C24:F24)) | H24: =IF(B24="","",B24-G24) | I24: =IF(B24=0,"",H24/B24) | J24: 0.1399
A25: Purificador Everest Fit Prata | B25: 1486 | C25: 739.37 | D25: 30 | E25: =IF(B25="","",B25*IF($J25="",$B$4,$J25)) | F25: =IF(B25="","",B25*$D$4) | G25: =IF(B25="","",SUM(C25:F25)) | H25: =IF(B25="","",B25-G25) | I25: =IF(B25=0,"",H25/B25) | J25: 0.1399
A26: Purificador Everest Star Preto | B26: 1486 | C26: 784.96 | D26: 30 | E26: =IF(B26="","",B26*IF($J26="",$B$4,$J26)) | F26: =IF(B26="","",B26*$D$4) | G26: =IF(B26="","",SUM(C26:F26)) | H26: =IF(B26="","",B26-G26) | I26: =IF(B26=0,"",H26/B26) | J26: 0.1399
A27: Purificador Everest Foz Branco | B27: 1589 | C27: 767.95 | D27: 30 | E27: =IF(B27="","",B27*IF($J27="",$B$4,$J27)) | F27: =IF(B27="","",B27*$D$4) | G27: =IF(B27="","",SUM(C27:F27)) | H27: =IF(B27="","",B27-G27) | I27: =IF(B27=0,"",H27/B27) | J27: 0.1399
A28: Purificador Everest Foz Cinza/Grafite | B28: 1689 | C28: 819.57 | D28: 30 | E28: =IF(B28="","",B28*IF($J28="",$B$4,$J28)) | F28: =IF(B28="","",B28*$D$4) | G28: =IF(B28="","",SUM(C28:F28)) | H28: =IF(B28="","",B28-G28) | I28: =IF(B28=0,"",H28/B28) | J28: 0.1399
A29: Purificador Everest Baby (todas as cores) | B29: 420 | C29: 150.13 | D29: 30 | E29: =IF(B29="","",B29*IF($J29="",$B$4,$J29)) | F29: =IF(B29="","",B29*$D$4) | G29: =IF(B29="","",SUM(C29:F29)) | H29: =IF(B29="","",B29-G29) | I29: =IF(B29=0,"",H29/B29) | J29: 0.11
A31: PREÇOS: purificadores conforme o Catálogo de Purificadores (pasta Catálogos) — valor total do parcelamento em 10x, que é como as vendas entram na planilha. À vista sai mais barato: Residencial branco R$ 1.329, demais cores R$ 1.376; Plus branco R$ 1.429, demais R$ 1.476; Foz branco R$ 1.489, cinza/grafite R$ 1.589; Baby R$ 379. Preço de balcão x preço com serviço: Carbon Tech 9" R$ 85,00 e Plissado R$ 80,00 no balcão; os dois podem ir a R$ 90,00 quando há deslocamento do técnico, instalação ou outra despesa envolvida.
A32: TAXAS REAIS DA MAQUININHA (medidas em Ago-Set/2026): débito 1,45% · crédito à vista 3,51% · crédito 2-3x 6,99% · 4x 7,99% · 5x 9,99% · 10x 13,99%. Dinheiro e Pix não têm taxa. A coluna "Taxa aplicada" (J) manda: em branco usa os 7% de B4 (itens de balcão); preenchida, vale o que estiver lá.
A33: CUSTOS (conferidos nos XMLs de compra em 12/09/2026): Refil Everest e Pré-Filtro = Eversoft NF 75472 (26/08). Pro Life, Carbon Tech 5" e Plissado = Filtros Planeta Água NF 133812 (28/08). Carbon Tech 9" = NF 133138 (12/08). E3 = NF 131997 (08/07). C+3 = Culligan (22/04). Registro = Everest (19/05). Purificadores = Everest, última nota de cada modelo (Fit/Star branco e preto e Plus prata reajustados em 17/07; Foz em 04/08). Mangueira = R$ 1,72/m (rolo 50 m por R$ 86,01). Termostato = Everest NF 344.517 de 18/02/2025 (única compra; R$ 38,53/un + IPI 9,75% + frete FOB) — preço de 2025, conferir na próxima compra.
A34: ATENÇÃO — a Filtros Planeta Água cobra por volume, não por tabela: o mesmo código muda de preço conforme a quantidade da nota. Carbon Tech 9" saiu a R$ 49,00/un comprando 10 un (17/06) e a R$ 30,87/un comprando 30 un (12/08). O Plissado subiu para R$ 20,26 na última compra só porque foram 4 unidades (era R$ 18,23 comprando 20). Comprar em lote maior nessa fornecedora derruba bastante o custo.

Sheet Conciliação Bancária
A1: CONCILIAÇÃO BANCÁRIA
A2: Compare o que está lançado na planilha com o que aparece no extrato do banco. Qualquer diferença aparece sozinha na coluna Status.
A3: ← Início
A4: Data | B4: Descrição | C4: Valor na Planilha (R$) | D4: Valor no Extrato (R$) | E4: Diferença (R$) | F4: Status | G4: Observações
E5: =IF(AND(C5="",D5=""),"",C5-D5) | F5: =IF(AND(C5="",D5=""),"",IF(ROUND(E5,2)=0,"OK","DIVERGENTE"))
E6: =IF(AND(C6="",D6=""),"",C6-D6) | F6: =IF(AND(C6="",D6=""),"",IF(ROUND(E6,2)=0,"OK","DIVERGENTE"))
E7: =IF(AND(C7="",D7=""),"",C7-D7) | F7: =IF(AND(C7="",D7=""),"",IF(ROUND(E7,2)=0,"OK","DIVERGENTE"))
E8: =IF(AND(C8="",D8=""),"",C8-D8) | F8: =IF(AND(C8="",D8=""),"",IF(ROUND(E8,2)=0,"OK","DIVERGENTE"))
E9: =IF(AND(C9="",D9=""),"",C9-D9) | F9: =IF(AND(C9="",D9=""),"",IF(ROUND(E9,2)=0,"OK","DIVERGENTE"))
E10: =IF(AND(C10="",D10=""),"",C10-D10) | F10: =IF(AND(C10="",D10=""),"",IF(ROUND(E10,2)=0,"OK","DIVERGENTE"))
E11: =IF(AND(C11="",D11=""),"",C11-D11) | F11: =IF(AND(C11="",D11=""),"",IF(ROUND(E11,2)=0,"OK","DIVERGENTE"))
E12: =IF(AND(C12="",D12=""),"",C12-D12) | F12: =IF(AND(C12="",D12=""),"",IF(ROUND(E12,2)=0,"OK","DIVERGENTE"))
E13: =IF(AND(C13="",D13=""),"",C13-D13) | F13: =IF(AND(C13="",D13=""),"",IF(ROUND(E13,2)=0,"OK","DIVERGENTE"))
E14: =IF(AND(C14="",D14=""),"",C14-D14) | F14: =IF(AND(C14="",D14=""),"",IF(ROUND(E14,2)=0,"OK","DIVERGENTE"))
E15: =IF(AND(C15="",D15=""),"",C15-D15) | F15: =IF(AND(C15="",D15=""),"",IF(ROUND(E15,2)=0,"OK","DIVERGENTE"))
E16: =IF(AND(C16="",D16=""),"",C16-D16) | F16: =IF(AND(C16="",D16=""),"",IF(ROUND(E16,2)=0,"OK","DIVERGENTE"))
... E44: =IF(AND(C44="",D44=""),"",C44-D44) | F44: =IF(AND(C44="",D44=""),"",IF(ROUND(E44,2)=0,"OK","DIVERGENTE"))
A45: TOTAIS | C45: =SUM(C5:C44) | D45: =SUM(D5:D44) | E45: =SUM(E5:E44) | F45: =COUNTIF(F5:F44,"DIVERGENTE")&" divergência(s)"

Sheet Cadastro Clientes-Fornec
A1: CADASTRO DE CLIENTES E FORNECEDORES
A2: Base única de nomes, documentos e contatos — evita retrabalho e erro de digitação. Pré-preenchido com os nomes que já aparecem em Ago/2026; telefone e endereço puxados da Planilha de Clientes quando encontrados.
A3: ← Início
A4: Nome | B4: Tipo | C4: PF ou PJ | D4: CPF / CNPJ | E4: Telefone / WhatsApp | F4: E-mail | G4: Endereço | H4: Cidade | I4: Observações
A5: Graciete Cordeiro | B5: Cliente | E5: 991403050 | G5: Rua Deodoro da Fonseca, 104, Ap 106 | H5: Jacobina - BA | I5: Caixa Dágua
A6: Lojão das Maquiagens | B6: Cliente | E6: 981460585 May | G6: Rua Coronel Teixeira, 84 | H6: Jacobina - BA | I6: Centro
A7: Edelmir Cordeiro | B7: Cliente | E7: 991217035 | G7: Rua Coronel Deraldo Dias, 40 | H7: Jacobina - BA | I7: Leader
A8: Atacadão das Confecções | B8: Cliente | E8: 981460585 May | G8: Rua Coronel Teixeira, 270 | H8: Jacobina - BA | I8: Centro
A9: Silva e Silva Advogados | B9: Cliente | E9: 991330608 | G9: Rua D Casa 20 (Proximo a Associação) | H9: Jacobina - BA | I9: Jacobina 2
A10: Multipet | B10: Cliente | G10: Rua Ruy Barbosa | H10: Jacobina - BA | I10: Matriz
A11: Cilmara Melo Nunes de Souza | B11: Cliente | E11: 988221828 | G11: Condominio Alamedas do Rio, 490 | H11: Jacobina - BA | I11: Nazare
A12: Farmácia Popular | B12: Cliente | E12: 98873-1939 | G12: Rua do Triangulo, 477 | H12: Jacobina - BA | I12: Peru
A13: Ivanilton Costa | B13: Cliente | E13: 36213804/ 991231675 | G13: Travessa Alberto Torres, 126 | H13: Jacobina - BA | I13: Estação
A14: Centro de Especialidades Odontomédicas | B14: Cliente | E14: 988044240 1 Cobertura (clínica) | G14: Rua Senador Pedro Lago , 17 Edificio Edite | H14: Jacobina - BA | I14: Centro
A15: Supermercado Brasil | B15: Cliente | E15: 99195-3324 | G15: Rua Silvio Dias Pires, 70 | H15: Jacobina - BA | I15: Estação
A16: Marcio Itamar | B16: Cliente | E16: 9902-1170 | G16: Rua José Marcelino, 317 | H16: Jacobina - BA | I16: Mundo Novo
A17: Arena Jacobina Society | B17: Cliente | E17: 991343522 | G17: Rua Renato Rocha, 90 | H17: Jacobina - BA | I17: Felix Tomaz
A18: Verdes Mares Tintas | B18: Cliente | E18: 3621-3207/981024265 | G18: Avenida Orlando Oliveira Pires, 843 | H18: Jacobina - BA | I18: Centro
A19: Silvania Mota | B19: Cliente | E19: 36211743/991543136 | G19: Rua Costa e Silva, 46 | H19: Jacobina - BA | I19: Mundo Novo
A20: Ariosvaldo Mendes | B20: Cliente
A21: Andrea Lopes dos Santos | B21: Cliente | E21: 999240849 / | G21: Rua 10, s/n (Proximo a casa de cigano) | H21: Jacobina - BA | I21: Jacobina 2
A22: Marsilia Marmores e Granitos Erelli | B22: Cliente | E22: 999773095 | G22: Estrada de Canavieiras, 9999 - Oficina | H22: Jacobina - BA | I22: Jacobina 3
A23: Clinica da Mulher - MR Valois Serviços | B23: Cliente | E23: 98819-2425 | G23: Rua JJ Seabra, 275 | H23: Jacobina - BA | I23: Estação
A24: Acerto de Armando | B24: Cliente | E24: 999980107 | G24: Condomínio Alamedas do Rio, 230 | H24: Jacobina - BA | I24: Nazare
A25: Audioclin Clinca Médica LTDA - Tarcisio Nascimento | B25: Cliente | E25: 99912-1735/98102-8696 | G25: Avenida Orlando Oliveira Pires, 370 | H25: Jacobina - BA | I25: Centro
A26: Maria das Dores e Reje Celia | B26: Cliente | E26: 991322761/988599211 | G26: Rua São João, 127 térreo | H26: Jacobina - BA | I26: Missão
A27: Nlx Comercio e Serviços Subway - Alexandre Neder | B27: Cliente | E27: 3622-2382 | G27: Avenida Orlando Oliveira Pires, 95 | H27: Jacobina - BA | I27: Centro
A28: Tropical Motos LTDA | B28: Cliente | E28: 98814-8239 | G28: Rua Reinaldo Jacobina Vieira, s/n | H28: Jacobina - BA | I28: Peru
A29: Ivanir Carneiro de Oliveira | B29: Cliente | E29: 981090497 | G29: Rua Presidente Medici, 507 | H29: Jacobina - BA | I29: Felix Tomaz
A30: Condominio Ilha do Ouro | B30: Cliente | E30: 99937-4915 | G30: Avenida Centenario, s/n | H30: Jacobina - BA | I30: Nazaré
A31: Angelo Marcio Bispo | B31: Cliente | E31: 36215685/991352253 | G31: Rua do Cajueiro, 11 | H31: Jacobina - BA | I31: Caixa Dágua
A32: Elio Pereira dos Santos | B32: Cliente | E32: 991166458 | G32: Rua do Cajueiro, 315 | H32: Jacobina - BA | I32: Caixa Dágua
A33: Maria Madalena de Santana Santos | B33: Cliente | E33: 981211491 | G33: Travessa João Teixeira, 283 | H33: Jacobina - BA | I33: Peru
A34: SESC Administração Regional do Estado da Bahia | B34: Cliente
A35: Lilian Patrícia | B35: Cliente
A36: Natalice da Silva Masquarenhas | B36: Cliente | E36: 991102473 | G36: Rua Divino Espirito Santo, 588 | H36: Jacobina - BA | I36: Felix Tomaz
A37: Joelma Almeida | B37: Cliente | E37: 999128394 | G37: Rua Bom Jesus da Gloria, 57 | H37: Jacobina - BA | I37: Missão
A38: Ten Internet | B38: Cliente
A39: Ivanilton | B39: Cliente | E39: 991390102 | G39: Rua da Independencia, s/n | H39: Jacobina - BA | I39: Mundo Novo
A40: Maria Conceição Dias Da Silva | B40: Cliente | E40: 7191754415 | G40: Loteamento Orlando Touro, 82 | H40: Jacobina - BA | I40: Mundo Novo
A41: Free Way | B41: Cliente | E41: 99816-1451 | G41: Avenida Luiz Alberto Dourado, s/n Academia | H41: Jacobina - BA | I41: Jacobina 4
A42: Everest Refrigeração | B42: Fornecedor | C42: PJ | I42: Fornecedores / Mercadoria
A43: Filtros Planeta Água | B43: Fornecedor | C43: PJ | I43: Fornecedores / Mercadoria
A44: Eversoft | B44: Fornecedor | C44: PJ | I44: Fornecedores / Mercadoria
A45: Culligan Latam Eireli | B45: Fornecedor | C45: PJ | I45: Fornecedores / Mercadoria
A46: Fracione Transportes | B46: Fornecedor | C46: PJ | I46: Transporte e Entregas
A47: Correios | B47: Fornecedor | C47: PJ | I47: Transporte e Entregas
A48: Tarcisio Oliveira Lima | B48: Fornecedor | C48: PJ | I48: Transporte e Entregas
A90: Células em amarelo = para você preencher. Os telefones vieram da Planilha de Clientes (pasta 01 - Clientes) por correspondência de nome — confira antes de usar.

Sheet Jan 2026
A1: RELATÓRIO FINANCEIRO — JANEIRO / 2026
A2: Fluxo de caixa da loja — entradas montadas a partir das notas fiscais (XML do DigiSat), com cliente e produtos; saídas do Livro Caixa
A3: ← Início
A4: Data | B4: Descrição / Cliente | C4: Produto | D4: Entrada (R$) | E4: Forma de Pagamento | F4: Taxa da Máquina (R$) | G4: Saída (R$) | H4: Categoria da Saída | I4: Observações | J4: ID Cliente | K4: Saídas por Categoria | N4: FATURAMENTO | P4: DESPESAS | R4: SALDO ANTES DO PRÓ-LABORE | T4: A RECEBER
A5: 46023 | B5: Aluguel Vitoria Maria | G5: 870 | H5: Aluguel | I5: Livro Caixa: Pagamento parcela ALUGUEL VITORIA MARIA (Doc. 1) · Vitoria Maria F Santos | K5: Fornecedores / Mercadoria | L5: =SUMIF(H5:H134,K5,G5:G134) | N5: =D135-F135-T5 | P5: =L18-L19 | R5: =D136 | T5: =SUMIF(E5:E134,"Aguardando Pagamento",D5:D134)
A6: 46024 | B6: Tissia Cristina Moncorvo Santos | C6: Refil Everest | D6: 130 | E6: Dinheiro | I6: NFC-e 8769 | J6: CLI-0653 | K6: Aluguel | L6: =SUMIF(H5:H134,K6,G5:G134)
A7: 46024 | B7: Maria das Dores Jordão Moreira | C7: Refil Pro Life | D7: 140 | E7: Pix | I7: NFC-e 8770 | J7: CLI-0652 | K7: Água, Energia e Internet | L7: =SUMIF(H5:H134,K7,G5:G134) | N7: PRÓ-LABORE EDILÂNIA | P7: COMBINADO NO MÊS | R7: =IF(L17>'Ponto de Equilíbrio'!$B$10,"PASSOU DO COMBINADO",IF(TODAY()>EOMONTH(DATE(2026,1,1),0),"ABAIXO DO COMBINADO","AINDA PODE GASTAR")) | T7: SOBRA FINAL DO MÊS
A8: 46024 | B8: RF Supermercado Brasil LTDA | C8: 4x Refil Everest + Refil Pro Life | D8: 700 | I8: NF-e 4001 · nota faturada a prazo (forma de recebimento não consta na nota) · venda de 11/12/2025 — pagamento recebido em 02/01/2026 | J8: EMP-0261 | K8: Impostos e Taxas | L8: =SUMIF(H5:H134,K8,G5:G134) | N8: =L17 | P8: ='Ponto de Equilíbrio'!$B$10 | R8: =ABS('Ponto de Equilíbrio'!$B$10-L17) | T8: =R5-L17
A9: 46024 | B9: Everest Refrigeracao e Industria | G9: 597.74 | H9: Fornecedores / Mercadoria | I9: NF 358698 de 04/09/2025 · parcela 4/5 (venc. 02/01/2026) · compra total R$ 2.988,70: Purificador Everest Plus Preto + Purificador Everest Star Preto + Purificador Everest Plus Prata + Purificador Everest Fit Preto · Livro Caixa | K9: Tarifas Bancárias e Cartão | L9: =SUMIF(H5:H134,K9,G5:G134)
A10: 46024 | B10: Filtros Planeta Agua Ind e Com Ltda | G10: 771.56 | H10: Fornecedores / Mercadoria | I10: NF 123868 de 24/10/2025 · parcela 4/5 (venc. 02/01/2026) · compra total R$ 4.058,44 (IPI R$ 200,60): 50x Refil Pro Life + 5x Refil Top Color + 5x Refil Fp4 + 20x Refil Carbon Tech 9.3/4 Pol + 10x Refil Top Multifilter + 5x Refil Top Color Fast + 10x Refil Fpa14 + 5x Refil Fpa22 + 5x Carcaca Fit 9.3/4 Pol Branca + 5x Conexão T + 5x Refil Fpa16 · Livro Caixa | K10: Transporte e Entregas | L10: =SUMIF(H5:H134,K10,G5:G134)
A11: 46025 | B11: Flavia Monyque Muniz Ribeiro | C11: Purificador Everest Baby Branco | D11: 510 | E11: Dinheiro | I11: NF-e 4019 | J11: CLI-0655 | K11: Salários, Comissões e Encargos | L11: =SUMIF(H5:H134,K11,G5:G134)
A12: 46025 | B12: Consumidor Final | C12: Refil Top Color | D12: 100 | E12: Dinheiro | I12: NFC-e 8771 | K12: Contabilidade | L12: =SUMIF(H5:H134,K12,G5:G134)
A13: 46027 | B13: Jackson Macedo de Sales | C13: Refil IBBL C+3 | D13: 95 | E13: Dinheiro | I13: NFC-e 8772 | K13: Manutenção e Reparos | L13: =SUMIF(H5:H134,K13,G5:G134)
A14: 46027 | B14: Eversoft Ind e Com de Plasticos Ltda | G14: 980.81 | H14: Fornecedores / Mercadoria | I14: NF 66404 de 08/08/2025 · parcela 5/5 (venc. 05/01/2026) · compra total R$ 4.904,13: 100x Refil Everest + 50x Pré Filtro · Livro Caixa | K14: Material de Limpeza e Escritório | L14: =SUMIF(H5:H134,K14,G5:G134)
A15: 46028 | B15: Tamo Junto Comercial e Solucoes Ltda | C15: Refil Carbon Tech 5" | D15: 60 | E15: Pix | I15: NFC-e 8773 | K15: Estornos de Vendas (Cancelamentos) | L15: =SUMIF(H5:H134,K15,G5:G134)
A16: 46028 | B16: Consumidor Final | C16: Refil IBBL C+5 + Pré Filtro | D16: 170 | E16: Dinheiro | I16: NFC-e 8774 | K16: Outras Despesas | L16: =SUMIF(H5:H134,K16,G5:G134)
A17: 46028 | B17: Consumidor Final | C17: 4x Refil PP | D17: 260 | E17: Crédito Parcelado | I17: NFC-e 8775 | K17: Pro Labore Edilânia | L17: =SUMIF(H5:H134,K17,G5:G134)
A18: 46028 | B18: Bomboniere Doce Mania - Veronildo Basilio | C18: Purificador Everest Fit Prata + Pré Filtro | D18: 1420 | E18: Dinheiro | I18: NF-e 4020 | J18: EMP-0188 | K18: Total | L18: =SUM(L5:L16)
A19: 46028 | B19: Jacobina Veiculos | D19: 180 | I19: Livro Caixa: Recebimento à vista Gerado pelo sistema (Doc. 8776) | J19: EMP-0201 | K19: Capital de Giro (BB) — ainda a devolver | L19: =SUMIFS('Capital de Giro (BB)'!D9:D200,'Capital de Giro (BB)'!A9:A200,">="&DATE(2026,1,1),'Capital de Giro (BB)'!A9:A200,"<="&DATE(2026,1,31),'Capital de Giro (BB)'!E9:E200,"A Devolver")
A20: 46028 | B20: Jacobina Veiculos | C20: Refil Everest + Pré Filtro | D20: 190 | E20: Dinheiro | I20: NFC-e 8777 | J20: EMP-0201
A21: 46028 | B21: Clinica Odonto Gold | C21: Refil Everest | D21: 140 | E21: Dinheiro | I21: NFC-e 8778 | J21: EMP-0194
A22: 46028 | B22: Vilas Boas Shopping da Construcao Ltda | C22: 2x Refil Everest | D22: 280 | I22: NF-e 4022 · nota faturada a prazo (forma de recebimento não consta na nota)
A23: 46028 | B23: Rejane Magalhães Borges Maia | C23: Refil Everest + Pré Filtro | D23: 190 | E23: Pix | I23: NFC-e 8779 | J23: CLI-0656
A24: 46028 | B24: Buriti veículos, peças e serviços Ltda (Ford) | C24: Refil Pro Life | D24: 140 | I24: NF-e 4005 · nota faturada a prazo (forma de recebimento não consta na nota) · venda de 16/12/2025 — pagamento recebido em 06/01/2026 | J24: EMP-0035
A25: 46028 | B25: Master Comercial de Veículos Ltda - Loja | C25: Refil Everest + Refil Pro Life | D25: 280 | I25: NF-e 4004 · nota faturada a prazo (forma de recebimento não consta na nota) · venda de 16/12/2025 — pagamento recebido em 06/01/2026 | J25: EMP-0100
A26: 46028 | B26: Real Sociedade Portuguesa de Beneficencia 16 de Setembro | C26: 4x Refil Everest + Refil Carbon Tech 5" | D26: 540 | I26: NF-e 4021. Recebimento não constava no Livro Caixa; conferido e baixado no DigiSat em 28/09/2026.
A27: 46028 | B27: Estorno de recebimento — Jacobina Veiculos Ltda | G27: 180 | H27: Estornos de Vendas (Cancelamentos) | I27: Livro Caixa: Estorno de recebimento do documento: Gerado pelo sistema (Doc. 877)
A28: 46029 | B28: Leal Vilas Boas & Cia Ltda | C28: Purificador Everest Star Prata + Pré Filtro | D28: 1508 | E28: Dinheiro | I28: NF-e 4023
A29: 46029 | B29: Consumidor Final | C29: Conexao Reta Rosca 1/2 Bspt P/Tubo 1/4 Pol Branca | D29: 20 | E29: Dinheiro | I29: NFC-e 8780
A30: 46029 | B30: Jose Augusto Ribeiro Oliveira | C30: Pré Filtro | D30: 60 | E30: Crédito Parcelado | I30: NFC-e 8781
A31: 46029 | B31: Consumidor Final | C31: Mangueira (1 m) + Registro | D31: 40 | E31: Dinheiro | I31: NFC-e 8782
A32: 46029 | B32: Consumidor Final | C32: Refil Top Color | D32: 95 | E32: Pix | I32: NFC-e 8783
A33: 46029 | B33: Consumidor Final | C33: Refil FP4 | D33: 85 | E33: Pix | I33: NFC-e 8784
A34: 46029 | B34: Filtros Planeta Agua Ind e Com Ltda | G34: 513.07 | H34: Fornecedores / Mercadoria | I34: NF 125587 de 10/12/2025 · parcela 1/4 (venc. 07/01/2026) · compra total R$ 1.793,26 (IPI R$ 86,32): 5x Refil Lacqua + 15x Refil Fit Poe Pp 9.3/4 + 10x Refil Carbon Block 5 Pol + 5x Refil Top Color + 5x Refil Acquatec + 5x Refiil Carbon Tech 9.3/4 Pol + 20x Refil Poli Flu Plissado 9.3/4 + 5x Refil Fpa16 + Mangueira · Livro Caixa
A35: 46029 | B35: Conta de Energia Loja | G35: 159.68 | H35: Água, Energia e Internet | I35: Livro Caixa: Pagamento parcela CONTA DE ENERGIA LOJA (Doc. 1) · Companhia de Eletricidade do Estado da Bahia Coelba
A36: 46030 | B36: Ana Marcia Rosario de Oliveira | C36: Purificador Everest Slim Prata | D36: 1448 | E36: Dinheiro | I36: NF-e 4024
A37: 46030 | B37: Euzete Maria de Oliveira Araujo | C37: Refil Everest | D37: 140 | E37: Pix | I37: NF-e 4025
A38: 46030 | B38: Consumidor Final | C38: Refil Top Color | D38: 95 | E38: Crédito Parcelado | I38: NFC-e 8785
A39: 46030 | B39: Consumidor Final | C39: Refil Top Color | D39: 95 | E39: Dinheiro | I39: NFC-e 8786
A40: 46030 | B40: Consumidor Final | C40: Mangueira (1 m) | D40: 10 | E40: Dinheiro | I40: NFC-e 8787
A41: 46030 | B41: Consumidor Final | C41: Refil Universal | D41: 30 | E41: Dinheiro | I41: NFC-e 8788
A42: 46030 | B42: Everest Refrigeracao e Industria | G42: 781.4 | H42: Fornecedores / Mercadoria | I42: NF 361446 de 10/10/2025 · parcela 3/5 (venc. 08/01/2026) · compra total R$ 3.906,99: Purificador Everest Fit Preto + Purificador Everest Star Branco + Purificador Everest Star Preto + Purificador Everest Slim Branco + 4x Purificador Everest Baby Branco + 4x Purificador Everest Baby Preto · Livro Caixa
A43: 46030 | B43: Shopee (Torneiras) | G43: 143.09 | H43: Tarifas Bancárias e Cartão | I43: Livro Caixa: Pagamento parcela SHOPEE (TORNEIRAS) (Doc. 1) · Adyen do Brasil Intituicao Pagamento Ltda
A44: 46031 | B44: Consumidor Final | C44: Refil Universal | D44: 35 | E44: Débito | I44: NFC-e 8789
A45: 46031 | B45: Consumidor Final | C45: Refil FP4 | D45: 80 | E45: Pix | I45: NFC-e 8790
A46: 46031 | B46: Danielma da Silva Bezerra Brasileiro | C46: Refil Everest | D46: 140 | E46: Crédito Parcelado | I46: NFC-e 8791
A47: 46031 | B47: Uniao Leste Brasileira da Iasd | D47: 170 | I47: Livro Caixa: Recebimento à vista Gerado pelo sistema. (Doc. 4026)
A48: 46031 | B48: Uniao Leste Brasileira da Iasd | C48: Refil Everest + Registro | D48: 170 | I48: NF-e 4027 · nota faturada a prazo (forma de recebimento não consta na nota)
A49: 46031 | B49: Estorno de recebimento — Uniao Leste Brasileira da Iasd | G49: 170 | H49: Estornos de Vendas (Cancelamentos) | I49: Livro Caixa: Estorno de recebimento do documento: Gerado pelo sistema. (Doc. 40)
A50: 46032 | B50: Consumidor Final | C50: Mangueira (2 m) | D50: 20 | E50: Crédito Parcelado | I50: NFC-e 8792
A51: 46032 | B51: Consumidor Final | C51: 2x Conexao Reta Rosca 1/2 Bspt P/Tubo 1/4 Pol Branca | D51: 50 | E51: Crédito Parcelado | I51: NFC-e 8793
A52: 46032 | B52: Consumidor Final | C52: Mangueira (3 m) | D52: 30 | E52: Dinheiro | I52: NFC-e 8794
A53: 46034 | B53: Ten Solucoes, e Tecnologia Ltda | C53: Refil Carbon Tech 5" + Refil Plissado | D53: 160 | E53: Dinheiro | I53: NF-e 4028
A54: 46034 | B54: Mariua Construcoes Ltda | C54: Refil Plissado + Refil Carbon Tech 9" | D54: 180 | E54: Dinheiro | I54: NF-e 4029
A55: 46034 | B55: Everest Refrigeracao e Industria | G55: 841.06 | H55: Fornecedores / Mercadoria | I55: NF 366264 de 11/12/2025 · parcela 1/5 (venc. 10/01/2026) · compra total R$ 4.205,29: Purificador Everest Slim Branco + Purificador Everest Slim Prata + 2x Purificador Everest Star Branco + Purificador Everest Star Prata + Purificador Everest Plus Prata · Livro Caixa
A56: 46034 | B56: Everest Refrigeracao e Industria | G56: 577.35 | H56: Fornecedores / Mercadoria | I56: NF 357294 de 14/08/2025 · parcela 5/5 (venc. 11/01/2026) · compra total R$ 2.886,75: 2x Purificador Everest Plus Branco + 2x Purificador Everest Slim Branco · Livro Caixa
A57: 46034 | B57: Ferias Wiliam 1 Parcela | G57: 1405 | H57: Salários, Comissões e Encargos | I57: Livro Caixa: Pagamento parcela FERIAS WILIAM 1 PARCELA (Doc. 1) · Wiliam Pinto Bispo
A58: 46035 | B58: Consumidor Final | C58: Mangueira (1 m) + Conexao Reta Rosca 1/2 Bspt P/Tubo 1/4 Pol Branca | D58: 40 | E58: Dinheiro | I58: NFC-e 8795
A59: 46035 | B59: Cleber Santos Carvalho | C59: Refil Everest | D59: 140 | E59: Crédito Parcelado | I59: NFC-e 8796
A60: 46035 | B60: Consumidor Final | C60: Refil Everest | D60: 140 | E60: Crédito Parcelado | I60: NFC-e 8797
A61: 46035 | B61: Consumidor Final | C61: Pré Filtro + Registro | D61: 90 | E61: Débito | I61: NFC-e 8798
A62: 46035 | B62: Andradina Mota dos Santos | C62: Refil Pro Life + Pré Filtro | D62: 200 | E62: Dinheiro | I62: NFC-e 8799 | J62: CLI-0662
A63: 46035 | B63: Maria da Conceição Costa e Silva | C63: Valvula Reguladora De Pressao Soft | D63: 50 | E63: Dinheiro | I63: NFC-e 8800 | J63: CLI-0651
A64: 46035 | B64: José Tiago Souza | C64: Refil Pro Life + Pré Filtro | D64: 185 | E64: Pix | I64: NFC-e 8801 | J64: CLI-0661
A65: 46035 | B65: Premiere Odontologia Ltda.Me - Ana Carolina | C65: Refil Everest | D65: 140 | E65: Pix | I65: NFC-e 8802
A66: 46036 | B66: Clinica DentalClin - Igor Santos Silva ME | C66: Refil Everest | D66: 140 | E66: Pix | I66: NFC-e 8803 | J66: EMP-0077
A67: 46036 | B67: Consumidor Final | C67: Refil Carbon Tech 9" | D67: 90 | E67: Pix | I67: NFC-e 8804
A68: 46036 | B68: Consumidor Final | C68: Refil IBBL C+5 | D68: 125 | E68: Pix | I68: NFC-e 8805
A69: 46037 | B69: PC Jacobina Administradora de Cartões LTDA | C69: Purificador Everest Star Preto | D69: 1348 | E69: Dinheiro | I69: NF-e 4030 | J69: EMP-0244
A70: 46037 | B70: Pc Jacobina Administradora de Cartoes Ltda | C70: Valvula Reguladora De Pressao Soft | D70: 60 | E70: Crédito Parcelado | I70: NFC-e 8806
A71: 46037 | B71: Consumidor Final | D71: 145 | I71: Livro Caixa: Recebimento à vista Gerado pelo sistema (Doc. 8807)
A72: 46037 | B72: Consumidor Final | C72: Refil PP + Refil Plissado | D72: 135 | E72: Pix | I72: NFC-e 8808
A73: 46037 | B73: Estorno de recebimento — Cliente Consumidor | G73: 145 | H73: Estornos de Vendas (Cancelamentos) | I73: Livro Caixa: Estorno de recebimento do documento: Gerado pelo sistema (Doc. 880)
A74: 46038 | B74: Consumidor Final | C74: Vela Filtro de Barro | D74: 10 | E74: Dinheiro | I74: NFC-e 8809
A75: 46038 | B75: Tarcisio Oliveira Lima | G75: 455.4 | H75: Contabilidade | I75: Livro Caixa: Pagamento parcela TARCISIO OLIVEIRA LIMA (Doc. 1) · Contabilidade Tarcisio Oliveira Lima
A76: 46038 | B76: Everest Refrigeracao e Industria | G76: 824.74 | H76: Fornecedores / Mercadoria | I76: NF 357493 de 19/08/2025 · parcela 5/5 (venc. 16/01/2026) · compra total R$ 4.123,62: Purificador Everest Star Branco + Purificador Everest Star Prata + Purificador Everest Star Cereja + Purificador Everest Slim Prata + Purificador Everest Fit Branco + Purificador Everest Fit Prata · Livro Caixa
A77: 46038 | B77: Filtros Planeta Agua Ind e Com Ltda | G77: 771.56 | H77: Fornecedores / Mercadoria | I77: NF 123868 de 24/10/2025 · parcela 5/5 (venc. 16/01/2026) · compra total R$ 4.058,44 (IPI R$ 200,60): 50x Refil Pro Life + 5x Refil Top Color + 5x Refil Fp4 + 20x Refil Carbon Tech 9.3/4 Pol + 10x Refil Top Multifilter + 5x Refil Top Color Fast + 10x Refil Fpa14 + 5x Refil Fpa22 + 5x Carcaca Fit 9.3/4 Pol Branca + 5x Conexão T + 5x Refil Fpa16 · Livro Caixa
A78: 46038 | B78: Jamef | G78: 358.82 | H78: Transporte e Entregas | I78: Livro Caixa: Pagamento parcela JAMEF (Doc. 1) · Jamef Transportes Ltda
A79: 46041 | B79: Lucas Santos Pinto de Souza | C79: Purificador Everest Star Branco | D79: 1398 | E79: Dinheiro | I79: NF-e 4031 | J79: CLI-0676
A80: 46041 | B80: Ila Cariele Correia Dantas | C80: Refil Everest | D80: 140 | E80: Pix | I80: NFC-e 8810
A81: 46041 | B81: Odontoclass Almeida & Gois Ltda | C81: Refil Everest | D81: 140 | E81: Crédito Parcelado | I81: NFC-e 8811
A82: 46041 | B82: Suelene Soares Lima | C82: Refil Everest | D82: 140 | E82: Dinheiro | I82: NFC-e 8812 | J82: CLI-0665
A83: 46041 | B83: Eversoft Ind e Com de Plasticos Ltda | G83: 878.92 | H83: Fornecedores / Mercadoria | I83: NF 67435 de 19/09/2025 · parcela 4/5 (venc. 17/01/2026) · compra total R$ 4.394,61: 100x Refil Everest · Livro Caixa
A84: 46041 | B84: Filtros Planeta Agua | G84: 519.19 | H84: Fornecedores / Mercadoria | I84: Livro Caixa: Pagamento à vista: FILTROS PLANETA AGUA (Doc. 1) · Filtros Planeta Agua Ind e Com Ltda
A85: 46042 | B85: Silva & Silva Sociedade de Advogados | C85: Refil Everest | D85: 140 | E85: Pix | I85: NF-e 4032
A86: 46042 | B86: Consumidor Final | C86: 2x Refil Everest + Suporte | D86: 320 | E86: Crédito Parcelado | I86: NFC-e 8813
A87: 46042 | B87: Maria Alencar de Souza | C87: Refil Everest | D87: 140 | E87: Dinheiro | I87: NFC-e 8814 | J87: CLI-0669
A88: 46042 | B88: Costa e Sa Advogados | C88: Refil FPA14 | D88: 100 | E88: Dinheiro | I88: NF-e 4033 | J88: EMP-0316
A89: 46042 | B89: Floripes da Silva Cunha | C89: Refil Everest | D89: 140 | E89: Débito | I89: NFC-e 8815
A90: 46042 | B90: J Diesel Motores e Reparos Automotivos Eireli | C90: Refil Everest | D90: 140 | E90: Dinheiro | I90: NF-e 4034
A91: 46042 | B91: Arivaldo Pereira Teixeira | C91: Refil Everest | D91: 140 | E91: Pix | I91: NFC-e 8816
A92: 46042 | B92: Everest Refrigeracao e Industria | G92: 800.65 | H92: Fornecedores / Mercadoria | I92: NF 362188 de 22/10/2025 · parcela 3/5 (venc. 20/01/2026) · compra total R$ 4.003,24: Purificador Everest Fit Branco + Purificador Everest Fit Prata + Purificador Everest Slim Branco + Purificador Everest Slim Prata + Purificador Everest Star Branco + 4x Purificador Everest Baby Cereja · Livro Caixa
A93: 46042 | B93: Guia do Fgts Digital | G93: 249.44 | H93: Impostos e Taxas | I93: Livro Caixa: Pagamento parcela GUIA DO FGTS DIGITAL (Doc. 1) · Planeta Agua Ltda
A94: 46042 | B94: Documento de Arrecadação de Receitas Fe | G94: 402.06 | H94: Impostos e Taxas | I94: Livro Caixa: Pagamento parcela DOCUMENTO DE ARRECADAÇÃO DE RECEITAS FE · Planeta Agua Ltda
A95: 46042 | B95: Simples Nacional | G95: 1644.44 | H95: Impostos e Taxas | I95: Livro Caixa: Pagamento à vista: SIMPLES NACIONAL (Doc. 1) · Planeta Agua Ltda
A96: 46043 | B96: Consumidor Final | C96: Refil Acquatec | D96: 85 | E96: Dinheiro | I96: NFC-e 8817
A97: 46043 | B97: Vivalda Vieira de Brito | C97: Refil Everest | D97: 140 | E97: Dinheiro | I97: NFC-e 8818 | J97: CLI-0668
A98: 46043 | B98: Sebastiao Alves da Silva | C98: Refil Everest + Suporte | D98: 200 | E98: Crédito Parcelado | I98: NFC-e 8819
A99: 46043 | B99: Bio Imagem Serviço de Diagnostico - Copa | C99: 2x Refil Everest | D99: 280 | E99: Dinheiro | I99: NF-e 4035 | J99: EMP-0030
A100: 46043 | B100: Clinica Odonto X | C100: Refil Everest | D100: 140 | E100: Dinheiro | I100: NF-e 4036 | J100: EMP-0306
...

Sheet Fev 2026
A1: RELATÓRIO FINANCEIRO — FEVEREIRO / 2026
A2: Fluxo de caixa da loja — entradas montadas a partir das notas fiscais (XML do DigiSat), com cliente e produtos; saídas do Livro Caixa
A3: ← Início
A4: Data | B4: Descrição / Cliente | C4: Produto | D4: Entrada (R$) | E4: Forma de Pagamento | F4: Taxa da Máquina (R$) | G4: Saída (R$) | H4: Categoria da Saída | I4: Observações | J4: ID Cliente | K4: Saídas por Categoria | N4: FATURAMENTO | P4: DESPESAS | R4: SALDO ANTES DO PRÓ-LABORE | T4: A RECEBER
A5: 46054 | B5: Aluguel Vitoria Maria | G5: 870 | H5: Aluguel | I5: Livro Caixa: Pagamento à vista: ALUGUEL VITORIA MARIA (Doc. 1) · Vitoria Maria F Santos | K5: Fornecedores / Mercadoria | L5: =SUMIF(H5:H148,K5,G5:G148) | N5: =D149-F149-T5 | P5: =L18-L19 | R5: =D150 | T5: =SUMIF(E5:E148,"Aguardando Pagamento",D5:D148)
A6: 46055 | B6: Terezinha Souza Maia | C6: Refil Everest + Pré Filtro | D6: 190 | E6: Pix | I6: NFC-e 8832 | J6: CLI-0644 | K6: Aluguel | L6: =SUMIF(H5:H148,K6,G5:G148)
A7: 46055 | B7: Roberta Lima dos Santos | C7: Refil Everest | D7: 140 | E7: Crédito Parcelado | I7: NFC-e 8833 | K7: Água, Energia e Internet | L7: =SUMIF(H5:H148,K7,G5:G148) | N7: PRÓ-LABORE EDILÂNIA | P7: COMBINADO NO MÊS | R7: =IF(L17>'Ponto de Equilíbrio'!$B$10,"PASSOU DO COMBINADO",IF(TODAY()>EOMONTH(DATE(2026,2,1),0),"ABAIXO DO COMBINADO","AINDA PODE GASTAR")) | T7: SOBRA FINAL DO MÊS
A8: 46055 | B8: Joselia Sousa Bacelar | C8: Refil Everest | D8: 135 | E8: Dinheiro | I8: NFC-e 8834 | J8: CLI-0687 | K8: Impostos e Taxas | L8: =SUMIF(H5:H148,K8,G5:G148) | N8: =L17 | P8: ='Ponto de Equilíbrio'!$B$10 | R8: =ABS('Ponto de Equilíbrio'!$B$10-L17) | T8: =R5-L17
A9: 46055 | B9: Edna da Silva Farias | C9: Refil Everest | D9: 140 | E9: Dinheiro | I9: NFC-e 8835 | J9: CLI-0686 | K9: Tarifas Bancárias e Cartão | L9: =SUMIF(H5:H148,K9,G5:G148)
A10: 46055 | B10: Farmacia Popular - Cremilda Matos dos Santos | C10: Refil Everest + Pré Filtro | D10: 180 | E10: Dinheiro | I10: NFC-e 8836 | J10: EMP-0147 | K10: Transporte e Entregas | L10: =SUMIF(H5:H148,K10,G5:G148)
A11: 46055 | B11: Vanete Nunes Franco | C11: Refil Everest | D11: 140 | E11: Crédito Parcelado | I11: NFC-e 8837 | K11: Salários, Comissões e Encargos | L11: =SUMIF(H5:H148,K11,G5:G148)
A12: 46055 | B12: Catuaba Materiais de Construção | C12: Refil Everest | D12: 140 | E12: Dinheiro | I12: NF-e 4048 | J12: EMP-0051 | K12: Contabilidade | L12: =SUMIF(H5:H148,K12,G5:G148)
A13: 46055 | B13: L Silva dos Santos - Leliane Silva | C13: Refil Everest | D13: 135 | E13: Pix | I13: NF-e 4049 | K13: Manutenção e Reparos | L13: =SUMIF(H5:H148,K13,G5:G148)
A14: 46055 | B14: Cleidiomar Moreira Gonzaga | C14: Refil Everest | D14: 140 | E14: Crédito Parcelado | I14: NFC-e 8838 | K14: Material de Limpeza e Escritório | L14: =SUMIF(H5:H148,K14,G5:G148)
A15: 46055 | B15: Consumidor Final | C15: Refil Everest + Registro | D15: 175 | E15: Pix | I15: NFC-e 8839 | K15: Estornos de Vendas (Cancelamentos) | L15: =SUMIF(H5:H148,K15,G5:G148)
A16: 46055 | B16: Amanda Caroline Vieria Bispo - Clinica Sorriso Lindo | C16: Termostato | D16: 170 | E16: Pix | I16: NFC-e 8840 | K16: Outras Despesas | L16: =SUMIF(H5:H148,K16,G5:G148)
A17: 46055 | B17: Instituto Psicopedagogico Maria Rita Eireli | C17: Refil Everest | D17: 160 | E17: Pix | I17: NF-e 4050 | K17: Pro Labore Edilânia | L17: =SUMIF(H5:H148,K17,G5:G148)
A18: 46055 | B18: Maria Carolina Gomes Vasconcelos Ltda | C18: Refil Everest | D18: 140 | E18: Dinheiro | I18: NF-e 4051 | K18: Total | L18: =SUM(L5:L16)
A19: 46055 | B19: Tiago Rodrigo de Araujo Valgueiro | C19: Refil Everest | D19: 140 | E19: Pix | I19: NFC-e 8841 | J19: CLI-0681 | K19: Capital de Giro (BB) — ainda a devolver | L19: =SUMIFS('Capital de Giro (BB)'!D9:D200,'Capital de Giro (BB)'!A9:A200,">="&DATE(2026,2,1),'Capital de Giro (BB)'!A9:A200,"<="&DATE(2026,2,28),'Capital de Giro (BB)'!E9:E200,"A Devolver")
A20: 46055 | B20: Arlindo Galdino dos Santos Junior - Floricelia Carvalho | C20: Refil Everest | D20: 140 | E20: Crédito Parcelado | I20: NFC-e 8842
A21: 46055 | B21: Fagner Palmeiras Gomes | C21: Purificador Everest Slim Branco | D21: 1398 | E21: Dinheiro | I21: NF-e 4052
A22: 46055 | B22: Alex Assis Ferreira Franco | C22: Refil Everest + Pré Filtro | D22: 180 | E22: Dinheiro | I22: NFC-e 8843 | J22: CLI-0361
A23: 46055 | B23: Consumidor Final | C23: Refil Prolux | D23: 100 | E23: Pix | I23: NFC-e 8844
A24: 46055 | B24: Colegio Aquarela LTDA | C24: Refil Carbon Tech 9" + Refil Plissado | D24: 180 | E24: Dinheiro | I24: NF-e 4053 | J24: ESC-0017
A25: 46055 | B25: Adriana Mota da Silva | C25: Refil Everest | D25: 140 | E25: Débito | I25: NFC-e 8845
A26: 46055 | B26: Neide Fagundes - Laercio Guilherme | C26: Refil Everest | D26: 140 | E26: Débito | I26: NFC-e 8846
A27: 46055 | B27: Rivanildo Amorin Lagos - Cladenir Amorin | C27: Refil Everest + Pré Filtro | D27: 190 | E27: Dinheiro | I27: NFC-e 8847 | J27: CLI-0691
A28: 46055 | B28: Consumidor Final | C28: Conexao Reta Rosca 1/2 Bspt P/Tubo 1/4 Pol Branca | D28: 20 | E28: Pix | I28: NFC-e 8848
A29: 46055 | B29: Consumidor Final | C29: Refil PP | D29: 70 | E29: Dinheiro | I29: NFC-e 8849
A30: 46056 | B30: Consumidor Final | C30: Refil Pro Life + Pré Filtro | D30: 200 | E30: Pix | I30: NFC-e 8850
A31: 46056 | B31: Consumidor Final | D31: 30 | I31: Livro Caixa: Recebimento à vista Gerado pelo sistema (Doc. 8851)
A32: 46056 | B32: Consumidor Final | C32: Mangueira (6 m) | D32: 30 | E32: Pix | I32: NFC-e 8852
A33: 46056 | B33: Consumidor Final | C33: Mangueira (1 m) | D33: 10 | E33: Dinheiro | I33: NFC-e 8853
A34: 46056 | B34: Consumidor Final | C34: Refil Carbon Tech | D34: 65 | E34: Pix | I34: NFC-e 8854
A35: 46056 | B35: Renata Campos Tavares Gomes Nunes - Cepi Pediatria | C35: Refil Everest | D35: 140 | E35: Pix | I35: NF-e 4055
A36: 46056 | B36: Consumidor Final | C36: Refil FPA16 | D36: 90 | E36: Pix | I36: NFC-e 8855
A37: 46056 | B37: Estorno de recebimento — Cliente Consumidor | G37: 30 | H37: Estornos de Vendas (Cancelamentos) | I37: Livro Caixa: Estorno de recebimento do documento: Gerado pelo sistema (Doc. 885)
A38: 46056 | B38: Everest Refrigeracao e Industria | G38: 597.74 | H38: Fornecedores / Mercadoria | I38: NF 358698 de 04/09/2025 · parcela 5/5 (venc. 01/02/2026) · compra total R$ 2.988,70: Purificador Everest Plus Preto + Purificador Everest Star Preto + Purificador Everest Plus Prata + Purificador Everest Fit Preto · Livro Caixa
A39: 46056 | B39: Embasa Adriano | G39: 74.27 | H39: Pro Labore Edilânia | I39: Livro Caixa: Pagamento à vista: EMBASA ADRIANO (Doc. 2) · Adriano Silva Fontes
A40: 46056 | B40: Coelba Adriano | G40: 435.39 | H40: Pro Labore Edilânia | I40: Livro Caixa: Pagamento à vista: COELBA ADRIANO (Doc. 1) · Adriano Silva Fontes
A41: 46056 | B41: Filtros Planeta Agua Ind e Com Ltda | G41: 426.73 | H41: Fornecedores / Mercadoria | I41: NF 125587 de 10/12/2025 · parcela 3/4 (venc. 04/02/2026) · compra total R$ 1.793,26 (IPI R$ 86,32): 5x Refil Lacqua + 15x Refil Fit Poe Pp 9.3/4 + 10x Refil Carbon Block 5 Pol + 5x Refil Top Color + 5x Refil Acquatec + 5x Refiil Carbon Tech 9.3/4 Pol + 20x Refil Poli Flu Plissado 9.3/4 + 5x Refil Fpa16 + Mangueira · Livro Caixa
A42: 46056 | B42: Coelba Loja | G42: 145.99 | H42: Água, Energia e Internet | I42: Livro Caixa: Pagamento parcela COELBA LOJA (Doc. 1) · Companhia de Eletricidade do Estado da Bahia Coelba
A43: 46057 | B43: Salão do Reino Congregação Oeste | C43: Refil Everest | D43: 90 | E43: Dinheiro | I43: NF-e 4056 | J43: EMP-0270
A44: 46057 | B44: Tarcisio Fialho Cesar Cardoso | C44: Refil Pro Life | D44: 130 | I44: NFC-e 8856 · nota faturada a prazo (forma de recebimento não consta na nota) | J44: CLI-0643
A45: 46057 | B45: Igreja Evangelica Assembleia de Deus | C45: Refil Multifilter + Refil Plissado | D45: 180 | I45: NF-e 4057 · nota faturada a prazo (forma de recebimento não consta na nota) | J45: EMP-0176
A46: 46057 | B46: Consumidor Final | C46: Refil Carbon Tech 9" | D46: 80 | E46: Pix | I46: NFC-e 8857
A47: 46057 | B47: Consumidor Final | C47: Refil Everest | D47: 140 | E47: Dinheiro | I47: NFC-e 8858
A48: 46058 | B48: Tatiana Miranda Siqueira | C48: Refil Everest + Pré Filtro | D48: 190 | E48: Pix | I48: NFC-e 8859 | J48: CLI-0696
A49: 46058 | B49: Consumidor Final | C49: Refil Plissado | D49: 100 | E49: Dinheiro | I49: NFC-e 8860
A50: 46058 | B50: Vitali jacobina Ltda | C50: Refil Everest | D50: 140 | I50: NF-e 4058 · nota faturada a prazo (forma de recebimento não consta na nota) · venda de 04/02/2026 — pagamento recebido em 05/02/2026 | J50: EMP-0305
A51: 46058 | B51: Payaya Loja de Conveniencias e Auto Pecas Ltda | C51: Purificador Everest Slim Preto + 2x Purificador Everest Baby Preto | D51: 2470 | E51: Dinheiro | I51: NF-e 4059
A52: 46058 | B52: Ieda Bahia de Andrade - Tarcisio Bahia | C52: Refil Everest | D52: 140 | E52: Dinheiro | I52: NFC-e 8861 | J52: CLI-0697
A53: 46058 | B53: Pedro Wesley Passos Alves | C53: Purificador Everest Plus Prata | D53: 1501.56 | E53: Dinheiro | I53: NF-e 4060 | J53: CLI-0316
A54: 46059 | B54: Maria Nilzete Santos Carvalho - Florisvaldo Alves Carvalho | C54: Refil Everest | D54: 140 | E54: Crédito Parcelado | I54: NFC-e 8862
A55: 46059 | B55: Matheus Guimarães Oliveira | C55: Refil Everest | D55: 140 | E55: Pix | I55: NFC-e 8863 | J55: CLI-0700
A56: 46059 | B56: Consumidor Final | C56: Refil Everest | D56: 140 | E56: Dinheiro | I56: NFC-e 8864
A57: 46059 | B57: Creuza Miranda Freire - Crisleide | C57: Refil Pro Life | D57: 140 | E57: Dinheiro | I57: NFC-e 8865 | J57: CLI-0701
A58: 46060 | B58: Consumidor Final | C58: Refil Top Color | D58: 80 | E58: Débito | I58: NFC-e 8866
A59: 46060 | B59: Consumidor Final | C59: Refil Universal | D59: 35 | E59: Dinheiro | I59: NFC-e 8867
A60: 46060 | B60: Consumidor Final | C60: Suporte | D60: 40 | E60: Dinheiro | I60: NFC-e 8868
A61: 46060 | B61: Consumidor Final | C61: Refil Pro Life | D61: 140 | E61: Dinheiro | I61: NFC-e 8869
A62: 46062 | B62: Consumidor Final | D62: 135 | I62: Livro Caixa: Recebimento à vista Gerado pelo sistema (Doc. 8870)
A63: 46062 | B63: Luiz Carlos Rodrigues da Silva - Maria Lucia | C63: Refil Pro Life | D63: 135 | E63: Débito | I63: NFC-e 8871
A64: 46062 | B64: Helena Cruz | C64: Refil Everest | D64: 130 | E64: Dinheiro | I64: NFC-e 8872 | J64: CLI-0704
A65: 46062 | B65: Marsilia Marmores e Granitos Erelli | C65: Refil Pro Life | D65: 140 | I65: NF-e 4063 · nota faturada a prazo (forma de recebimento não consta na nota) | J65: EMP-0216
A66: 46062 | B66: Estorno de recebimento — Cielo S. A. | G66: 135 | H66: Estornos de Vendas (Cancelamentos) | I66: Livro Caixa: Estorno de recebimento do documento: Gerado pelo sistema (Doc. 887)
A67: 46063 | B67: Temistocles de Carvalho Andrade | C67: Refil Everest | D67: 140 | E67: Dinheiro | I67: NFC-e 8873 | J67: CLI-0679
A68: 46063 | B68: Papelaria Castro - Itamar Castro Ribeiro LTDA | C68: Refil Pro Life + Pré Filtro | D68: 185 | E68: Dinheiro | I68: NF-e 4064 | J68: EMP-0243
A69: 46063 | B69: Maria Conceição Carvalho Mesquita | D69: 135 | I69: Livro Caixa: Recebimento à vista Gerado pelo sistema (Doc. 8874) | J69: CLI-0702
A70: 46063 | B70: Ronaldo Ferreira dos Anjos - Maria Lucia | C70: Refil Everest | D70: 135 | E70: Pix | I70: NFC-e 8875
A71: 46063 | B71: Consumidor Final | C71: Registro + Mangueira (1 m) | D71: 40 | E71: Crédito Parcelado | I71: NFC-e 8876
A72: 46063 | B72: Kaline Pinto Marques - Stenio Carlos Ribeiro | C72: Refil Everest + Pré Filtro | D72: 200 | E72: Crédito Parcelado | I72: NFC-e 8877
A73: 46063 | B73: Maria José Azevedo de Almeida | C73: Refil Everest | D73: 140 | E73: Dinheiro | I73: NFC-e 8878 | J73: CLI-0706
A74: 46063 | B74: Consumidor Final | C74: Vela Filtro de Barro | D74: 10 | E74: Dinheiro | I74: NFC-e 8879
A75: 46063 | B75: Maria Conceição Carvalho Mesquita | C75: Refil Everest + Refil Pro Life | D75: 270 | E75: Pix | I75: NFC-e 8880 | J75: CLI-0702
A76: 46063 | B76: L A Laboratorio de Analises Matos Ltda | C76: Refil Everest | D76: 140 | I76: NF-e 4065. Recebimento não constava no Livro Caixa; conferido e baixado no DigiSat em 28/09/2026.
A77: 46063 | B77: Estorno de recebimento — Maria Conceicao Carvalho Mesquita Maia - Loane Mesquita | G77: 135 | H77: Estornos de Vendas (Cancelamentos) | I77: Livro Caixa: Estorno de recebimento do documento: Gerado pelo sistema (Doc. 887)
A78: 46064 | B78: Camioneiro Auto Pecas Eireli Epp | C78: Refil Everest + Pré Filtro | D78: 190 | E78: Pix | I78: NF-e 4066
A79: 46064 | B79: Valeria Menezes Almeida | C79: Refil Everest | D79: 140 | E79: Crédito Parcelado | I79: NFC-e 8881
A80: 46064 | B80: Maiara Nascimento Grassi Sangalo - Marcus Antonio | C80: Refil Everest + Pré Filtro + Refil Pro Life | D80: 340 | E80: Pix | I80: NFC-e 8882 | J80: CLI-0711
A81: 46064 | B81: Consumidor Final | C81: Mangueira (2 m) | D81: 20 | E81: Débito | I81: NFC-e 8883
A82: 46064 | B82: Real Calçados | C82: 2x Refil Everest + Refil Pro Life + 2x Pré Filtro | D82: 500 | E82: Dinheiro | I82: NF-e 4067 | J82: EMP-0255
A83: 46064 | B83: Jordana Alves de Lima Ribeiro | C83: Refil Everest | D83: 140 | E83: Crédito Parcelado | I83: NFC-e 8884
A84: 46065 | B84: Patricia Lima Franco Barbosa | C84: Purificador Everest Fit Prata | D84: 1448 | E84: Dinheiro | I84: NF-e 4069 | J84: CLI-0715
A85: 46065 | B85: Rosiane Ferreira Lima / Aldo | C85: Refil Pro Life | D85: 135 | E85: Dinheiro | I85: NFC-e 8885 | J85: CLI-0713
A86: 46065 | B86: Nubia Dantas Silva - Vinicius Silva | C86: Refil Pro Life + Pré Filtro | D86: 200 | E86: Crédito Parcelado | I86: NFC-e 8886
A87: 46066 | B87: Lucelio Pereira do Nascimento | C87: Refil Everest | D87: 130 | E87: Pix | I87: NFC-e 8887 | J87: CLI-0335
A88: 46066 | B88: Carneiro Ultra Drogaria LTDA - Filial 02 | C88: Refil Everest | D88: 140 | E88: Dinheiro | I88: NF-e 4070 | J88: EMP-0044
A89: 46066 | B89: Atacadão das Confecções e Utilidades LTDA | C89: Refil Everest | D89: 140 | E89: Dinheiro | I89: NF-e 4071 | J89: EMP-0018
A90: 46066 | B90: Elisete Pereira da Silva | C90: Refil Everest | D90: 140 | E90: Dinheiro | I90: NFC-e 8888 | J90: CLI-0716
A91: 46066 | B91: Tesla Imagem Medicina Diagnostica Ltda | C91: 3x Refil Everest + 2x Pré Filtro | D91: 540 | I91: NF-e 4062 · nota faturada a prazo (forma de recebimento não consta na nota) · venda de 09/02/2026 — pagamento recebido em 13/02/2026 | J91: EMP-0289
A92: 46066 | B92: Everest Refrigeracao e Industria | G92: 781.4 | H92: Fornecedores / Mercadoria | I92: NF 361446 de 10/10/2025 · parcela 4/5 (venc. 07/02/2026) · compra total R$ 3.906,99: Purificador Everest Fit Preto + Purificador Everest Star Branco + Purificador Everest Star Preto + Purificador Everest Slim Branco + 4x Purificador Everest Baby Branco + 4x Purificador Everest Baby Preto · Livro Caixa
A93: 46066 | B93: Everest Refrigeracao e Industria | G93: 810.99 | H93: Fornecedores / Mercadoria | I93: NF 368012 de 08/01/2026 · parcela 1/5 (venc. 07/02/2026) · compra total R$ 4.054,97: Purificador Everest Fit Branco + 2x Purificador Everest Slim Branco + Purificador Everest Slim Preto + 2x Purificador Everest Star Branco · Livro Caixa
A94: 46066 | B94: Everest Refrigeracao e Industria | G94: 841.06 | H94: Fornecedores / Mercadoria | I94: NF 366264 de 11/12/2025 · parcela 2/5 (venc. 09/02/2026) · compra total R$ 4.205,29: Purificador Everest Slim Branco + Purificador Everest Slim Prata + 2x Purificador Everest Star Branco + Purificador Everest Star Prata + Purificador Everest Plus Prata · Livro Caixa
A95: 46066 | B95: Jamef | G95: 477.32 | H95: Transporte e Entregas | I95: Livro Caixa: Pagamento parcela JAMEF (Doc. 1) · Jamef Transportes Ltda
A96: 46066 | B96: Everest Refrigeracao e Industria | G96: 865.5 | H96: Fornecedores / Mercadoria | I96: NF 368529 de 14/01/2026 · parcela 1/5 (venc. 13/02/2026) · compra total R$ 4.327,52: Purificador Everest Plus Branco + Purificador Everest Plus Prata + Purificador Everest Star Prata + Purificador Everest Slim Prata + Purificador Everest Fit Prata + Purificador Everest Fit Branco · Livro Caixa
A97: 46067 | B97: Neide Ferreira de Jesus | C97: Refil Everest | D97: 140 | E97: Pix | I97: NFC-e 8889 | J97: CLI-0717
A98: 46067 | B98: Consumidor Final | C98: 2x Refil FPA14 | D98: 175 | E98: Pix | I98: NFC-e 8890
A99: 46067 | B99: Consumidor Final | C99: Carcaça 9" + Refil Carbon Tech 5" | D99: 150 | E99: Dinheiro | I99: NFC-e 8891
A100: 46067 | B100: Consumidor Final | C100: Conexao Em T Rosca De 1/2 Com Engate Rapido Reto 1/4 X 1/4 | D100: 37 | E100: Crédito Parcelado | I100: NFC-e 8892
...

Sheet Mar 2026
A1: RELATÓRIO FINANCEIRO — MARÇO / 2026
A2: Fluxo de caixa da loja — entradas montadas a partir das notas fiscais (XML do DigiSat), com cliente e produtos; saídas do Livro Caixa
A3: ← Início
A4: Data | B4: Descrição / Cliente | C4: Produto | D4: Entrada (R$) | E4: Forma de Pagamento | F4: Taxa da Máquina (R$) | G4: Saída (R$) | H4: Categoria da Saída | I4: Observações | J4: ID Cliente | K4: Saídas por Categoria | N4: FATURAMENTO | P4: DESPESAS | R4: SALDO ANTES DO PRÓ-LABORE | T4: A RECEBER
A5: 46082 | B5: Aluguel Vitoria Maria | G5: 870 | H5: Aluguel | I5: Livro Caixa: Pagamento à vista: ALUGUEL VITORIA MARIA (Doc. 1) · Vitoria Maria F Santos | K5: Fornecedores / Mercadoria | L5: =SUMIF(H5:H126,K5,G5:G126) | N5: =D127-F127-T5 | P5: =L18-L19 | R5: =D128 | T5: =SUMIF(E5:E126,"Aguardando Pagamento",D5:D126)
A6: 46083 | B6: Consumidor Final | C6: Mangueira (1 m) | D6: 10 | E6: Dinheiro | I6: NFC-e 8913 | K6: Aluguel | L6: =SUMIF(H5:H126,K6,G5:G126)
A7: 46083 | B7: Consumidor Final | C7: Mangueira (1 m) | D7: 7 | E7: Pix | I7: NFC-e 8914 | K7: Água, Energia e Internet | L7: =SUMIF(H5:H126,K7,G5:G126) | N7: PRÓ-LABORE EDILÂNIA | P7: COMBINADO NO MÊS | R7: =IF(L17>'Ponto de Equilíbrio'!$B$10,"PASSOU DO COMBINADO",IF(TODAY()>EOMONTH(DATE(2026,3,1),0),"ABAIXO DO COMBINADO","AINDA PODE GASTAR")) | T7: SOBRA FINAL DO MÊS
A8: 46084 | B8: Lucas Souza | C8: Refil Everest | D8: 140 | E8: Pix | I8: NF-e 4093 | J8: CLI-0494 | K8: Impostos e Taxas | L8: =SUMIF(H5:H126,K8,G5:G126) | N8: =L17 | P8: ='Ponto de Equilíbrio'!$B$10 | R8: =ABS('Ponto de Equilíbrio'!$B$10-L17) | T8: =R5-L17
A9: 46085 | B9: Lidia Maria Cardoso Silva | C9: Purificador Everest Slim Branco | D9: 1200 | E9: Dinheiro | I9: NF-e 4094 | J9: CLI-0740 | K9: Tarifas Bancárias e Cartão | L9: =SUMIF(H5:H126,K9,G5:G126)
A10: 46085 | B10: Consumidor Final | C10: Refil BAG | D10: 50 | E10: Dinheiro | I10: NFC-e 8915 | K10: Transporte e Entregas | L10: =SUMIF(H5:H126,K10,G5:G126)
A11: 46085 | B11: Jackson Macedo de Sales | C11: Refil Carbon Tech 9" | D11: 60 | E11: Dinheiro | I11: NF-e 4095 | K11: Salários, Comissões e Encargos | L11: =SUMIF(H5:H126,K11,G5:G126)
A12: 46085 | B12: Juliana Monteiro | C12: Refil Everest | D12: 140 | E12: Pix | I12: NFC-e 8916 | J12: CLI-0737 | K12: Contabilidade | L12: =SUMIF(H5:H126,K12,G5:G126)
A13: 46085 | B13: Banco do Nordeste do Brasil | C13: Refil Everest + Pré Filtro | D13: 200 | E13: Dinheiro | I13: NF-e 4097 | J13: EMP-0220 | K13: Manutenção e Reparos | L13: =SUMIF(H5:H126,K13,G5:G126)
A14: 46085 | B14: Centro de Cultura Anglo Americano de Jacobina LTDA - CCAA | C14: Refil Pro Life | D14: 120 | E14: Dinheiro | I14: NF-e 4098 | J14: EMP-0057 | K14: Material de Limpeza e Escritório | L14: =SUMIF(H5:H126,K14,G5:G126)
A15: 46085 | B15: Banco do Nordeste do Brasil | G15: 200 | H15: Outras Despesas | I15: Livro Caixa: Pagamento à vista: Gerado pelo sistema. (Doc. 4096) | K15: Estornos de Vendas (Cancelamentos) | L15: =SUMIF(H5:H126,K15,G5:G126)
A16: 46086 | B16: Eduardo da Cruz Cardoso Gomes | C16: Refil Everest | D16: 140 | E16: Crédito Parcelado | I16: NFC-e 8917 | K16: Outras Despesas | L16: =SUMIF(H5:H126,K16,G5:G126)
A17: 46087 | B17: Jacira do Carmo de Oliveira | C17: Purificador Everest Baby Preto | D17: 478 | E17: Dinheiro | I17: NF-e 4099 | J17: CLI-0742 | K17: Pro Labore Edilânia | L17: =SUMIF(H5:H126,K17,G5:G126)
A18: 46088 | B18: Danilo Pereira Santos (Oficina) | C18: Purificador Everest Slim Prata | D18: 1348 | E18: Dinheiro | I18: NF-e 4101 | J18: CLI-0507 | K18: Total | L18: =SUM(L5:L16)
A19: 46088 | B19: Eva Lages Matos de Freitas | C19: Refil Everest | D19: 70 | I19: NFC-e 8918 · venda de 07/03/2026, total R$ 140,00 — parcela 1 · nota faturada a prazo (forma de recebimento não consta na nota) | J19: CLI-0741 | K19: Capital de Giro (BB) — ainda a devolver | L19: =SUMIFS('Capital de Giro (BB)'!D9:D200,'Capital de Giro (BB)'!A9:A200,">="&DATE(2026,3,1),'Capital de Giro (BB)'!A9:A200,"<="&DATE(2026,3,31),'Capital de Giro (BB)'!E9:E200,"A Devolver")
A20: 46090 | B20: Paulo Vitor Biulchi dos Santos | C20: Refil Everest | D20: 140 | E20: Pix | I20: NFC-e 8919 | J20: CLI-0747
A21: 46090 | B21: Carmen Steffens - Lucia Maria Oliveira Silva Dias EPP | C21: Refil Pro Life | D21: 140 | I21: NF-e 4100 · nota faturada a prazo (forma de recebimento não consta na nota) · venda de 06/03/2026 — pagamento recebido em 09/03/2026 | J21: EMP-0039
A22: 46090 | B22: Adilson Brasileiro dos Santos | C22: Refil Everest | D22: 140 | E22: Pix | I22: NFC-e 8920 | J22: CLI-0746
A23: 46090 | B23: Consumidor Final | C23: Refil Carbon Tech 9" | D23: 80 | E23: Dinheiro | I23: NFC-e 8921
A24: 46090 | B24: Eric Rodrigo Lopes Ribeiro | C24: Refil Pro Life + Pré Filtro | D24: 200 | E24: Crédito Parcelado | I24: NFC-e 8922
A25: 46090 | B25: Consumidor Final | C25: Mangueira (2 m) | D25: 18 | E25: Dinheiro | I25: NFC-e 8923
A26: 46090 | B26: Serviço Nacional de Apredizagem Comercial - Senac | C26: Refil Everest | D26: 140 | I26: NF-e 4061 · nota faturada a prazo (forma de recebimento não consta na nota) · venda de 06/02/2026 — pagamento recebido em 09/03/2026 | J26: EMP-0276
A27: 46090 | B27: DrillGeo Geologia e Sondagens | C27: Refil Carbon Tech 9" + Refil Plissado | D27: 180 | I27: NF-e 4073 · nota faturada a prazo (forma de recebimento não consta na nota) · venda de 18/02/2026 — pagamento recebido em 09/03/2026 | J27: EMP-0125
A28: 46091 | B28: Leticia Santos Silva | C28: Refil Pro Life | D28: 140 | E28: Crédito Parcelado | I28: NFC-e 8924
A29: 46091 | B29: Ronaldo Nascimento Santos | C29: Refil Pro Life | D29: 140 | E29: Crédito Parcelado | I29: NFC-e 8925
A30: 46091 | B30: Centro Medico Boa Saude | C30: Refil Everest | D30: 140 | E30: Pix | I30: NF-e 4102 | J30: EMP-0061
A31: 46091 | B31: DFLL Serviços Medicos Ltda - ImCardio - Instituto Materno Cardiologico | C31: 2x Refil Everest + 2x Pré Filtro | D31: 380 | E31: Dinheiro | I31: NF-e 4103 | J31: EMP-0116
A32: 46092 | B32: Emperi Odontologia | C32: 2x Refil Everest | D32: 280 | E32: Dinheiro | I32: NF-e 4104 | J32: EMP-0134
A33: 46092 | B33: Uillian Tarçio Lopes Brito | C33: Refil Everest | D33: 140 | E33: Pix | I33: NFC-e 8926 | J33: CLI-0752
A34: 46093 | B34: Consumidor Final | C34: Refil Carbon Tech 9" | D34: 60 | E34: Dinheiro | I34: NFC-e 8927
A35: 46093 | B35: Consumidor Final | C35: Refil Carbon Tech 9" | D35: 85 | E35: Crédito Parcelado | I35: NFC-e 8928
A36: 46093 | B36: Consumidor Final | C36: 2x Vela Filtro de Barro | D36: 24 | E36: Débito | I36: NFC-e 8929
A37: 46093 | B37: Consumidor Final | C37: Refil CP500 BR | D37: 90 | E37: Débito | I37: NFC-e 8930
A38: 46093 | B38: Everest Refrigeracao e Industria | G38: 781.39 | H38: Fornecedores / Mercadoria | I38: NF 361446 de 10/10/2025 · parcela 5/5 (venc. 09/03/2026) · compra total R$ 3.906,99: Purificador Everest Fit Preto + Purificador Everest Star Branco + Purificador Everest Star Preto + Purificador Everest Slim Branco + 4x Purificador Everest Baby Branco + 4x Purificador Everest Baby Preto · Livro Caixa
A39: 46093 | B39: Everest Refrigeracao e Industria | G39: 810.99 | H39: Fornecedores / Mercadoria | I39: NF 368012 de 08/01/2026 · parcela 2/5 (venc. 09/03/2026) · compra total R$ 4.054,97: Purificador Everest Fit Branco + 2x Purificador Everest Slim Branco + Purificador Everest Slim Preto + 2x Purificador Everest Star Branco · Livro Caixa
A40: 46093 | B40: Everest Refrigeracao e Industria | G40: 841.06 | H40: Fornecedores / Mercadoria | I40: NF 366264 de 11/12/2025 · parcela 3/5 (venc. 11/03/2026) · compra total R$ 4.205,29: Purificador Everest Slim Branco + Purificador Everest Slim Prata + 2x Purificador Everest Star Branco + Purificador Everest Star Prata + Purificador Everest Plus Prata · Livro Caixa
A41: 46093 | B41: Jamef | G41: 708.72 | H41: Transporte e Entregas | I41: Livro Caixa: Pagamento parcela JAMEF (Doc. 1) · Jamef Transportes Ltda
A42: 46093 | B42: Culligan Latam Eireli | G42: 1391.96 | H42: Fornecedores / Mercadoria | I42: NF 132866 de 10/02/2026 · parcela 1/3 (venc. 12/03/2026) · compra total R$ 4.176,30: 30x Filtro De Agua Protection Lacrado + 50x Cofilter Lacrado - Pre C + 30x Filtro De Agua Natural Max + 10x Filtro De Agua Natural Lacrado · Livro Caixa
A43: 46093 | B43: Conta de Energia Loja | G43: 139.92 | H43: Água, Energia e Internet | I43: Livro Caixa: Pagamento parcela CONTA DE ENERGIA LOJA (Doc. 1) · Companhia de Eletricidade do Estado da Bahia Coelba
A44: 46094 | B44: Jamille Oliveira Sousa Santos - Paulo Orlando | C44: Refil Everest | D44: 145 | E44: Crédito Parcelado | I44: NFC-e 8931
A45: 46094 | B45: Carneiro Ultra Drogaria LTDA - Filial 01 | C45: Refil Everest + Pré Filtro | D45: 200 | E45: Dinheiro | I45: NF-e 4106 | J45: EMP-0043
A46: 46095 | B46: Jairo Cesar Moro | C46: Purificador Everest Star Branco | D46: 1398 | E46: Dinheiro | I46: NF-e 4107 | J46: CLI-0755
A47: 46095 | B47: RF Supermercado Brasil LTDA | C47: Refil E3 + 2x Refil Everest | D47: 370 | I47: NF-e 4085 · nota faturada a prazo (forma de recebimento não consta na nota) · venda de 27/02/2026 — pagamento recebido em 14/03/2026 | J47: EMP-0261
A48: 46095 | B48: RF Supermercado Brasil LTDA | C48: 3x Refil Everest | D48: 420 | I48: NF-e 4086 · nota faturada a prazo (forma de recebimento não consta na nota) · venda de 27/02/2026 — pagamento recebido em 14/03/2026 | J48: EMP-0261
A49: 46097 | B49: L.C. Servicos e Transporte Ltda | C49: Bebedouro industrial 25L | D49: 2500 | E49: Pix | I49: NF-e 4108
A50: 46097 | B50: Consumidor Final | C50: Refil Plissado + Refil FP4 | D50: 165 | E50: Pix | I50: NFC-e 8932
A51: 46098 | B51: Jacy Lima da Silva | C51: Refil Everest | D51: 140 | E51: Dinheiro | I51: NFC-e 8933 | J51: CLI-0756
A52: 46098 | B52: Sara Andreia Barros de Souza Santana - Escola Educare | C52: Refil Everest | D52: 135 | E52: Pix | I52: NF-e 4109 | J52: EMP-0272
A53: 46098 | B53: Consumidor Final | C53: Refil Everest + Mangueira (1 m) | D53: 150 | E53: Pix | I53: NFC-e 8934
A54: 46098 | B54: Consumidor Final | C54: Refil Everest | D54: 140 | E54: Pix | I54: NFC-e 8935
A55: 46098 | B55: Moab Lima Rios | C55: Refil Everest | D55: 140 | E55: Pix | I55: NFC-e 8936 | J55: OUT-0066
A56: 46098 | B56: Consumidor Final | C56: Mangueira (1 m) | D56: 10 | E56: Dinheiro | I56: NFC-e 8937
A57: 46098 | B57: Consumidor Final | C57: Refil FPA14 | D57: 95 | E57: Crédito Parcelado | I57: NFC-e 8938
A58: 46098 | B58: Farmacia Dois de Julho - José Tiago Souza | C58: Refil Everest | D58: 140 | E58: Dinheiro | I58: NFC-e 8939 | J58: EMP-0144
A59: 46098 | B59: Sandra Maria Vieira Moreira Araújo | C59: Purificador Everest Fit Prata | D59: 1300 | E59: Pix | I59: NF-e 4110 | J59: CLI-0758
A60: 46099 | B60: Aspec Sociedade Paraibana de Educacao e Cultura Ltda | C60: 24x Refil IBBL C+3 | D60: 3000 | I60: NF-e 4089 · nota faturada a prazo (forma de recebimento não consta na nota) · venda de 27/02/2026 — pagamento recebido em 18/03/2026
A61: 46099 | B61: Regina Cleia Cavalcant Ribeiro - Matheus Ribeiro | C61: Refil Everest + Pré Filtro + Mangueira (1 m) | D61: 210 | E61: Crédito Parcelado | I61: NFC-e 8940
A62: 46099 | B62: Consumidor Final | C62: Refil Everest | D62: 140 | E62: Pix | I62: NFC-e 8941
A63: 46099 | B63: Valnice Jacobina Ribeiro Oliveira | C63: Refil Everest | D63: 140 | E63: Crédito Parcelado | I63: NFC-e 8942
A64: 46099 | B64: Consumidor Final | C64: Refil FP4 | D64: 80 | E64: Pix | I64: NFC-e 8943
A65: 46099 | B65: Consumidor Final | C65: Bico Rio | D65: 25 | E65: Pix | I65: NFC-e 8944
A66: 46100 | B66: Consumidor Final | C66: Refil Top Color | D66: 95 | E66: Crédito Parcelado | I66: NFC-e 8945
A67: 46100 | B67: Consumidor Final | C67: Refil Acquatec | D67: 85 | E67: Pix | I67: NFC-e 8946
A68: 46100 | B68: Newnet Consultoria e Informatica Ltda | C68: Refil Acquatec | D68: 90 | I68: NF-e 4111. Recebimento não constava no Livro Caixa; conferido e baixado no DigiSat em 28/09/2026.
A69: 46101 | B69: Igreja Adventista Jacobina | C69: Refil Everest | D69: 140 | E69: Dinheiro | I69: NF-e 4112 | J69: EMP-0020
A70: 46101 | B70: Ordem dos Advogados do Brasil Subsecao Jacobina Ba | C70: 2x Refil Pro Life | D70: 280 | I70: NF-e 4105 · nota faturada a prazo (forma de recebimento não consta na nota) · venda de 12/03/2026 — pagamento recebido em 20/03/2026
A71: 46101 | B71: David Dantas Martins Mendes | C71: Refil Everest | D71: 140 | E71: Pix | I71: NF-e 4113
A72: 46101 | B72: Caio Cesar Souza Santos - Js Material de Construcao | C72: Refil Everest | D72: 140 | E72: Crédito Parcelado | I72: NFC-e 8947
A73: 46101 | B73: George Martins Silva | C73: Refil Everest + Pré Filtro | D73: 200 | E73: Pix | I73: NFC-e 8948 | J73: CLI-0763
A74: 46101 | B74: Darline de Oliveira Almeida Liro | C74: Refil Everest | D74: 130 | E74: Pix | I74: NFC-e 8949 | J74: CLI-0765
A75: 46101 | B75: Patios Nordeste Jacobina Spe Ltda | C75: Refil Top Color | D75: 95 | E75: Dinheiro | I75: NF-e 4114
A76: 46101 | B76: Everest Refrigeracao e Industria | G76: 865.5 | H76: Fornecedores / Mercadoria | I76: NF 368529 de 14/01/2026 · parcela 2/5 (venc. 15/03/2026) · compra total R$ 4.327,52: Purificador Everest Plus Branco + Purificador Everest Plus Prata + Purificador Everest Star Prata + Purificador Everest Slim Prata + Purificador Everest Fit Prata + Purificador Everest Fit Branco · Livro Caixa
A77: 46101 | B77: Tarcisio Oliveira Lima | G77: 486.32 | H77: Contabilidade | I77: Livro Caixa: Pagamento parcela TARCISIO OLIVEIRA LIMA (Doc. 1) · Tarcisio Oliveira Lima
A78: 46101 | B78: Filtros Planeta Agua Ind e Com Ltda | G78: 420.87 | H78: Fornecedores / Mercadoria | I78: NF 126565 de 20/01/2026 · parcela 3/4 (venc. 17/03/2026) · compra total R$ 1.771,04 (IPI R$ 87,54): 65x Refil Pro Life · Livro Caixa
A79: 46101 | B79: Fgts | G79: 267.2 | H79: Impostos e Taxas | I79: Livro Caixa: Pagamento parcela FGTS (Doc. 1) · Planeta Agua Ltda
A80: 46101 | B80: Receitas Federais | G80: 430.27 | H80: Impostos e Taxas | I80: Livro Caixa: Pagamento parcela RECEITAS FEDERAIS (Doc. 2) · Planeta Agua Ltda
A81: 46101 | B81: Simples Nacional | G81: 1829.8 | H81: Impostos e Taxas | I81: Livro Caixa: Pagamento parcela SIMPLES NACIONAL (Doc. 1) · Planeta Agua Ltda
A82: 46102 | B82: Socec - Sociedade Capibaribe de Educacao e Cultura S/A | C82: 8x Refil IBBL C+3 | D82: 1040 | E82: Pix | I82: NF-e 4088 · Grupo Ânima — venda de 27/02/2026, Nota Paga no portal V360 em 21/03/2026. Recebimento não constava no Livro Caixa; baixa dada no DigiSat em 28/09/2026.
A83: 46104 | B83: Maria do Carmo Mendes | C83: Refil Everest | D83: 130 | E83: Dinheiro | I83: NFC-e 8950 | J83: OUT-0061
A84: 46104 | B84: Central do Suplemento | C84: Refil Everest | D84: 140 | E84: Dinheiro | I84: NF-e 4116 | J84: EMP-0055
A85: 46104 | B85: Antonio Cesar Freitas Souza | C85: Refil Pro Life | D85: 140 | E85: Crédito Parcelado | I85: NFC-e 8951
A86: 46104 | B86: Consumidor Final | C86: 2x Refil Acquatec | D86: 190 | E86: Crédito Parcelado | I86: NFC-e 8952
A87: 46104 | B87: Centro de Estudos Calmonense | C87: Refil CP500 BR | D87: 90 | E87: Pix | I87: NF-e 4117 | J87: OUT-0011
A88: 46104 | B88: Jose Alfredo de Oliveira Alkim - Maiara de Souza | C88: Refil Everest + Pré Filtro | D88: 200 | E88: Crédito Parcelado | I88: NFC-e 8953
A89: 46106 | B89: Jose Luciano Vieira Costa | C89: 2x Refil Everest | D89: 280 | E89: Dinheiro | I89: NF-e 4119
A90: 46106 | B90: Centro Medico de Jacobina LTDA - Clinica Santa Barbara | C90: 3x Refil Everest | D90: 420 | I90: NF-e 4120 · nota faturada a prazo (forma de recebimento não consta na nota) | J90: EMP-0063
A91: 46106 | B91: Metrica Construção Ltda | C91: Refil Everest + Mangueira (2 m) | D91: 160 | E91: Dinheiro | I91: NF-e 4121 | J91: EMP-0221
A92: 46106 | B92: Consumidor Final | C92: Refil Universal | D92: 30 | E92: Dinheiro | I92: NFC-e 8954
A93: 46106 | B93: Consumidor Final | C93: Refil Universal | D93: 26 | E93: Crédito Parcelado | I93: NFC-e 8955
A94: 46106 | B94: Vera Lucia Gomes Sampaio (Igreja Quadrangular) | C94: Purificador Everest Plus Branco | D94: 1500 | E94: Dinheiro | I94: NF-e 4122 | J94: CLI-0520
A95: 46106 | B95: Climo Clínica Médica Oftalmológica Ldta - Aloisio Sales | C95: Purificador Everest Star Branco | D95: 1298 | I95: NF-e 4118 · nota faturada a prazo (forma de recebimento não consta na nota) · venda de 24/03/2026 — pagamento recebido em 25/03/2026 | J95: EMP-0067
A96: 46107 | B96: R. M. Laboratorio Ltda. | C96: Refil Everest + Pré Filtro | D96: 200 | I96: NF-e 4123 · nota faturada a prazo (forma de recebimento não consta na nota) · venda de 25/03/2026 — pagamento recebido em 26/03/2026
A97: 46107 | B97: Paulo Diogenes de Oliveira Eireli | C97: Refil Everest | D97: 135 | E97: Dinheiro | I97: NF-e 4124
A98: 46107 | B98: Ages Educação Ltda - Irecê | C98: 2x Pré Filtro IBBL + 2x Refil IBBL C+3 | D98: 580 | I98: NF-e 4125 · nota faturada a prazo (forma de recebimento não consta na nota) | J98: ESC-0005
A99: 46107 | B99: Everest Refrigeracao e Industria | G99: 800.64 | H99: Fornecedores / Mercadoria | I99: NF 362188 de 22/10/2025 · parcela 5/5 (venc. 21/03/2026) · compra total R$ 4.003,24: Purificador Everest Fit Branco + Purificador Everest Fit Prata + Purificador Everest Slim Branco + Purificador Everest Slim Prata + Purificador Everest Star Branco + 4x Purificador Everest Baby Cereja · Livro Caixa
A100: 46107 | B100: Eversoft Ind e Com de Plasticos Ltda | G100: 878.93 | H100: Fornecedores / Mercadoria | I100: NF 68349 de 24/10/2025 · parcela 5/5 (venc. 23/03/2026) · compra total R$ 4.394,61: 100x Refil Everest · Livro Caixa
...

Sheet Abr 2026
A1: RELATÓRIO FINANCEIRO — ABRIL / 2026
A2: Fluxo de caixa da loja — entradas montadas a partir das notas fiscais (XML do DigiSat), com cliente e produtos; saídas do Livro Caixa
A3: ← Início
A4: Data | B4: Descrição / Cliente | C4: Produto | D4: Entrada (R$) | E4: Forma de Pagamento | F4: Taxa da Máquina (R$) | G4: Saída (R$) | H4: Categoria da Saída | I4: Observações | J4: ID Cliente | K4: Saídas por Categoria | N4: FATURAMENTO | P4: DESPESAS | R4: SALDO ANTES DO PRÓ-LABORE | T4: A RECEBER
A5: 46113 | B5: Tatiana Miranda Siqueira | C5: Refil Everest + Mangueira (1 m) | D5: 150 | E5: Pix | I5: NF-e 4138 | J5: CLI-0696 | K5: Fornecedores / Mercadoria | L5: =SUMIF(H5:H132,K5,G5:G132) | N5: =D133-F133-T5 | P5: =L18-L19 | R5: =D134 | T5: =SUMIF(E5:E132,"Aguardando Pagamento",D5:D132)
A6: 46113 | B6: Consumidor Final | C6: Refil Everest | D6: 130 | E6: Dinheiro | I6: NFC-e 8960 | K6: Aluguel | L6: =SUMIF(H5:H132,K6,G5:G132)
A7: 46113 | B7: Rui Robson Ferreira Andrade - Maria lucia | C7: Purificador Everest Fit Branco | D7: 1348 | E7: Dinheiro | I7: NF-e 4139 | J7: CLI-0754 | K7: Água, Energia e Internet | L7: =SUMIF(H5:H132,K7,G5:G132) | N7: PRÓ-LABORE EDILÂNIA | P7: COMBINADO NO MÊS | R7: =IF(L17>'Ponto de Equilíbrio'!$B$10,"PASSOU DO COMBINADO",IF(TODAY()>EOMONTH(DATE(2026,4,1),0),"ABAIXO DO COMBINADO","AINDA PODE GASTAR")) | T7: SOBRA FINAL DO MÊS
A8: 46113 | B8: Embasa Adriano | G8: 51.61 | H8: Pro Labore Edilânia | I8: Livro Caixa: Pagamento parcela EMBASA ADRIANO (Doc. 1) · Empresa Baiana de Aguas e Saneamento Sa | K8: Impostos e Taxas | L8: =SUMIF(H5:H132,K8,G5:G132) | N8: =L17 | P8: ='Ponto de Equilíbrio'!$B$10 | R8: =ABS('Ponto de Equilíbrio'!$B$10-L17) | T8: =R5-L17
A9: 46113 | B9: Aluguel Vitoria Maria | G9: 870 | H9: Aluguel | I9: Livro Caixa: Pagamento à vista: ALUGUEL VITORIA MARIA (Doc. 1) · Vitoria Maria F Santos | K9: Tarifas Bancárias e Cartão | L9: =SUMIF(H5:H132,K9,G5:G132)
A10: 46114 | B10: Consumidor Final | C10: Registro + Mangueira (1 m) | D10: 40 | E10: Dinheiro | I10: NFC-e 8961 | K10: Transporte e Entregas | L10: =SUMIF(H5:H132,K10,G5:G132)
A11: 46114 | B11: Consumidor Final | C11: Refil Acquatec + Refil Universal | D11: 125 | E11: Débito | I11: NFC-e 8962 | K11: Salários, Comissões e Encargos | L11: =SUMIF(H5:H132,K11,G5:G132)
A12: 46114 | B12: Climo Clínica Médica Oftalmológica Ldta - Aloisio Sales | C12: Refil Everest | D12: 140 | E12: Dinheiro | I12: NF-e 4141 | J12: EMP-0067 | K12: Contabilidade | L12: =SUMIF(H5:H132,K12,G5:G132)
A13: 46115 | B13: Apec - Sociedade Potiguar de Educacao e Cultura Ltda | C13: 2x Refil IBBL C+3 + Pré Filtro IBBL | D13: 440 | E13: Pix | I13: NF-e 4091 · Grupo Ânima — venda de 02/03/2026, Nota Paga no portal V360 em 03/04/2026. Recebimento não constava no Livro Caixa; baixa dada no DigiSat em 28/09/2026. | K13: Manutenção e Reparos | L13: =SUMIF(H5:H132,K13,G5:G132)
A14: 46116 | B14: Apec - Sociedade Potiguar de Educacao e Cultura Ltda | C14: 3x Pré Filtro IBBL + 3x Refil IBBL C+3 | D14: 870 | E14: Pix | I14: NF-e 4092 · Grupo Ânima — venda de 02/03/2026, Nota Paga no portal V360 em 04/04/2026. Recebimento não constava no Livro Caixa; baixa dada no DigiSat em 28/09/2026. | K14: Material de Limpeza e Escritório | L14: =SUMIF(H5:H132,K14,G5:G132)
A15: 46118 | B15: Consumidor Final | C15: Refil Everest + Pré Filtro | D15: 150 | E15: Crédito Parcelado | I15: NFC-e 8963 | K15: Estornos de Vendas (Cancelamentos) | L15: =SUMIF(H5:H132,K15,G5:G132)
A16: 46118 | B16: Consumidor Final | C16: Refil Everest | D16: 140 | E16: Pix | I16: NFC-e 8964 | K16: Outras Despesas | L16: =SUMIF(H5:H132,K16,G5:G132)
A17: 46118 | B17: Jucileide Texeira Gama Costa | C17: Refil Everest | D17: 140 | E17: Pix | I17: NFC-e 8965 | J17: CLI-0774 | K17: Pro Labore Edilânia | L17: =SUMIF(H5:H132,K17,G5:G132)
A18: 46118 | B18: Maria Margareth Almeida Santos | C18: Refil Everest | D18: 140 | E18: Dinheiro | I18: NF-e 4142 | J18: CLI-0776 | K18: Total | L18: =SUM(L5:L16)
A19: 46118 | B19: Carneiro e Silva Ltda - Farmacia Santo Antonio | C19: Refil Everest | D19: 130 | E19: Dinheiro | I19: NF-e 4143 | J19: EMP-0040 | K19: Capital de Giro (BB) — ainda a devolver | L19: =SUMIFS('Capital de Giro (BB)'!D9:D200,'Capital de Giro (BB)'!A9:A200,">="&DATE(2026,4,1),'Capital de Giro (BB)'!A9:A200,"<="&DATE(2026,4,30),'Capital de Giro (BB)'!E9:E200,"A Devolver")
A20: 46118 | B20: Mariano Paulo Farias | C20: Refil Everest + Mangueira (1 m) | D20: 140 | E20: Dinheiro | I20: NFC-e 8966 | J20: CLI-0778
A21: 46118 | B21: Maria Margareth Almeida Santos | C21: Refil Pro Life | D21: 140 | E21: Crédito Parcelado | I21: NFC-e 8967
A22: 46118 | B22: Socec - Sociedade Capibaribe de Educacao e Cultura Ltda | C22: 20x Refil IBBL C+3 | D22: 2600 | E22: Pix | I22: NF-e 4090 · Grupo Ânima — venda de 02/03/2026, Nota Paga no portal V360 em 06/04/2026. Recebimento não constava no Livro Caixa; baixa dada no DigiSat em 28/09/2026.
A23: 46119 | B23: Consumidor Final | C23: 4x Refil Plissado + 2x Carcaça 9" + Suporte Metal Duplo Fit | D23: 630 | E23: Crédito Parcelado | I23: NFC-e 8968
A24: 46119 | B24: Margarida Mesquita | C24: Refil Pro Life | D24: 140 | E24: Dinheiro | I24: NFC-e 8969 | J24: CLI-0777
A25: 46119 | B25: Valdeci Souza Silva | C25: Refil Pro Life | D25: 70 | I25: NFC-e 8970 · venda de 07/04/2026, total R$ 140,00 — parcela 1 · nota faturada a prazo (forma de recebimento não consta na nota) | J25: CLI-0779
A26: 46119 | B26: Cor e Fest | C26: Refil Everest + Pré Filtro | D26: 200 | E26: Dinheiro | I26: NF-e 4145 | J26: EMP-0109
A27: 46119 | B27: Unilatus Servico Educacional Ltda Me | C27: Refil Pro Life + Pré Filtro + Suporte | D27: 240 | I27: NF-e 4144. Recebimento não constava no Livro Caixa; conferido e baixado no DigiSat em 28/09/2026.
A28: 46120 | B28: Iristela Miranda Paiva | C28: Purificador Everest Fit Preto | D28: 1448 | E28: Dinheiro | I28: NF-e 4146 | J28: CLI-0780
A29: 46120 | B29: Frutos de Goiás - Rivael Sousa Santos | C29: 2x Refil Everest + Pré Filtro | D29: 320 | E29: Dinheiro | I29: NFC-e 8971 | J29: EMP-0312
A30: 46120 | B30: Maria Conceição | C30: Refil Pro Life | D30: 140 | E30: Pix | I30: NFC-e 8972 | J30: CLI-0297
A31: 46121 | B31: Itan Souza Nascimento | C31: Refil Everest | D31: 140 | E31: Dinheiro | I31: NFC-e 8973 | J31: CLI-0781
A32: 46121 | B32: Consumidor Final | C32: Refil PP | D32: 65 | E32: Pix | I32: NFC-e 8974
A33: 46121 | B33: Consumidor Final | C33: Vela Filtro de Barro | D33: 12 | E33: Débito | I33: NFC-e 8975
A34: 46121 | B34: Consumidor Final | C34: Mangueira (2 m) | D34: 20 | E34: Débito | I34: NFC-e 8976
A35: 46122 | B35: Consumidor Final | C35: Refil Pro Life | D35: 140 | E35: Dinheiro | I35: NFC-e 8977
A36: 46122 | B36: Consumidor Final | C36: Vela Filtro de Barro | D36: 10 | E36: Dinheiro | I36: NFC-e 8978
A37: 46123 | B37: Jaqueline Carneiro - Agripina | C37: Refil Everest + Bico Rio | D37: 170 | E37: Pix | I37: NFC-e 8979 | J37: CLI-0782
A38: 46125 | B38: Joseni Menezes Almeida | C38: Refil Everest | D38: 140 | E38: Crédito Parcelado | I38: NFC-e 8980
A39: 46125 | B39: Adailton Sampaio Avelino | C39: Refil Pro Life | D39: 140 | E39: Pix | I39: NFC-e 8981 | J39: CLI-0787
A40: 46125 | B40: Empresa Sertaneja de Hoteis Ltda - Hotel Serra do Ouro | C40: Refil Everest + Mangueira (5 m) | D40: 195 | E40: Pix | I40: NF-e 4148 | J40: EMP-0136
A41: 46125 | B41: Jco Industria de Cosmeticos Ltda | C41: Purificador Everest Plus Branco | D41: 1498 | E41: Dinheiro | I41: NF-e 4149
A42: 46125 | B42: Culligan Latam Eireli | G42: 1391.96 | H42: Fornecedores / Mercadoria | I42: NF 132866 de 10/02/2026 · parcela 2/3 (venc. 13/04/2026) · compra total R$ 4.176,30: 30x Filtro De Agua Protection Lacrado + 50x Cofilter Lacrado - Pre C + 30x Filtro De Agua Natural Max + 10x Filtro De Agua Natural Lacrado · Livro Caixa
A43: 46126 | B43: Vania Menezes de Almeida | C43: Refil Pro Life | D43: 140 | E43: Crédito Parcelado | I43: NFC-e 8982
A44: 46126 | B44: Ana Rosa Pereira de Oliveira | C44: Refil Pro Life | D44: 210 | E44: Crédito Parcelado | I44: NFC-e 8983
A45: 46126 | B45: Rosa Meire Pinto Miranda | C45: Refil Everest | D45: 140 | E45: Débito | I45: NFC-e 8984
A46: 46126 | B46: Francisco Assis Menezes Oliveira | C46: Refil Everest | D46: 140 | E46: Débito | I46: NFC-e 8985
A47: 46126 | B47: Consumidor Final | C47: Refil Carbon Tech 9" | D47: 80 | E47: Dinheiro | I47: NFC-e 8986
A48: 46126 | B48: Mais Fono Terapias Ltda | C48: Refil Acquatec + Refil Everest | D48: 230 | I48: NF-e 4150. Recebimento não constava no Livro Caixa; conferido e baixado no DigiSat em 28/09/2026. | J48: EMP-0212
A49: 46127 | B49: RF Supermercado Brasil LTDA | C49: 3x Refil Pro Life | D49: 420 | I49: NF-e 4074 · nota faturada a prazo (forma de recebimento não consta na nota) · venda de 19/02/2026 — pagamento recebido em 15/04/2026 | J49: EMP-0261
A50: 46127 | B50: Meu Dente Clinica Odontologica Ltda | D50: 420 | I50: Livro Caixa: Recebimento à vista Gerado pelo sistema. (Doc. 4152)
A51: 46127 | B51: Consultorio Odontologico Cleber Dourado | C51: Refil Everest | D51: 140 | E51: Dinheiro | I51: NF-e 4153 | J51: EMP-0101
A52: 46127 | B52: Edelzuita Lima Ferreira | C52: Refil Everest | D52: 140 | E52: Dinheiro | I52: NFC-e 8987 | J52: CLI-0789
A53: 46127 | B53: Semeco Serviços Medicos e Consultoria LTDA - Sergio | C53: Refil Pro Life | D53: 140 | E53: Dinheiro | I53: NF-e 4154 | J53: EMP-0273
A54: 46127 | B54: Clinica Medica Odonto Fis - Lar Protegido | C54: 3x Refil Everest | D54: 399.99 | E54: Dinheiro | I54: NF-e 4155
A55: 46127 | B55: Samira Leal Vilas Boas | C55: Refil Everest | D55: 140 | E55: Dinheiro | I55: NFC-e 8988 | J55: CLI-0791
A56: 46127 | B56: Tarcisio Oliveira Lima | G56: 486.32 | H56: Contabilidade | I56: Livro Caixa: Pagamento parcela TARCISIO OLIVEIRA LIMA (Doc. 1) · Tarcisio Oliveira Lima
A57: 46127 | B57: Jamef | G57: 403.56 | H57: Transporte e Entregas | I57: Livro Caixa: Pagamento parcela JAMEF (Doc. 1) · Jamef Transportes Ltda
A58: 46127 | B58: Everest Refrigeracao e Industria | G58: 883.1 | H58: Fornecedores / Mercadoria | I58: NF 368529 de 14/01/2026 · parcela 3/5 (venc. 14/04/2026) · compra total R$ 4.327,52: Purificador Everest Plus Branco + Purificador Everest Plus Prata + Purificador Everest Star Prata + Purificador Everest Slim Prata + Purificador Everest Fit Prata + Purificador Everest Fit Branco · Livro Caixa
A59: 46128 | B59: Meu Dente Clinica Odontologica Ltda | C59: 2x Refil Everest | D59: 280 | E59: Dinheiro | I59: NF-e 4156
A60: 46128 | B60: Eugenia Maria Almeida dos Santos | C60: Refil Pro Life | D60: 140 | E60: Crédito Parcelado | I60: NFC-e 8989
A61: 46128 | B61: Ieda Rego de Matos | C61: Refil Pro Life + Mangueira (1 m) | D61: 150 | E61: Pix | I61: NFC-e 8990 | J61: CLI-0793
A62: 46128 | B62: Int Odontologia - Larissa sena | C62: Refil FPA14 | D62: 110 | E62: Pix | I62: NF-e 4157 | J62: EMP-0184
A63: 46128 | B63: Samira Leal Vilas Boas | C63: Refil Everest | D63: 130 | E63: Pix | I63: NFC-e 8991 | J63: CLI-0791
A64: 46128 | B64: Maria Jose Carneiro Oliveira Lima | C64: Refil Pro Life | D64: 140 | E64: Crédito Parcelado | I64: NFC-e 8992
A65: 46128 | B65: Cristiane Goncalves de Oliveira | C65: Refil Everest | D65: 140 | E65: Crédito Parcelado | I65: NFC-e 8993
A66: 46128 | B66: Consumidor Final | C66: Refil Universal | D66: 30 | E66: Dinheiro | I66: NFC-e 8994
A67: 46128 | B67: Jorge Samuel Mendes Moraes | C67: Refil Everest + Pré Filtro | D67: 200 | E67: Dinheiro | I67: NFC-e 8995 | J67: CLI-0391
A68: 46128 | B68: Consumidor Final | C68: Refil Top Color | D68: 85 | E68: Dinheiro | I68: NFC-e 8996
A69: 46128 | B69: Consumidor Final | C69: Registro | D69: 65 | E69: Dinheiro | I69: NFC-e 8997
A70: 46128 | B70: Tropical Motos LTDA | C70: Refil Everest | D70: 140 | I70: NF-e 4140 · nota faturada a prazo (forma de recebimento não consta na nota) · venda de 02/04/2026 — pagamento recebido em 16/04/2026 | J70: EMP-0296
A71: 46128 | B71: Estorno de recebimento — Meu Dente Clinica Odontologica Ltda | G71: 420 | H71: Estornos de Vendas (Cancelamentos) | I71: Livro Caixa: Estorno de recebimento do documento: Gerado pelo sistema. (Doc. 41)
A72: 46129 | B72: Wagner Oliveira Menezes - Ketina | C72: Refil Everest + Registro + Mangueira (3 m) | D72: 190 | E72: Pix | I72: NFC-e 8998 | J72: CLI-0659
A73: 46129 | B73: Consumidor Final | C73: Conexao Reta Rosca 1/2 Bspt P/Tubo 1/4 Pol Branca + Mangueira (1 m) | D73: 35 | E73: Crédito Parcelado | I73: NFC-e 8999
A74: 46129 | B74: Consumidor Final | C74: Refil Plissado | D74: 70 | E74: Dinheiro | I74: NFC-e 9000
A75: 46129 | B75: Juliana Ferreira Queiroz e Cia Ltda | C75: Refil Everest + Mangueira (10 m) | D75: 240 | I75: NF-e 4160. Recebimento não constava no Livro Caixa; conferido e baixado no DigiSat em 28/09/2026.
A76: 46130 | B76: Consumidor Final | C76: Refil Everest | D76: 140 | E76: Crédito Parcelado | I76: NFC-e 9001
A77: 46130 | B77: Quiteria Nunes de Souza | C77: Purificador Everest Star Branco | D77: 1348 | E77: Dinheiro | I77: NF-e 4161 | J77: CLI-0795
A78: 46130 | B78: Quiteria Nunes de Souza | C78: Refil FP1/FP2/FP5/FP8 | D78: 90 | E78: Débito | I78: NFC-e 9002
A79: 46132 | B79: Consumidor Final | C79: 2x Refil Plissado + 2x Carcaça 9" | D79: 400 | E79: Dinheiro | I79: NFC-e 9003
A80: 46132 | B80: Rafael Mesquita Victoria | C80: Purificador Everest Plus Prata | D80: 1448 | E80: Dinheiro | I80: NF-e 4162
A81: 46132 | B81: RF Supermercado Brasil LTDA | C81: Refil Pro Life | D81: 140 | I81: NF-e 4151 · nota faturada a prazo (forma de recebimento não consta na nota) · venda de 14/04/2026 — pagamento recebido em 20/04/2026 | J81: EMP-0261
A82: 46132 | B82: Gdf Guia do Fgts Digital | G82: 149.12 | H82: Impostos e Taxas | I82: Livro Caixa: Pagamento parcela GDF GUIA DO FGTS DIGITAL (Doc. 1) · Planeta Agua Ltda
A83: 46132 | B83: Documento de Arrecadação de Receitas Fe | G83: 319.29 | H83: Impostos e Taxas | I83: Livro Caixa: Pagamento parcela DOCUMENTO DE ARRECADAÇÃO DE RECEITAS FE · Planeta Agua Ltda
A84: 46132 | B84: Filtros Planeta Agua Ind e Com Ltda | G84: 600.64 | H84: Fornecedores / Mercadoria | I84: NF 128882 de 23/03/2026 · parcela 1/4 (venc. 20/04/2026) · compra total R$ 2.113,93 (IPI R$ 96,20): 25x Refil Pro Life + 2x Refil Top Color + 10x Refil Carbon Tech 9.3/4 Pol + 15x Refil Poli Flu Plissado 9.3/4 + 20x Refil E3 + 3x Carcaca Fit 9.3/4 Pol Branca + 15x Conexão T + Mangueira · Livro Caixa
A85: 46132 | B85: Simples Nacional | G85: 1858.96 | H85: Impostos e Taxas | I85: Livro Caixa: Pagamento parcela SIMPLES NACIONAL (Doc. 1) · Planeta Agua Ltda
A86: 46132 | B86: Eversoft Ind e Com de Plasticos Ltda | G86: 541.37 | H86: Fornecedores / Mercadoria | I86: NF 70444 de 23/01/2026 · parcela 3/5 (venc. 23/04/2026) · compra total R$ 2.706,83: 50x Refil Everest + 50x Pré Filtro · Livro Caixa
A87: 46132 | B87: Eversoft Ind e Com de Plasticos Ltda | G87: 878.92 | H87: Fornecedores / Mercadoria | I87: NF 71084 de 23/02/2026 · parcela 2/5 (venc. 24/04/2026) · compra total R$ 4.394,61: 100x Refil Everest · Livro Caixa
A88: 46134 | B88: Valdice Fontes da Silva | C88: Refil Everest | D88: 140 | E88: Dinheiro | I88: NFC-e 9004 | J88: CLI-0798
A89: 46134 | B89: Consumidor Final | C89: Conexao Em T Rosca De 1/2 Com Engate Rapido Reto 1/4 X 1/4 | D89: 37 | E89: Crédito Parcelado | I89: NFC-e 9005
A90: 46134 | B90: Consumidor Final | C90: Refil Everest | D90: 140 | E90: Pix | I90: NFC-e 9006
A91: 46135 | B91: Lapec Lab - Laboratorio de Analises e Pesquisas Clinicas Ltd | C91: Refil Everest | D91: 120 | E91: Dinheiro | I91: NF-e 4165
A92: 46135 | B92: Instituto Irmãs do Divino Espirito Santo - Silvana Goncalves | C92: Refil Everest | D92: 140 | E92: Dinheiro | I92: NF-e 4166 | J92: EMP-0181
A93: 46135 | B93: Jacobina Material de Limpeza Eireli | C93: Refil Everest | D93: 140 | E93: Dinheiro | I93: NF-e 4167
A94: 46135 | B94: Cooperativa de Credito Sicoob Sertao Ltda. | C94: Refil Everest | D94: 140 | E94: Dinheiro | I94: NF-e 4168
A95: 46135 | B95: Sociedade Educacional de Jacobina Ltda | C95: 2x Refil Carbon Tech 5" | D95: 140 | E95: Dinheiro | I95: NF-e 4169
A96: 46135 | B96: Ediane Guimarães de Souza - Raimundo | C96: Refil Everest + Pré Filtro | D96: 190 | E96: Dinheiro | I96: NFC-e 9007 | J96: CLI-0796
A97: 46135 | B97: Claudiane Pereira Carvalho Oliveira | C97: Purificador Everest Slim Branco | D97: 1298 | E97: Dinheiro | I97: NF-e 4171 | J97: OUT-0014
A98: 46135 | B98: Consumidor Final | C98: Refil Lacqua + Pré Filtro | D98: 160 | E98: Pix | I98: NFC-e 9008
A99: 46135 | B99: Ana Cristina da Silva Teixeira | C99: 2x Refil Everest + Pré Filtro | D99: 340 | E99: Pix | I99: NFC-e 9009 | J99: CLI-0799
A100: 46136 | B100: Reginaldo Santos da Silva | C100: Refil Pro Life | D100: 140 | E100: Dinheiro | I100: NF-e 4172 | J100: CLI-0067
...

Sheet Mai 2026
A1: RELATÓRIO FINANCEIRO — MAIO / 2026
A2: Fluxo de caixa da loja — entradas montadas a partir das notas fiscais (XML do DigiSat), com cliente e produtos; saídas do Livro Caixa
A3: ← Início
A4: Data | B4: Descrição / Cliente | C4: Produto | D4: Entrada (R$) | E4: Forma de Pagamento | F4: Taxa da Máquina (R$) | G4: Saída (R$) | H4: Categoria da Saída | I4: Observações | J4: ID Cliente | K4: Saídas por Categoria | N4: FATURAMENTO | P4: DESPESAS | R4: SALDO ANTES DO PRÓ-LABORE | T4: A RECEBER
A5: 46143 | B5: Salario Wiliam | G5: 1571.32 | H5: Salários, Comissões e Encargos | I5: Livro Caixa: Pagamento à vista: SALARIO WILIAM (Doc. 1) · Wiliam Pinto Bispo | K5: Fornecedores / Mercadoria | L5: =SUMIF(H5:H132,K5,G5:G132) | N5: =D133-F133-T5 | P5: =L18-L19 | R5: =D134 | T5: =SUMIF(E5:E132,"Aguardando Pagamento",D5:D132)
A6: 46143 | B6: Aluguel Vitoria Maria | G6: 870 | H6: Aluguel | I6: Livro Caixa: Pagamento à vista: ALUGUEL VITORIA MARIA (Doc. 1) · Vitoria Maria F Santos | K6: Aluguel | L6: =SUMIF(H5:H132,K6,G5:G132)
A7: 46144 | B7: Maricelia Santana Silva | C7: (Mesma venda — parcela seguinte, sem produtos novos) | D7: 30 | I7: NFC-e 9012 · venda de 25/04/2026, total R$ 130,00 — parcela 2 · nota faturada a prazo (forma de recebimento não consta na nota) | J7: CLI-0802 | K7: Água, Energia e Internet | L7: =SUMIF(H5:H132,K7,G5:G132) | N7: PRÓ-LABORE EDILÂNIA | P7: COMBINADO NO MÊS | R7: =IF(L17>'Ponto de Equilíbrio'!$B$10,"PASSOU DO COMBINADO",IF(TODAY()>EOMONTH(DATE(2026,5,1),0),"ABAIXO DO COMBINADO","AINDA PODE GASTAR")) | T7: SOBRA FINAL DO MÊS
A8: 46144 | B8: Banco do Nordeste do Brasil | C8: 2x Refil Everest | D8: 280 | E8: Dinheiro | I8: NF-e 4181 | J8: EMP-0220 | K8: Impostos e Taxas | L8: =SUMIF(H5:H132,K8,G5:G132) | N8: =L17 | P8: ='Ponto de Equilíbrio'!$B$10 | R8: =ABS('Ponto de Equilíbrio'!$B$10-L17) | T8: =R5-L17
A9: 46144 | B9: Roziane Santos Silva | C9: Refil Everest | D9: 140 | E9: Crédito Parcelado | I9: NFC-e 9027 | K9: Tarifas Bancárias e Cartão | L9: =SUMIF(H5:H132,K9,G5:G132)
A10: 46144 | B10: Serv de Apoio As Micro e Pequenas Empresas do Est da Bahia | C10: Refil FP4 | D10: 100 | I10: NF-e 4182. Recebimento não constava no Livro Caixa; conferido e baixado no DigiSat em 28/09/2026. | K10: Transporte e Entregas | L10: =SUMIF(H5:H132,K10,G5:G132)
A11: 46144 | B11: Eversoft Ind e Com de Plasticos Ltda | G11: 878.92 | H11: Fornecedores / Mercadoria | I11: NF 72153 de 02/04/2026 · parcela 1/5 (venc. 02/05/2026) · compra total R$ 4.394,61: 100x Refil Everest · Livro Caixa | K11: Salários, Comissões e Encargos | L11: =SUMIF(H5:H132,K11,G5:G132)
A12: 46144 | B12: Everest Refrigeracao e Industria | G12: 706.65 | H12: Fornecedores / Mercadoria | I12: NF 374271 de 06/04/2026 · parcela 1/5 (venc. 06/05/2026) · compra total R$ 3.533,27: Purificador Everest Plus Prata + Purificador Everest Star Branco + Purificador Everest Star Preto + Purificador Everest Slim Prata + Purificador Everest Fit Branco · Livro Caixa | K12: Contabilidade | L12: =SUMIF(H5:H132,K12,G5:G132)
A13: 46146 | B13: Consumidor Final | C13: Refil Carbon Tech 5" + Anel Oring De Vedaca Fit | D13: 65 | E13: Pix | I13: NFC-e 9028 | K13: Manutenção e Reparos | L13: =SUMIF(H5:H132,K13,G5:G132)
A14: 46146 | B14: Consumidor Final | C14: Refil Carbon Tech 9" + Anel Oring De Vedaca Fit | D14: 95 | E14: Pix | I14: NFC-e 9029 | K14: Material de Limpeza e Escritório | L14: =SUMIF(H5:H132,K14,G5:G132)
A15: 46146 | B15: Alfredo Ferreira Sacramento | C15: Refil Everest + Pré Filtro | D15: 190 | E15: Dinheiro | I15: NFC-e 9030 | J15: CLI-0810 | K15: Estornos de Vendas (Cancelamentos) | L15: =SUMIF(H5:H132,K15,G5:G132)
A16: 46146 | B16: Consumidor Final | C16: Refil Everest + Mangueira (1 m) | D16: 150 | E16: Crédito Parcelado | I16: NFC-e 9031 | K16: Outras Despesas | L16: =SUMIF(H5:H132,K16,G5:G132)
A17: 46146 | B17: Catia Tiara | C17: Refil Everest + Pré Filtro | D17: 190 | E17: Pix | I17: NFC-e 9032 | J17: CLI-0812 | K17: Pro Labore Edilânia | L17: =SUMIF(H5:H132,K17,G5:G132)
A18: 46146 | B18: Consumidor Final | C18: 2x Carcaça 9" + 2x Refil Carbon Tech | D18: 330 | E18: Dinheiro | I18: NFC-e 9033 | K18: Total | L18: =SUM(L5:L16)
A19: 46146 | B19: Everest Refrigeracao e Industria | G19: 572.25 | H19: Fornecedores / Mercadoria | I19: Livro Caixa: Pagamento parcela Gerado pelo sistema - nº 346431 (Doc. 346431) | K19: Capital de Giro (BB) — ainda a devolver | L19: =SUMIFS('Capital de Giro (BB)'!D9:D200,'Capital de Giro (BB)'!A9:A200,">="&DATE(2026,5,1),'Capital de Giro (BB)'!A9:A200,"<="&DATE(2026,5,31),'Capital de Giro (BB)'!E9:E200,"A Devolver")
A20: 46146 | B20: Coelba | G20: 125.37 | H20: Água, Energia e Internet | I20: Livro Caixa: Pagamento parcela COELBA (Doc. 1) · Companhia de Eletricidade do Estado da Bahia Coelba
A21: 46146 | B21: Filtros Planeta Agua Ind e Com Ltda | G21: 972.2 | H21: Fornecedores / Mercadoria | I21: NF 123868 de 24/10/2025 · parcela 1/5 (venc. 21/11/2025) · compra total R$ 4.058,44 (IPI R$ 200,60): 50x Refil Pro Life + 5x Refil Top Color + 5x Refil Fp4 + 20x Refil Carbon Tech 9.3/4 Pol + 10x Refil Top Multifilter + 5x Refil Top Color Fast + 10x Refil Fpa14 + 5x Refil Fpa22 + 5x Carcaca Fit 9.3/4 Pol Branca + 5x Conexão T + 5x Refil Fpa16 · Livro Caixa
A22: 46146 | B22: 1 Parcela Ferias Daniel | G22: 500 | H22: Salários, Comissões e Encargos | I22: Livro Caixa: Pagamento à vista: 1 PARCELA FERIAS DANIEL (Doc. 1) · Daniel Barbosa dos Santos
A23: 46146 | B23: Eversoft Ind e Com de Plasticos Ltda | G23: 878.92 | H23: Fornecedores / Mercadoria | I23: NF 68349 de 24/10/2025 · parcela 5/5 (venc. 23/03/2026) · compra total R$ 4.394,61: 100x Refil Everest · Livro Caixa
A24: 46146 | B24: Everest Refrigeracao e Industria | G24: 546.76 | H24: Fornecedores / Mercadoria | I24: NF 360351 de 25/09/2025 · parcela 5/5 (venc. 22/02/2026) · compra total R$ 2.733,82: Purificador Everest Fit Branco + Purificador Everest Fit Prata + Purificador Everest Slim Prata + Purificador Everest Star Branco · Livro Caixa
A25: 46146 | B25: Eversoft Ind e Com de Plasticos Ltda | G25: 878.92 | H25: Fornecedores / Mercadoria | I25: NF 69886 de 30/12/2025 · parcela 4/5 (venc. 29/04/2026) · compra total R$ 4.394,61: 100x Refil Everest · Livro Caixa
A26: 46146 | B26: Embasa Adriano | G26: 50.07 | H26: Pro Labore Edilânia | I26: Livro Caixa: Pagamento parcela EMBASA ADRIANO (Doc. 1) · Empresa Baiana de Aguas e Saneamento Sa
A27: 46146 | B27: Filtros Planeta Agua Ind e Com Ltda | G27: 420.87 | H27: Fornecedores / Mercadoria | I27: NF 126565 de 20/01/2026 · parcela 4/4 (venc. 31/03/2026) · compra total R$ 1.771,04 (IPI R$ 87,54): 65x Refil Pro Life · Livro Caixa
A28: 46146 | B28: Eversoft Ind e Com de Plasticos Ltda | G28: 20.6 | H28: Fornecedores / Mercadoria | I28: NF 69107 de 27/11/2025 · parcela 5/5 (venc. 26/04/2026) · compra total R$ 4.904,13: 100x Refil Everest + 50x Pré Filtro · Livro Caixa
A29: 46146 | B29: Conta de Energia Loja | G29: 148.15 | H29: Água, Energia e Internet | I29: Livro Caixa: Pagamento parcela CONTA DE ENERGIA LOJA (Doc. 1) · Companhia de Eletricidade do Estado da Bahia Coelba
A30: 46146 | B30: Everest Refrigeracao e Industria | G30: 810.99 | H30: Fornecedores / Mercadoria | I30: NF 368012 de 08/01/2026 · parcela 4/5 (venc. 08/05/2026) · compra total R$ 4.054,97: Purificador Everest Fit Branco + 2x Purificador Everest Slim Branco + Purificador Everest Slim Preto + 2x Purificador Everest Star Branco · Livro Caixa
A31: 46146 | B31: Everest Refrigeracao e Industria | G31: 841.06 | H31: Fornecedores / Mercadoria | I31: NF 366264 de 11/12/2025 · parcela 5/5 (venc. 10/05/2026) · compra total R$ 4.205,29: Purificador Everest Slim Branco + Purificador Everest Slim Prata + 2x Purificador Everest Star Branco + Purificador Everest Star Prata + Purificador Everest Plus Prata · Livro Caixa
A32: 46146 | B32: Everest Refrigeracao e Industria | G32: 725.48 | H32: Fornecedores / Mercadoria | I32: NF 372597 de 11/03/2026 · parcela 2/5 (venc. 10/05/2026) · compra total R$ 3.627,42: 2x Purificador Everest Plus Branco + Purificador Everest Fit Preto + Purificador Everest Slim Preto + Purificador Everest Star Preto · Livro Caixa
A33: 46147 | B33: Lapec Lab - Laboratorio de Analises e Pesquisas Clinicas Ltd | C33: Refil Everest | D33: 120 | E33: Dinheiro | I33: NF-e 4183
A34: 46147 | B34: Consumidor Final | C34: Refil FP1/FP2/FP5/FP8 | D34: 75 | E34: Crédito Parcelado | I34: NFC-e 9034
A35: 46148 | B35: Marinalva Souza Nascimento | C35: Refil Everest + Mangueira (1 m) | D35: 150 | E35: Crédito Parcelado | I35: NFC-e 9035
A36: 46148 | B36: Valdice de Jesus Silva Costa | C36: Refil Everest | D36: 130 | E36: Dinheiro | I36: NFC-e 9036
A37: 46148 | B37: Valdeci Souza Silva | C37: (Mesma venda — parcela seguinte, sem produtos novos) | D37: 70 | I37: NFC-e 8970 · venda de 07/04/2026, total R$ 140,00 — parcela 2 · nota faturada a prazo (forma de recebimento não consta na nota) | J37: CLI-0779
A38: 46148 | B38: Consumidor Final | C38: Refil Universal | D38: 30 | E38: Pix | I38: NFC-e 9037
A39: 46148 | B39: Filtros Planeta Agua Ind e Com Ltda | G39: 504.43 | H39: Fornecedores / Mercadoria | I39: NF 128882 de 23/03/2026 · parcela 2/4 (venc. 04/05/2026) · compra total R$ 2.113,93 (IPI R$ 96,20): 25x Refil Pro Life + 2x Refil Top Color + 10x Refil Carbon Tech 9.3/4 Pol + 15x Refil Poli Flu Plissado 9.3/4 + 20x Refil E3 + 3x Carcaca Fit 9.3/4 Pol Branca + 15x Conexão T + Mangueira · Livro Caixa
A40: 46149 | B40: Jackson Macedo de Sales | C40: 3x Refil Carbon Tech 9" | D40: 180 | E40: Pix | I40: NF-e 4184
A41: 46149 | B41: Anderson da Conceicao Gomes | C41: Refil Everest | D41: 140 | E41: Crédito Parcelado | I41: NFC-e 9038
A42: 46150 | B42: Vinicius Oliveira Lima | C42: Purificador Everest Star Preto | D42: 1448 | E42: Dinheiro | I42: NF-e 4185 | J42: CLI-0817
A43: 46150 | B43: Paulo Marques Figueiredo - Neusa | C43: Refil Everest | D43: 140 | E43: Crédito Parcelado | I43: NFC-e 9039
A44: 46150 | B44: Consumidor Final | C44: Torneira Acqua Azzurra Toc Branca Saq | D44: 16 | E44: Dinheiro | I44: NFC-e 9040
A45: 46150 | B45: Glecia da Silva Lopes Vieira | C45: Refil Everest | D45: 140 | E45: Crédito Parcelado | I45: NFC-e 9041
A46: 46150 | B46: Edna da Silva Souza - Casa no Sitio | C46: Refil Everest | D46: 135 | E46: Pix | I46: NFC-e 9042 | J46: CLI-0248
A47: 46150 | B47: Marsilia Marmores e Granitos Erelli | C47: Refil Pro Life + Refil IBBL C+3 | D47: 275 | E47: Pix | I47: NF-e 4186 | J47: EMP-0216
A48: 46150 | B48: Everest Refrigeracao e Industria | G48: 810.99 | H48: Fornecedores / Mercadoria | I48: NF 368012 de 08/01/2026 · parcela 4/5 (venc. 08/05/2026) · compra total R$ 4.054,97: Purificador Everest Fit Branco + 2x Purificador Everest Slim Branco + Purificador Everest Slim Preto + 2x Purificador Everest Star Branco · Livro Caixa
A49: 46151 | B49: Consumidor Final | C49: Vela Filtro de Barro | D49: 5 | E49: Dinheiro | I49: NFC-e 9043
A50: 46153 | B50: Marineuza Pinho Ramos Barbosa | C50: Refil Everest | D50: 135 | E50: Pix | I50: NFC-e 9044 | J50: CLI-0819
A51: 46153 | B51: Danilo Carvalho Alves | C51: Refil Everest | D51: 135 | E51: Pix | I51: NFC-e 9045 | J51: CLI-0814
A52: 46154 | B52: Consumidor Final | D52: 75 | I52: Livro Caixa: Recebimento à vista Gerado pelo sistema (Doc. 9046)
A53: 46154 | B53: Cbv Construtora Ltda | C53: Refil PA 230 | D53: 75 | E53: Pix | I53: NF-e 4188
A54: 46154 | B54: Consumidor Final | C54: Refil Carbon Tech 5" | D54: 55 | E54: Pix | I54: NFC-e 9047
A55: 46154 | B55: Julio Cesar Vilas Boas Santos - Adriadne Me | C55: Refil Everest | D55: 140 | E55: Pix | I55: NFC-e 9048 | J55: CLI-0820
A56: 46154 | B56: Consumidor Final | C56: Mangueira (2 m) | D56: 20 | E56: Crédito Parcelado | I56: NFC-e 9049
A57: 46154 | B57: Consumidor Final | C57: Mangueira (2 m) | D57: 25 | E57: Pix | I57: NFC-e 9050
A58: 46154 | B58: Celcina Barbosa Miranda | C58: Refil Pro Life | D58: 140 | E58: Dinheiro | I58: NFC-e 9051 | J58: CLI-0821
A59: 46154 | B59: Consumidor Final | C59: Torneira Acqua Azzurra Toc Branca/Azul Saq | D59: 15 | E59: Dinheiro | I59: NFC-e 9052
A60: 46154 | B60: Estorno de recebimento — Cliente Consumidor | G60: 75 | H60: Estornos de Vendas (Cancelamentos) | I60: Livro Caixa: Estorno de recebimento do documento: Gerado pelo sistema (Doc. 904)
A61: 46155 | B61: Jose Ismaildo de Brito | C61: Purificador Everest Star Branco | D61: 1230 | E61: Dinheiro | I61: NF-e 4190
A62: 46155 | B62: Juscineide Santos Silva Cruz | C62: Refil Everest | D62: 140 | E62: Crédito Parcelado | I62: NFC-e 9053
A63: 46155 | B63: Servico Nacional de Aprendizagem Industrial | C63: Refil Plissado | D63: 80 | E63: Dinheiro | I63: NF-e 4193
A64: 46155 | B64: Igreja Batista Filadelfia | C64: Refil Everest + Suporte | D64: 180 | I64: NF-e 4192. Recebimento não constava no Livro Caixa; conferido e baixado no DigiSat em 28/09/2026.
A65: 46156 | B65: Consumidor Final | C65: Refil FPA14 | D65: 100 | E65: Pix | I65: NFC-e 9054
A66: 46156 | B66: Marta Souza Cunha | C66: Refil Everest | D66: 140 | E66: Crédito Parcelado | I66: NFC-e 9055
A67: 46156 | B67: Centro Medico de Jacobina LTDA - Clinica Santa Barbara | C67: 3x Refil Everest + Refil Pro Life | D67: 560 | I67: NF-e 4189 · nota faturada a prazo (forma de recebimento não consta na nota) · venda de 12/05/2026 — pagamento recebido em 14/05/2026 | J67: EMP-0063
A68: 46156 | B68: Ages Empreendimentos Educacionais Ltda | C68: 5x Refil IBBL C+3 | D68: 450 | E68: Pix | I68: NF-e 4158 · Grupo Ânima — venda de 17/04/2026, Nota Paga no portal V360 em 14/05/2026. Recebimento não constava no Livro Caixa; baixa dada no DigiSat em 28/09/2026.
A69: 46156 | B69: Ages Educacao Ltda | C69: 9x Refil Consul | D69: 1305 | E69: Pix | I69: NF-e 4159 · Grupo Ânima — venda de 17/04/2026, Nota Paga no portal V360 em 14/05/2026. Recebimento não constava no Livro Caixa; baixa dada no DigiSat em 28/09/2026.
A70: 46156 | B70: Culligan Latam Eireli | G70: 240 | H70: Fornecedores / Mercadoria | I70: NF 138165 de 22/04/2026 · compra total R$ 240,00: 10x Filtro De Agua Natural Lacrado · Livro Caixa
A71: 46157 | B71: Consumidor Final | D71: 145 | I71: Livro Caixa: Recebimento à vista Gerado pelo sistema (Doc. 9056)
A72: 46157 | B72: Karcia Magali Ribeiro Rodrigues | C72: Refil Everest | D72: 145 | E72: Crédito Parcelado | I72: NFC-e 9057
A73: 46157 | B73: Ligia Oliveira da Luz | C73: Refil Everest | D73: 140 | E73: Crédito Parcelado | I73: NFC-e 9058
A74: 46157 | B74: Consumidor Final | C74: Refil BAG | D74: 50 | E74: Débito | I74: NFC-e 9059
A75: 46157 | B75: Estorno de recebimento — Cielo S. A. | G75: 145 | H75: Estornos de Vendas (Cancelamentos) | I75: Livro Caixa: Estorno de recebimento do documento: Gerado pelo sistema (Doc. 905)
A76: 46158 | B76: Ages Educacao Ltda | C76: Carvao Ativado Mineral Po Puro Embalagem 1Kg + 2x Pré Filtro IBBL + 2x Refil IBBL C+3 | D76: 670 | E76: Pix | I76: NF-e 4147 · Grupo Ânima — venda de 11/04/2026, Nota Paga no portal V360 em 16/05/2026. Recebimento não constava no Livro Caixa; baixa dada no DigiSat em 28/09/2026.
A77: 46160 | B77: Consumidor Final | C77: 2x Refil Plissado + Refil Carbon Tech 5" | D77: 220 | E77: Crédito Parcelado | I77: NFC-e 9060
A78: 46160 | B78: Arlindo Galdino dos Santos Junior - Floricelia | C78: Refil Pro Life | D78: 140 | E78: Dinheiro | I78: NFC-e 9061 | J78: CLI-0677
A79: 46160 | B79: Maiza Cerqueira Barcelar | C79: Purificador Everest Fit Branco | D79: 1250 | E79: Dinheiro | I79: NF-e 4194 | J79: CLI-0818
A80: 46161 | B80: Costa e Sa Advogados | C80: Refil FPA14 | D80: 100 | E80: Dinheiro | I80: NF-e 4195 | J80: EMP-0316
A81: 46161 | B81: Cleidiomar Moreira Gonzaga | C81: Refil FP1/FP2/FP5/FP8 | D81: 150 | E81: Crédito Parcelado | I81: NFC-e 9062
A82: 46161 | B82: Consumidor Final | C82: Refil Pro Life | D82: 140 | E82: Crédito Parcelado | I82: NFC-e 9063
A83: 46162 | B83: Consumidor Final | C83: Refil PP | D83: 75 | E83: Pix | I83: NFC-e 9064
A84: 46162 | B84: Consumidor Final | C84: Refil Pro Life | D84: 130 | E84: Débito | I84: NFC-e 9065
A85: 46163 | B85: Eco-Marmores e Granitos Importação e Exportação Ltda | C85: Refil Pro Life | D85: 140 | E85: Pix | I85: NF-e 4198 | J85: EMP-0130
A86: 46163 | B86: Colegio Castro Alves | C86: 2x Refil Everest | D86: 280 | E86: Pix | I86: NF-e 4199 | J86: ESC-0012
A87: 46163 | B87: Hospital do Trauma Servicos Medicos Hospitalares Ltda | C87: Refil Everest | D87: 140 | E87: Dinheiro | I87: NF-e 4200
A88: 46163 | B88: Ana Claudia Oliveira dos Santos | C88: Refil Everest | D88: 140 | E88: Crédito Parcelado | I88: NFC-e 9066
A89: 46164 | B89: Aliomar Gomes Navarro | C89: Refil Everest + Pré Filtro | D89: 200 | E89: Crédito Parcelado | I89: NFC-e 9067
A90: 46164 | B90: Vanda Cleia Oliveira da Silva | C90: Refil Everest | D90: 140 | E90: Pix | I90: NFC-e 9068 | J90: CLI-0829
A91: 46164 | B91: Consumidor Final | C91: Refil Everest | D91: 140 | E91: Pix | I91: NFC-e 9069
A92: 46164 | B92: Mariua Construcoes Ltda | C92: Refil Plissado + Refil Carbon Tech 9" | D92: 180 | E92: Pix | I92: NF-e 4201
A93: 46164 | B93: Filtros Planeta Agua Ind e Com Ltda | G93: 504.43 | H93: Fornecedores / Mercadoria | I93: NF 128882 de 23/03/2026 · parcela 3/4 (venc. 18/05/2026) · compra total R$ 2.113,93 (IPI R$ 96,20): 25x Refil Pro Life + 2x Refil Top Color + 10x Refil Carbon Tech 9.3/4 Pol + 15x Refil Poli Flu Plissado 9.3/4 + 20x Refil E3 + 3x Carcaca Fit 9.3/4 Pol Branca + 15x Conexão T + Mangueira · Livro Caixa
A94: 46164 | B94: Receitas Federais | G94: 405.39 | H94: Impostos e Taxas | I94: Livro Caixa: Pagamento parcela RECEITAS FEDERAIS (Doc. 1) · Planeta Agua Ltda
A95: 46164 | B95: Fgts | G95: 240.96 | H95: Impostos e Taxas | I95: Livro Caixa: Pagamento parcela FGTS (Doc. 1) · Planeta Agua Ltda
A96: 46164 | B96: Simples Nacional | G96: 2111.69 | H96: Impostos e Taxas | I96: Livro Caixa: Pagamento parcela SIMPLES NACIONAL (Doc. 1) · Planeta Agua Ltda
A97: 46165 | B97: Consumidor Final | C97: Mangueira (1 m) | D97: 10 | E97: Dinheiro | I97: NFC-e 9070
A98: 46167 | B98: Caio Marcelo da Silva Passos | C98: Refil Everest | D98: 140 | E98: Pix | I98: NFC-e 9071 | J98: CLI-0830
A99: 46167 | B99: Consumidor Final | C99: Refil Lacqua | D99: 85 | E99: Pix | I99: NFC-e 9072
A100: 46167 | B100: Consumidor Final | C100: Refil Carbon Tech 5" | D100: 50 | E100: Dinheiro | I100: NFC-e 9073
...

Sheet Jun 2026
A1: RELATÓRIO FINANCEIRO — JUNHO / 2026
A2: Fluxo de caixa da loja — entradas montadas a partir das notas fiscais (XML do DigiSat), com cliente e produtos; saídas do Livro Caixa
A3: ← Início
A4: Data | B4: Descrição / Cliente | C4: Produto | D4: Entrada (R$) | E4: Forma de Pagamento | F4: Taxa da Máquina (R$) | G4: Saída (R$) | H4: Categoria da Saída | I4: Observações | J4: ID Cliente | K4: Saídas por Categoria | N4: FATURAMENTO | P4: DESPESAS | R4: SALDO ANTES DO PRÓ-LABORE | T4: A RECEBER
A5: 46174 | B5: Gidionor Andrade dos Santos - Creuza Silva Souza | C5: Refil Pro Life | D5: 140 | E5: Dinheiro | I5: NFC-e 9083 | J5: CLI-0838 | K5: Fornecedores / Mercadoria | L5: =SUMIF(H5:H120,K5,G5:G120) | N5: =D121-F121-T5 | P5: =L18-L19 | R5: =D122 | T5: =SUMIF(E5:E120,"Aguardando Pagamento",D5:D120)
A6: 46174 | B6: Albuquerque Scardua Serviços Medicos Ltda - Ameped | C6: Refil Pro Life + Mangueira (1 m) | D6: 150 | E6: Pix | I6: NF-e 4213 | J6: EMP-0005 | K6: Aluguel | L6: =SUMIF(H5:H120,K6,G5:G120)
A7: 46174 | B7: Maria do Socorro Lima Grassi | C7: Refil Everest | D7: 140 | E7: Dinheiro | I7: NFC-e 9084 | J7: CLI-0839 | K7: Água, Energia e Internet | L7: =SUMIF(H5:H120,K7,G5:G120) | N7: PRÓ-LABORE EDILÂNIA | P7: COMBINADO NO MÊS | R7: =IF(L17>'Ponto de Equilíbrio'!$B$10,"PASSOU DO COMBINADO",IF(TODAY()>EOMONTH(DATE(2026,6,1),0),"ABAIXO DO COMBINADO","AINDA PODE GASTAR")) | T7: SOBRA FINAL DO MÊS
A8: 46175 | B8: Eva Lages Matos de Freitas | C8: (Mesma venda — parcela seguinte, sem produtos novos) | D8: 70 | I8: NFC-e 8918 · venda de 07/03/2026, total R$ 140,00 — parcela 2 · nota faturada a prazo (forma de recebimento não consta na nota) | J8: CLI-0741 | K8: Impostos e Taxas | L8: =SUMIF(H5:H120,K8,G5:G120) | N8: =L17 | P8: ='Ponto de Equilíbrio'!$B$10 | R8: =ABS('Ponto de Equilíbrio'!$B$10-L17) | T8: =R5-L17
A9: 46176 | B9: Lojão das Maquiagens | C9: Refil Everest | D9: 140 | E9: Dinheiro | I9: NF-e 4215 | J9: EMP-0207 | K9: Tarifas Bancárias e Cartão | L9: =SUMIF(H5:H120,K9,G5:G120)
A10: 46176 | B10: Jidalva Freitas Silva | C10: Refil Pro Life | D10: 140 | E10: Pix | I10: NFC-e 9085 | J10: CLI-0840 | K10: Transporte e Entregas | L10: =SUMIF(H5:H120,K10,G5:G120)
A11: 46176 | B11: Ricardo Alcantara Mesquita | C11: Refil Everest | D11: 140 | E11: Crédito Parcelado | I11: NFC-e 9086 | K11: Salários, Comissões e Encargos | L11: =SUMIF(H5:H120,K11,G5:G120)
A12: 46176 | B12: Consumidor Final | C12: Refil Everest | D12: 140 | E12: Pix | I12: NFC-e 9087 | K12: Contabilidade | L12: =SUMIF(H5:H120,K12,G5:G120)
A13: 46177 | B13: Ages Empreendimentos Educacionais Ltda | C13: 8x Pré Filtro IBBL + 8x Refil IBBL C+3 | D13: 2160 | E13: Pix | I13: NF-e 4178 · Grupo Ânima — venda de 29/04/2026, Nota Paga no portal V360 em 04/06/2026. Recebimento não constava no Livro Caixa; baixa dada no DigiSat em 28/09/2026. | K13: Manutenção e Reparos | L13: =SUMIF(H5:H120,K13,G5:G120)
A14: 46178 | B14: Gabriela Ferreira Gama | C14: Purificador Everest Slim Branco | D14: 1398 | E14: Dinheiro | I14: NF-e 4218 | J14: CLI-0848 | K14: Material de Limpeza e Escritório | L14: =SUMIF(H5:H120,K14,G5:G120)
A15: 46178 | B15: Consumidor Final | C15: Refil Universal | D15: 30 | E15: Débito | I15: NFC-e 9088 | K15: Estornos de Vendas (Cancelamentos) | L15: =SUMIF(H5:H120,K15,G5:G120)
A16: 46178 | B16: Consumidor Final | C16: Refil Pro Life | D16: 35 | E16: Dinheiro | I16: NFC-e 9089 | K16: Outras Despesas | L16: =SUMIF(H5:H120,K16,G5:G120)
A17: 46178 | B17: Reinaldo de Jesus - Elizete | C17: Refil Everest + Registro | D17: 170 | E17: Pix | I17: NFC-e 9090 | J17: CLI-0842 | K17: Pro Labore Edilânia | L17: =SUMIF(H5:H120,K17,G5:G120)
A18: 46178 | B18: Bio Imagem Serviço de Diagnostico - Copa | C18: 2x Refil Everest | D18: 200 | I18: NF-e 4219 · venda de 05/06/2026, total R$ 280,00 — parcela 1 · nota faturada a prazo (forma de recebimento não consta na nota) | J18: EMP-0030 | K18: Total | L18: =SUM(L5:L16)
A19: 46178 | B19: Ages Empreendimentos Educacionais Ltda | C19: 8x Pré Filtro IBBL + 8x Refil IBBL C+3 | D19: 2160 | E19: Pix | I19: NF-e 4180 · Grupo Ânima — venda de 30/04/2026, Nota Paga no portal V360 em 05/06/2026. Recebimento não constava no Livro Caixa; baixa dada no DigiSat em 28/09/2026. | K19: Capital de Giro (BB) — ainda a devolver | L19: =SUMIFS('Capital de Giro (BB)'!D9:D200,'Capital de Giro (BB)'!A9:A200,">="&DATE(2026,6,1),'Capital de Giro (BB)'!A9:A200,"<="&DATE(2026,6,30),'Capital de Giro (BB)'!E9:E200,"A Devolver")
A20: 46178 | B20: Filtros Planeta Agua Ind e Com Ltda | G20: 504.43 | H20: Fornecedores / Mercadoria | I20: NF 128882 de 23/03/2026 · parcela 4/4 (venc. 01/06/2026) · compra total R$ 2.113,93 (IPI R$ 96,20): 25x Refil Pro Life + 2x Refil Top Color + 10x Refil Carbon Tech 9.3/4 Pol + 15x Refil Poli Flu Plissado 9.3/4 + 20x Refil E3 + 3x Carcaca Fit 9.3/4 Pol Branca + 15x Conexão T + Mangueira · Livro Caixa
A21: 46178 | B21: Eversoft Ind e Com de Plasticos Ltda | G21: 878.92 | H21: Fornecedores / Mercadoria | I21: NF 72153 de 02/04/2026 · parcela 2/5 (venc. 01/06/2026) · compra total R$ 4.394,61: 100x Refil Everest · Livro Caixa
A22: 46178 | B22: Aluguel Vitoria Maria | G22: 870 | H22: Aluguel | I22: Livro Caixa: Pagamento parcela ALUGUEL VITORIA MARIA (Doc. 1) · Vitoria Maria F Santos
A23: 46178 | B23: Documento de Arrecadação de Receitas Fed | G23: 430.27 | H23: Impostos e Taxas | I23: Livro Caixa: Pagamento à vista: DOCUMENTO DE ARRECADAÇÃO DE RECEITAS FED · Ministerio da Fazenda
A24: 46178 | B24: Coelba Loja | G24: 150.65 | H24: Água, Energia e Internet | I24: Livro Caixa: Pagamento parcela COELBA LOJA (Doc. 1) · Companhia de Eletricidade do Estado da Bahia Coelba
A25: 46178 | B25: Everest Refrigeracao e Industria | G25: 706.65 | H25: Fornecedores / Mercadoria | I25: NF 374271 de 06/04/2026 · parcela 2/5 (venc. 05/06/2026) · compra total R$ 3.533,27: Purificador Everest Plus Prata + Purificador Everest Star Branco + Purificador Everest Star Preto + Purificador Everest Slim Prata + Purificador Everest Fit Branco · Livro Caixa
A26: 46178 | B26: Filtros Planeta Agua Ind e Com Ltda | G26: 804.71 | H26: Fornecedores / Mercadoria | I26: NF 130510 de 08/05/2026 · parcela 1/4 (venc. 05/06/2026) · compra total R$ 2.803,16 (IPI R$ 138,56): 50x Refil Pro Life + 3x Refil Top Color + 5x Refil Acquatec + 5x Refil Fp4 + 6x Refil Carbon Tech 9.3/4 Pol + 6x Refil Poli Flu Plissado 9.3/4 + 5x Refil E3 + 5x Refil Top Multifilter + 3x Refil Top Color Fast + 5x Refil Fpa14 · Livro Caixa
A27: 46179 | B27: Consumidor Final | C27: Mangueira (1 m) | D27: 10 | E27: Dinheiro | I27: NFC-e 9091
A28: 46179 | B28: Consumidor Final | C28: Mangueira (1 m) | D28: 10 | E28: Pix | I28: NFC-e 9092
A29: 46179 | B29: Consumidor Final | C29: Refil FP4 | D29: 80 | E29: Pix | I29: NFC-e 9093
A30: 46181 | B30: Servico Nacional de Aprendizagem Rural Senar | C30: Refil FPA14 + Refil Multifilter | D30: 175 | E30: Dinheiro | I30: NF-e 4220
A31: 46181 | B31: José Carlos Silveira Gomes | C31: Refil Everest | D31: 135 | E31: Pix | I31: NFC-e 9094 | J31: CLI-0845
A32: 46181 | B32: Consumidor Final | C32: Mangueira (1 m) | D32: 10 | E32: Débito | I32: NFC-e 9095
A33: 46181 | B33: Consumidor Final | C33: Conexao Reta Rosca 1/2 Bspt P/Tubo 1/4 Pol Branca | D33: 25 | E33: Débito | I33: NFC-e 9096
A34: 46182 | B34: Consumidor Final | C34: Refil Everest | D34: 140 | E34: Crédito Parcelado | I34: NFC-e 9097
A35: 46182 | B35: Skina Mineira LTDA | C35: Refil Pro Life + Pré Filtro | D35: 200 | E35: Dinheiro | I35: NF-e 4221 | J35: EMP-0278
A36: 46182 | B36: Marisa Araujo Oliveira Nascimento | C36: Refil Everest | D36: 140 | E36: Dinheiro | I36: NF-e 4222
A37: 46182 | B37: Bio Imagem Serviço de Diagnostico - Copa | C37: (Mesma venda — parcela seguinte, sem produtos novos) | D37: 80 | I37: NF-e 4219 · venda de 05/06/2026, total R$ 280,00 — parcela 2 · nota faturada a prazo (forma de recebimento não consta na nota) | J37: EMP-0030
A38: 46182 | B38: Everest Refrigeracao e Industria | G38: 811.01 | H38: Fornecedores / Mercadoria | I38: NF 368012 de 08/01/2026 · parcela 5/5 (venc. 07/06/2026) · compra total R$ 4.054,97: Purificador Everest Fit Branco + 2x Purificador Everest Slim Branco + Purificador Everest Slim Preto + 2x Purificador Everest Star Branco · Livro Caixa
A39: 46182 | B39: Everest Refrigeracao e Industria | G39: 725.48 | H39: Fornecedores / Mercadoria | I39: NF 372597 de 11/03/2026 · parcela 3/5 (venc. 09/06/2026) · compra total R$ 3.627,42: 2x Purificador Everest Plus Branco + Purificador Everest Fit Preto + Purificador Everest Slim Preto + Purificador Everest Star Preto · Livro Caixa
A40: 46182 | B40: Filtros Planeta Agua Ind e Com Ltda | G40: 504.75 | H40: Fornecedores / Mercadoria | I40: NF 129257 de 31/03/2026 · parcela 4/4 (venc. 09/06/2026) · compra total R$ 2.123,99 (IPI R$ 104,98): 5x Refil Fp4 + 10x Refil Carbon Tech 5 Pol + 10x Refil Carbon Tech 9.3/4 Pol + 36x Refil Pre-E3 · Livro Caixa
A41: 46183 | B41: Darc Store (calçados) - Carlos Henrique de Oliveira Salvador Ltda | C41: Refil Everest | D41: 140 | E41: Dinheiro | I41: NF-e 4223 | J41: EMP-0113
A42: 46183 | B42: Darc Store - Loja 12 (roupas) - Tayane Calçados e Vestuario Ltda | C42: Refil Everest | D42: 140 | E42: Dinheiro | I42: NF-e 4224 | J42: EMP-0112
A43: 46183 | B43: A F Mendonça Oliveira Eireli - Mendonça Disk Agua | C43: Refil Everest | D43: 140 | E43: Dinheiro | I43: NF-e 4225 | J43: EMP-0002
A44: 46183 | B44: DrillGeo Geologia e Sondagens | C44: Refil Plissado + Refil Carbon Tech 9" | D44: 180 | I44: NF-e 4187 · nota faturada a prazo (forma de recebimento não consta na nota) · venda de 09/05/2026 — pagamento recebido em 10/06/2026 | J44: EMP-0125
A45: 46184 | B45: Consumidor Final | C45: Mangueira (1 m) | D45: 10 | E45: Dinheiro | I45: NFC-e 9098
A46: 46184 | B46: Irenilda Almeida Santos | C46: Purificador Everest Slim Prata + Pré Filtro | D46: 1510 | E46: Dinheiro | I46: NF-e 4226
A47: 46184 | B47: Consumidor Final | C47: Refil PA 200 | D47: 60 | E47: Dinheiro | I47: NFC-e 9099
A48: 46184 | B48: Consumidor Final | C48: Refil Everest | D48: 140 | E48: Pix | I48: NFC-e 9100
A49: 46185 | B49: Consumidor Final | C49: Refil Pro Life + Pré Filtro | D49: 200 | E49: Pix | I49: NFC-e 9101
A50: 46185 | B50: Avertina Maria de Oliveira | C50: Refil Everest + Pré Filtro | D50: 185 | E50: Dinheiro | I50: NFC-e 9102 | J50: CLI-0850
A51: 46185 | B51: Consumidor Final | C51: Refil FP4 | D51: 90 | E51: Crédito Parcelado | I51: NFC-e 9103
A52: 46185 | B52: Consumidor Final | C52: Conexao Reta Rosca 1/2 Bspt P/Tubo 1/4 Pol Branca + Mangueira (1 m) | D52: 40 | E52: Dinheiro | I52: NFC-e 9104
A53: 46185 | B53: Consumidor Final | C53: Refil Plissado + Mangueira (1 m) | D53: 95 | E53: Dinheiro | I53: NFC-e 9105
A54: 46185 | B54: Apec - Sociedade Potiguar de Educacao e Cultura Ltda | C54: 4x Refil Libell | D54: 368.6 | E54: Pix | I54: NF-e 4191 · Grupo Ânima — venda de 13/05/2026, Nota Paga no portal V360 em 12/06/2026. Recebimento não constava no Livro Caixa; baixa dada no DigiSat em 28/09/2026.
A55: 46188 | B55: Silvio Candido da Silva - Celia Borges | C55: Refil Everest + Pré Filtro | D55: 180 | E55: Dinheiro | I55: NFC-e 9106 | J55: CLI-0851
A56: 46188 | B56: Jalicia Lima Santos Muricy | C56: Refil Everest | D56: 140 | E56: Pix | I56: NFC-e 9107 | J56: CLI-0627
A57: 46188 | B57: Maria Inez Lages Matos | C57: Refil Everest | D57: 140 | E57: Pix | I57: NFC-e 9108 | J57: CLI-0846
A58: 46188 | B58: Consumidor Final | C58: Refil FP4 | D58: 90 | E58: Débito | I58: NFC-e 9109
A59: 46188 | B59: Consumidor Final | C59: Mangueira (2 m) | D59: 20 | E59: Dinheiro | I59: NFC-e 9110
A60: 46189 | B60: Consumidor Final | C60: Suporte | D60: 35 | E60: Pix | I60: NFC-e 9111
A61: 46189 | B61: Jonio Ribeiro Oliveira | C61: Refil Everest + Pré Filtro | D61: 200 | E61: Crédito Parcelado | I61: NFC-e 9112
A62: 46189 | B62: Valdiney Santos da Silva | C62: Refil Carbon Tech 5" | D62: 60 | E62: Dinheiro | I62: NF-e 4227 | J62: CLI-0463
A63: 46189 | B63: Consumidor Final | C63: Mangueira (1 m) | D63: 10 | E63: Dinheiro | I63: NFC-e 9113
A64: 46189 | B64: Consumidor Final | C64: Conexao Em T Rosca De 1/2 Com Engate Rapido Reto 1/4 X 1/4 + Valvula De Fechamento Tubo De 1/4 Para 1/4 Pol Branca | D64: 65 | E64: Pix | I64: NFC-e 9114
A65: 46189 | B65: RF Supermercado Brasil LTDA | C65: 3x Refil Pro Life + Registro | D65: 450 | I65: NF-e 4217 · nota faturada a prazo (forma de recebimento não consta na nota) · venda de 05/06/2026 — pagamento recebido em 16/06/2026 | J65: EMP-0261
A66: 46189 | B66: Veronildo Baslio Souza | C66: Refil Everest | D66: 135 | E66: Dinheiro | I66: NF-e 4228 | J66: CLI-0853
A67: 46189 | B67: Leonardo Arizi | C67: Refil Everest + Pré Filtro + Mangueira (1 m) | D67: 200 | E67: Crédito Parcelado | I67: NFC-e 9115
A68: 46189 | B68: Tarcisio Oliveira Lima | G68: 486.32 | H68: Contabilidade | I68: Livro Caixa: Pagamento parcela TARCISIO OLIVEIRA LIMA (Doc. 1) · Contabilidade Tarcisio Oliveira Lima
A69: 46189 | B69: Everest Refrigeracao e Industria | G69: 865.52 | H69: Fornecedores / Mercadoria | I69: NF 368529 de 14/01/2026 · parcela 5/5 (venc. 13/06/2026) · compra total R$ 4.327,52: Purificador Everest Plus Branco + Purificador Everest Plus Prata + Purificador Everest Star Prata + Purificador Everest Slim Prata + Purificador Everest Fit Prata + Purificador Everest Fit Branco · Livro Caixa
A70: 46190 | B70: Valdenice de Jesus Cerqueira | C70: Refil Everest | D70: 130 | E70: Dinheiro | I70: NFC-e 9116 | J70: CLI-0855
A71: 46190 | B71: Avenida Posto e Combustivel | C71: Refil Everest | D71: 140 | E71: Dinheiro | I71: NF-e 4229
A72: 46190 | B72: Jacobina Automoveis | C72: Refil Everest | D72: 135 | E72: Dinheiro | I72: NF-e 4231 | J72: EMP-0192
A73: 46190 | B73: Antonio Carlos Marcolino da Silva | C73: Refil Everest | D73: 140 | E73: Dinheiro | I73: NFC-e 9117 | J73: OUT-0006
A74: 46190 | B74: Consumidor Final | C74: 2x Refil Everest + 2x Pré Filtro + Registro | D74: 415 | E74: Dinheiro | I74: NFC-e 9118
A75: 46190 | B75: P Vieira da Silva - Me | C75: Refil Everest + Pré Filtro + Registro | D75: 230 | I75: NF-e 4230. Recebimento não constava no Livro Caixa; conferido e baixado no DigiSat em 28/09/2026.
A76: 46191 | B76: Centro Medico de Jacobina LTDA - Clinica Santa Barbara | C76: 8x Refil Everest | D76: 1120 | I76: NF-e 4214 · nota faturada a prazo (forma de recebimento não consta na nota) · venda de 02/06/2026 — pagamento recebido em 18/06/2026 | J76: EMP-0063
A77: 46191 | B77: Jose Augusto Martins dos Santos - Erica Martins | C77: Refil Everest | D77: 120 | E77: Crédito Parcelado | I77: NFC-e 9119
A78: 46191 | B78: Consumidor Final | C78: Refil E3 | D78: 90 | E78: Crédito Parcelado | I78: NFC-e 9120
A79: 46191 | B79: Luana Barros Vieira de Carvalho - Emanuel Bernadino | C79: Refil Everest + Pré Filtro | D79: 200 | E79: Crédito Parcelado | I79: NFC-e 9121
A80: 46191 | B80: Consumidor Final | C80: Refil BAG | D80: 50 | E80: Crédito Parcelado | I80: NFC-e 9122
A81: 46191 | B81: Instituição Adventista Nordeste Brasileiro | C81: Pré Filtro + Refil Everest + 2x Refil Plissado + 2x Refil Multifilter + Refil Carbon Tech 9" | D81: 625 | I81: NF-e 4232 · nota faturada a prazo (forma de recebimento não consta na nota) · venda de 17/06/2026 — pagamento recebido em 18/06/2026 | J81: ESC-0016
A82: 46191 | B82: Everest Refrigeracao e Industria | G82: 856.35 | H82: Fornecedores / Mercadoria | I82: NF 377739 de 19/05/2026 · parcela 1/5 (venc. 18/06/2026) · compra total R$ 4.281,74: Purificador Everest Slim Branco + Purificador Everest Slim Preto + Purificador Everest Plus Branco + Purificador Everest Star Branco + Purificador Everest Fit Branco + Purificador Everest Plus Prata · Livro Caixa
A83: 46191 | B83: Everest Refrigeracao e Industria | G83: 865.5 | H83: Fornecedores / Mercadoria | I83: NF 377738 de 19/05/2026 · parcela 1/5 (venc. 18/06/2026) · compra total R$ 4.327,52: Purificador Everest Plus Branco + Purificador Everest Plus Prata + Purificador Everest Slim Branco + 2x Purificador Everest Fit Prata + Purificador Everest Fit Preto · Livro Caixa
A84: 46191 | B84: Everest Refrigeracao e Industria | G84: 167.91 | H84: Fornecedores / Mercadoria | I84: NF 377737 de 19/05/2026 · parcela 1/5 (venc. 18/06/2026) · compra total R$ 725,16 (IPI R$ 28,60): 12x Conexão T + 30x Registro + 20x Botao Completo Purificador (N) + 30x Suporte · Livro Caixa
A85: 46191 | B85: Filtros Planeta Agua Ind e Com Ltda | G85: 666.15 | H85: Fornecedores / Mercadoria | I85: NF 130510 de 08/05/2026 · parcela 2/4 (venc. 19/06/2026) · compra total R$ 2.803,16 (IPI R$ 138,56): 50x Refil Pro Life + 3x Refil Top Color + 5x Refil Acquatec + 5x Refil Fp4 + 6x Refil Carbon Tech 9.3/4 Pol + 6x Refil Poli Flu Plissado 9.3/4 + 5x Refil E3 + 5x Refil Top Multifilter + 3x Refil Top Color Fast + 5x Refil Fpa14 · Livro Caixa
A86: 46191 | B86: Guia do Fgts Digital | G86: 267.2 | H86: Impostos e Taxas | I86: Livro Caixa: Pagamento parcela GUIA DO FGTS DIGITAL (Doc. 1) · Caixa Economica Federal
A87: 46192 | B87: Ronie de Santana Lima | C87: Refil Pro Life + Pré Filtro | D87: 180 | E87: Pix | I87: NFC-e 9123 | J87: CLI-0858
A88: 46192 | B88: Consumidor Final | C88: Conexão | D88: 30 | E88: Pix | I88: NFC-e 9124
A89: 46192 | B89: Consumidor Final | C89: Registro | D89: 30 | E89: Dinheiro | I89: NFC-e 9125
A90: 46193 | B90: Osvaldina Soares Nery - Marilene Soares Dibec | C90: Refil Pro Life | D90: 135 | E90: Pix | I90: NFC-e 9126
A91: 46195 | B91: Aparecido Candido da Silva | C91: Refil Pro Life | D91: 140 | E91: Crédito Parcelado | I91: NFC-e 9127
A92: 46195 | B92: Consumidor Final | C92: 2x Filtro Bica Movel Preto | D92: 215 | E92: Pix | I92: NFC-e 9128
A93: 46195 | B93: Uelber do Nascimento Barbosa - Carine Lima | C93: Refil Pro Life | D93: 140 | E93: Crédito Parcelado | I93: NFC-e 9129
A94: 46195 | B94: Comercial de Motos, Motores, Peças e Acessórios Várzea - Yamaha | C94: Refil Everest | D94: 130 | E94: Pix | I94: NF-e 4234 | J94: EMP-0098
A95: 46196 | B95: Piemonte da Chapada Transportes Ltda | C95: Refil Everest + Refil Carbon Tech 9" | D95: 200 | E95: Dinheiro | I95: NF-e 4235
A96: 46196 | B96: Real Sociedade Portuguesa de Beneficencia 16 de Setembro | C96: 4x Refil Everest + Refil Carbon Block | D96: 560 | E96: Dinheiro | I96: NF-e 4236
A97: 46198 | B97: Escola Municipal Nubia Maria Mangabeira Guerra | C97: Purificador Everest Plus Prata | D97: 1440 | I97: NF-e 4233 · nota faturada a prazo (forma de recebimento não consta na nota) · venda de 18/06/2026 — pagamento recebido em 25/06/2026 | J97: ESC-0020
A98: 46198 | B98: Jefferson do Rosario Rios Freitas | C98: Refil Pro Life | D98: 140 | E98: Pix | I98: NFC-e 9130 | J98: CLI-0861
A99: 46198 | B99: Consumidor Final | C99: Refil Universal | D99: 30 | E99: Débito | I99: NFC-e 9131
A100: 46198 | B100: Consumidor Final | C100: Refil FPA14 | D100: 95 | E100: Crédito Parcelado | I100: NFC-e 9132
...

Sheet Jul 2026
A1: RELATÓRIO FINANCEIRO — JULHO / 2026
A2: Fluxo de caixa da loja — entradas montadas a partir das notas fiscais (XML do DigiSat), com cliente e produtos; saídas do Livro Caixa
A3: ← Início
A4: Data | B4: Descrição / Cliente | C4: Produto | D4: Entrada (R$) | E4: Forma de Pagamento | F4: Taxa da Máquina (R$) | G4: Saída (R$) | H4: Categoria da Saída | I4: Observações | J4: ID Cliente | K4: Saídas por Categoria | N4: FATURAMENTO | P4: DESPESAS | R4: SALDO ANTES DO PRÓ-LABORE | T4: A RECEBER
A5: 46204 | B5: Luzia Rodrigues de Souza | C5: Purificador Everest Star Branco | D5: 1250 | E5: Dinheiro | I5: NF-e 4244 | J5: CLI-0864 | K5: Fornecedores / Mercadoria | L5: =SUMIF(H5:H123,K5,G5:G123) | N5: =D124-F124-T5 | P5: =L18-L19 | R5: =D125 | T5: =SUMIF(E5:E123,"Aguardando Pagamento",D5:D123)
A6: 46204 | B6: Consumidor Final | C6: Filtro Bica Movel Branco | D6: 115 | E6: Pix | I6: NFC-e 9138 | K6: Aluguel | L6: =SUMIF(H5:H123,K6,G5:G123)
A7: 46204 | B7: Joaquim Silva Oliveira - Gessy | C7: Refil Everest | D7: 140 | E7: Crédito Parcelado | I7: NFC-e 9139 | K7: Água, Energia e Internet | L7: =SUMIF(H5:H123,K7,G5:G123) | N7: PRÓ-LABORE EDILÂNIA | P7: COMBINADO NO MÊS | R7: =IF(L17>'Ponto de Equilíbrio'!$B$10,"PASSOU DO COMBINADO",IF(TODAY()>EOMONTH(DATE(2026,7,1),0),"ABAIXO DO COMBINADO","AINDA PODE GASTAR")) | T7: SOBRA FINAL DO MÊS
A8: 46204 | B8: Contabilidade Abreu | C8: Refil Everest | D8: 140 | E8: Pix | I8: NF-e 4245 | J8: EMP-0105 | K8: Impostos e Taxas | L8: =SUMIF(H5:H123,K8,G5:G123) | N8: =L17 | P8: ='Ponto de Equilíbrio'!$B$10 | R8: =ABS('Ponto de Equilíbrio'!$B$10-L17) | T8: =R5-L17
A9: 46204 | B9: Jonas Cezar Alves de Araujo | C9: Refil Everest | D9: 140 | E9: Pix | I9: NFC-e 9140 | J9: CLI-0865 | K9: Tarifas Bancárias e Cartão | L9: =SUMIF(H5:H123,K9,G5:G123)
A10: 46204 | B10: Banco Bradesco Sa | C10: Refil Plissado + Refil Top Color | D10: 195 | I10: NF-e 4243. Recebimento não constava no Livro Caixa; conferido e baixado no DigiSat em 28/09/2026. | K10: Transporte e Entregas | L10: =SUMIF(H5:H123,K10,G5:G123)
A11: 46204 | B11: Eversoft Ind e Com de Plasticos Ltda | G11: 878.92 | H11: Fornecedores / Mercadoria | I11: NF 72153 de 02/04/2026 · parcela 3/5 (venc. 01/07/2026) · compra total R$ 4.394,61: 100x Refil Everest · Livro Caixa | K11: Salários, Comissões e Encargos | L11: =SUMIF(H5:H123,K11,G5:G123)
A12: 46204 | B12: Embasa Adriano | G12: 50.07 | H12: Pro Labore Edilânia | I12: Livro Caixa: Pagamento parcela EMBASA ADRIANO (Doc. 1) · Empresa Baiana de Aguas e Saneamento Sa | K12: Contabilidade | L12: =SUMIF(H5:H123,K12,G5:G123)
A13: 46204 | B13: Aluguel Vitoria Maria | G13: 880 | H13: Aluguel | I13: Livro Caixa: Pagamento à vista: ALUGUEL VITORIA MARIA (Doc. 1) · Vitoria Maria F Santos | K13: Manutenção e Reparos | L13: =SUMIF(H5:H123,K13,G5:G123)
A14: 46206 | B14: Hidroluz | C14: Refil BAG + Mangueira Fina Branca 6,35 X 1Mm | D14: 70 | E14: Dinheiro | I14: NF-e 4246 | J14: EMP-0169 | K14: Material de Limpeza e Escritório | L14: =SUMIF(H5:H123,K14,G5:G123)
A15: 46206 | B15: Gomes e Nascimento Equipamentos de Seguranca Ltda | C15: Refil Pro Life | D15: 130 | I15: NF-e 4241 · nota faturada a prazo (forma de recebimento não consta na nota) · venda de 30/06/2026 — pagamento recebido em 03/07/2026 | K15: Estornos de Vendas (Cancelamentos) | L15: =SUMIF(H5:H123,K15,G5:G123)
A16: 46206 | B16: Consumidor Final | C16: Refil Carbon Block | D16: 50 | E16: Pix | I16: NFC-e 9141 | K16: Outras Despesas | L16: =SUMIF(H5:H123,K16,G5:G123)
A17: 46206 | B17: Bolsa Estagio | G17: 600 | H17: Salários, Comissões e Encargos | I17: Livro Caixa: Pagamento à vista: BOLSA ESTAGIO (Doc. 1) · Erick Feitosa Evangelista | K17: Pro Labore Edilânia | L17: =SUMIF(H5:H123,K17,G5:G123)
A18: 46206 | B18: Rescisão Daniel | G18: 4145.56 | H18: Salários, Comissões e Encargos | I18: Livro Caixa: Pagamento à vista: RESCISÃO DANIEL (Doc. 1) · Daniel Barbosa dos Santos | K18: Total | L18: =SUM(L5:L16)
A19: 46206 | B19: Salario Wiliam | G19: 1643.43 | H19: Salários, Comissões e Encargos | I19: Livro Caixa: Pagamento à vista: SALARIO WILIAM (Doc. 1) · Wiliam Pinto Bispo | K19: Capital de Giro (BB) — ainda a devolver | L19: =SUMIFS('Capital de Giro (BB)'!D9:D200,'Capital de Giro (BB)'!A9:A200,">="&DATE(2026,7,1),'Capital de Giro (BB)'!A9:A200,"<="&DATE(2026,7,31),'Capital de Giro (BB)'!E9:E200,"A Devolver")
A20: 46206 | B20: Filtros Planeta Agua Ind e Com Ltda | G20: 666.15 | H20: Fornecedores / Mercadoria | I20: NF 130510 de 08/05/2026 · parcela 3/4 (venc. 03/07/2026) · compra total R$ 2.803,16 (IPI R$ 138,56): 50x Refil Pro Life + 3x Refil Top Color + 5x Refil Acquatec + 5x Refil Fp4 + 6x Refil Carbon Tech 9.3/4 Pol + 6x Refil Poli Flu Plissado 9.3/4 + 5x Refil E3 + 5x Refil Top Multifilter + 3x Refil Top Color Fast + 5x Refil Fpa14 · Livro Caixa
A21: 46209 | B21: Rodolfo de Santana Silva | C21: Refil Everest | D21: 140 | E21: Crédito Parcelado | I21: NFC-e 9142
A22: 46209 | B22: Maria Rita Silva Souza | C22: Refil Everest | D22: 140 | E22: Crédito Parcelado | I22: NFC-e 9143
A23: 46209 | B23: N N Modas - F B de Araujo | C23: Refil Everest + Pré Filtro | D23: 190 | E23: Dinheiro | I23: NF-e 4248 | J23: EMP-0228
A24: 46209 | B24: Wiliam Pinto Bispo | D24: 1643.43 | I24: Livro Caixa: Estorno de pagamento do documento: SALARIO WILIAM (Doc. 1)
A25: 46209 | B25: Cledson Oliveira dos Santos | C25: Refil Everest + Pré Filtro | D25: 190 | E25: Dinheiro | I25: NFC-e 9144 | J25: CLI-0877
A26: 46209 | B26: Jailma Moreira dos Santos | C26: Refil Everest | D26: 135 | E26: Dinheiro | I26: NFC-e 9145 | J26: CLI-0870
A27: 46209 | B27: Vitoria Maria F Santos | D27: 870 | I27: Livro Caixa: Estorno de pagamento do documento: ALUGUEL VITORIA MARIA
A28: 46209 | B28: Clinica Humana | C28: 4x Refil Everest | D28: 560 | I28: NF-e 4247 · nota faturada a prazo (forma de recebimento não consta na nota) · venda de 03/07/2026 — pagamento recebido em 06/07/2026 | J28: EMP-0079
A29: 46209 | B29: Lojas GeoComercial Ltda | C29: Refil Everest + Pré Filtro | D29: 200 | I29: NF-e 4240 · nota faturada a prazo (forma de recebimento não consta na nota) · venda de 30/06/2026 — pagamento recebido em 06/07/2026 | J29: EMP-0208
A30: 46209 | B30: Aluguel Vitoria Maria | G30: 870 | H30: Aluguel | I30: Livro Caixa: Pagamento à vista: ALUGUEL VITORIA MARIA (Doc. 1) · Vitoria Maria F Santos
A31: 46210 | B31: Cbv Construtora Ltda | C31: 2x Refil Carbon Tech 9" | D31: 160 | E31: Dinheiro | I31: NF-e 4249
A32: 46210 | B32: Consumidor Final | C32: Refil Pro Life + Pré Filtro | D32: 200 | E32: Pix | I32: NFC-e 9146
A33: 46210 | B33: Iranildo Benedito Silva | C33: Refil Everest | D33: 140 | E33: Pix | I33: NFC-e 9147 | J33: CLI-0871
A34: 46210 | B34: Drillgeo Geologia e Sondagens S/A | C34: Refil Plissado + Refil Carbon Tech 9" | D34: 180 | I34: NF-e 4250. Recebimento não constava no Livro Caixa; conferido e baixado no DigiSat em 28/09/2026.
A35: 46211 | B35: Cbv Construtora Ltda | C35: Refil PA 230 | D35: 80 | E35: Pix | I35: NF-e 4251
A36: 46211 | B36: Clinica Ginecologica Pinho LTDA - Cligine | C36: Refil Everest | D36: 135 | E36: Dinheiro | I36: NF-e 4252 | J36: EMP-0078
A37: 46211 | B37: Eliana Oliveira Nunes | C37: Refil Pro Life + Pré Filtro | D37: 200 | E37: Crédito Parcelado | I37: NFC-e 9148
A38: 46211 | B38: Otica Realce - Fernando Carneiro & Cia Ltda | C38: Refil Everest | D38: 140 | E38: Pix | I38: NF-e 4253 | J38: EMP-0241
A39: 46211 | B39: Somhara Brito | C39: Suporte + Registro | D39: 120 | E39: Pix | I39: NFC-e 9149 | J39: CLI-0161
A40: 46211 | B40: Marilza da Silva Oliveira Matos | C40: Refil Pro Life + Pré Filtro | D40: 190 | E40: Pix | I40: NFC-e 9150 | J40: CLI-0873
A41: 46211 | B41: Everest Refrigeracao e Industria | G41: 706.65 | H41: Fornecedores / Mercadoria | I41: NF 374271 de 06/04/2026 · parcela 3/5 (venc. 05/07/2026) · compra total R$ 3.533,27: Purificador Everest Plus Prata + Purificador Everest Star Branco + Purificador Everest Star Preto + Purificador Everest Slim Prata + Purificador Everest Fit Branco · Livro Caixa
A42: 46211 | B42: Eversoft Ind e Com de Plasticos Ltda | G42: 980.83 | H42: Fornecedores / Mercadoria | I42: NF 72869 de 07/05/2026 · parcela 2/5 (venc. 06/07/2026) · compra total R$ 4.904,13: 100x Refil Everest + 50x Pré Filtro · Livro Caixa
A43: 46211 | B43: Conta de Energia Loja | G43: 141.67 | H43: Água, Energia e Internet | I43: Livro Caixa: Pagamento parcela CONTA DE ENERGIA LOJA (Doc. 1) · Companhia de Eletricidade do Estado da Bahia Coelba
A44: 46211 | B44: Conta de Energia Adriano | G44: 316.11 | H44: Pro Labore Edilânia | I44: Livro Caixa: Pagamento parcela CONTA DE ENERGIA ADRIANO (Doc. 1) · Companhia de Eletricidade do Estado da Bahia Coelba
A45: 46211 | B45: Everest Refrigeracao e Industria | G45: 725.48 | H45: Fornecedores / Mercadoria | I45: NF 372597 de 11/03/2026 · parcela 4/5 (venc. 09/07/2026) · compra total R$ 3.627,42: 2x Purificador Everest Plus Branco + Purificador Everest Fit Preto + Purificador Everest Slim Preto + Purificador Everest Star Preto · Livro Caixa
A46: 46211 | B46: Eversoft Ind e Com de Plasticos Ltda | G46: 878.92 | H46: Fornecedores / Mercadoria | I46: NF 73636 de 10/06/2026 · parcela 1/5 (venc. 10/07/2026) · compra total R$ 4.394,61: 100x Refil Everest · Livro Caixa
A47: 46211 | B47: Mercado Livre | G47: 216.46 | H47: Tarifas Bancárias e Cartão | I47: Livro Caixa: Pagamento à vista: MERCADO LIVRE (Doc. 1) · Mercado Pago Instituicao de Pagamento Ltda
A48: 46212 | B48: Armando Dias Freire | C48: 77x Refil Everest | D48: 3465 | E48: Dinheiro | I48: NFC-e 9151
A49: 46212 | B49: Armando Dias Freire | C49: Refil Everest | D49: 35 | E49: Dinheiro | I49: NFC-e 9152
A50: 46212 | B50: Ritha de Cassia Vieira Seixas Brito | C50: Refil Everest | D50: 140 | E50: Pix | I50: NFC-e 9153 | J50: CLI-0875
A51: 46212 | B51: Orlinda Rocha da Silva | C51: Refil Pro Life | D51: 140 | E51: Débito | I51: NFC-e 9154
A52: 46212 | B52: G - Link Telecon - Gleidson Nascimento Barbosa | C52: Refil Pro Life + Mangueira Plastica Para Agua 06 35Mm | D52: 150 | E52: Dinheiro | I52: NF-e 4254 | J52: EMP-0160
A53: 46212 | B53: Carlos Geovane Carneiro de Oliveira | C53: Refil Everest | D53: 135 | E53: Dinheiro | I53: NF-e 4255
A54: 46212 | B54: Ocimar Correia Feitosa | C54: Purificador Everest Baby Preto + Conexão | D54: 500 | E54: Dinheiro | I54: NF-e 4256 | J54: CLI-0878
A55: 46212 | B55: Pro Labore Edilania | G55: 1550 | H55: Pro Labore Edilânia | I55: Livro Caixa: Pagamento parcela Pro labore Edilania (Doc. 1) · Edilania Fontes - Loja
A56: 46213 | B56: Sindicato dos Trabalhadores Em Educacao das Redes Publicas E | C56: Purificador Everest Plus Prata + Pré Filtro | D56: 1500 | E56: Dinheiro | I56: NF-e 4257
A57: 46213 | B57: Lucilia Batista de Santa Rosa | C57: Purificador Everest Fit Branco + Pré Filtro | D57: 1460 | E57: Dinheiro | I57: NF-e 4258 | J57: CLI-0879
A58: 46214 | B58: Tiago Manoel Dias Ferreira | C58: Purificador Everest Fit Preto + Pré Filtro | D58: 1510 | E58: Dinheiro | I58: NF-e 4259
A59: 46214 | B59: Antonio Carlos Santana Rios | C59: Refil Pro Life + Mangueira (1 m) | D59: 150 | E59: Crédito Parcelado | I59: NFC-e 9155
A60: 46216 | B60: Igreja Missionaria de Jacobina Cristo para as Nações | D60: 40 | I60: Livro Caixa: Recebimento à vista Gerado pelo sistema. (Doc. 4260) | J60: EMP-0178
A61: 46216 | B61: Igreja Missionaria de Jacobina Cristo para as Nações | D61: 40 | I61: Livro Caixa: Recebimento à vista Gerado pelo sistema. (Doc. 4261) | J61: EMP-0178
A62: 46216 | B62: Jupiter Tecidos Ltda | C62: Refil Everest + Refil Plissado + Refil CP500 BR + Suporte | D62: 400 | I62: NF-e 4262. Recebimento não constava no Livro Caixa; conferido e baixado no DigiSat em 28/09/2026.
A63: 46216 | B63: Estorno de recebimento — Igreja Missionaria de Jacobina Cristo Para As Nacoes | G63: 40 | H63: Estornos de Vendas (Cancelamentos) | I63: Livro Caixa: Estorno de recebimento do documento: Gerado pelo sistema. (Doc. 42)
A64: 46216 | B64: Estorno de recebimento — Igreja Missionaria de Jacobina Cristo Para As Nacoes | G64: 40 | H64: Estornos de Vendas (Cancelamentos) | I64: Livro Caixa: Estorno de recebimento do documento: Gerado pelo sistema. (Doc. 42)
A65: 46218 | B65: Farmácia Ferreira - A Fórmula | C65: Refil Everest + Pré Filtro | D65: 200 | E65: Dinheiro | I65: NF-e 4264 | J65: EMP-0145
A66: 46218 | B66: Jupiter Tecidos Ltda | C66: Refil Everest + Refil Plissado + Refil CP500 BR + Suporte | D66: 400 | E66: Dinheiro | I66: NF-e 4267
A67: 46218 | B67: José Alves de Andrade - Rosilda Alves | C67: Refil Everest | D67: 135 | E67: Pix | I67: NFC-e 9156 | J67: CLI-0881
A68: 46218 | B68: D Bruno Calcados e Confeccoes Ltda Epp | C68: 2x Refil Everest + 2x Pré Filtro | D68: 400 | E68: Dinheiro | I68: NF-e 4268
A69: 46218 | B69: Consumidor Final | C69: 3x Refil Multifilter + Refil Carbon Block | D69: 310 | E69: Dinheiro | I69: NFC-e 9157
A70: 46218 | B70: Luis Henrique Cabral Assis - Luciana Maia | C70: Refil Pro Life + Mangueira (1 m) | D70: 150 | E70: Débito | I70: NFC-e 9158
A71: 46218 | B71: Jupiter Tecidos Ltda | G71: 400 | H71: Outras Despesas | I71: Livro Caixa: Pagamento à vista: Gerado pelo sistema. (Doc. 4266)
A72: 46218 | B72: Taxa Administrativa de Estagio | G72: 75 | H72: Salários, Comissões e Encargos | I72: Livro Caixa: Pagamento parcela TAXA ADMINISTRATIVA DE ESTAGIO (Doc. 1) · Instituto Euvaldo Lodi - Nucleo Regional da Bahia
A73: 46218 | B73: Filtros Planeta Agua Ind e Com Ltda | G73: 609.26 | H73: Fornecedores / Mercadoria | I73: NF 131442 de 17/06/2026 · parcela 1/4 (venc. 15/07/2026) · compra total R$ 2.122,28 (IPI R$ 104,91): 25x Refil Pro Life + 5x Refil Fit Poe Pp 9.3/4 + 10x Refil Bebedouro B A G + 8x Refil Carbon Tech 5 Pol + 10x Refil Carbon Tech 9.3/4 Pol + 2x Refil Pa 230 Fit + 4x Refil Fpa16 · Livro Caixa
A74: 46218 | B74: Tarcosop Oliveira Lima | G74: 486.32 | H74: Contabilidade | I74: Livro Caixa: Pagamento parcela TARCOSOP OLIVEIRA LIMA (Doc. 1) · Contabilidade Tarcisio Oliveira Lima
A75: 46218 | B75: Filtros Planeta Agua Ind e Com Ltda | G75: 666.15 | H75: Fornecedores / Mercadoria | I75: NF 130510 de 08/05/2026 · parcela 4/4 (venc. 17/07/2026) · compra total R$ 2.803,16 (IPI R$ 138,56): 50x Refil Pro Life + 3x Refil Top Color + 5x Refil Acquatec + 5x Refil Fp4 + 6x Refil Carbon Tech 9.3/4 Pol + 6x Refil Poli Flu Plissado 9.3/4 + 5x Refil E3 + 5x Refil Top Multifilter + 3x Refil Top Color Fast + 5x Refil Fpa14 · Livro Caixa
A76: 46218 | B76: Fatura Internet Proxxima | G76: 69.99 | H76: Água, Energia e Internet | I76: Livro Caixa: Pagamento à vista: FATURA INTERNET PROXXIMA (Doc. 1) · Proxxima Telecomunicacoes
A77: 46219 | B77: Consumidor Final | C77: Refil Carbon Tech 9" + Refil Top Color | D77: 180 | E77: Crédito Parcelado | I77: NFC-e 9159
A78: 46220 | B78: Maria do Carmo Mendes | D78: 65 | I78: Livro Caixa: Recebimento à vista Gerado pelo sistema (Doc. 9160) | J78: OUT-0061
A79: 46220 | B79: Consumidor Final | C79: Registro | D79: 65 | E79: Dinheiro | I79: NFC-e 9161
A80: 46220 | B80: Maria do Carmo Mendes | C80: Conjunto Torneira Star/Plus/Fit Completa N + 2x Botão Completo | D80: 200 | E80: Pix | I80: NFC-e 9162 | J80: OUT-0061
A81: 46220 | B81: Grafica Editora Regis Brindes Ltda | C81: Refil Everest + Refil Pro Life | D81: 270 | E81: Dinheiro | I81: NF-e 4269
A82: 46220 | B82: Estorno de recebimento — Maria do Carmo Mendes | G82: 65 | H82: Estornos de Vendas (Cancelamentos) | I82: Livro Caixa: Estorno de recebimento do documento: Gerado pelo sistema (Doc. 916)
A83: 46220 | B83: Produtos de Limpeza | G83: 10.99 | H83: Material de Limpeza e Escritório | I83: Livro Caixa: Pagamento à vista: PRODUTOS DE LIMPEZA (Doc. 1) · Jacobina Material de Limpeza Eireli
A84: 46220 | B84: Material de Escritorio | G84: 12.2 | H84: Material de Limpeza e Escritório | I84: Livro Caixa: Pagamento à vista: MATERIAL DE ESCRITORIO (Doc. 1) · Universo das Variedades
A85: 46223 | B85: Consumidor Final | C85: Refil Carbon Block | D85: 55 | E85: Dinheiro | I85: NFC-e 9164
A86: 46223 | B86: Maria Conceição Carvalho Mesquita | C86: Refil Pro Life | D86: 135 | I86: NFC-e 9163 · venda de 17/07/2026, total R$ 140,00 — parcela 1 · nota faturada a prazo (forma de recebimento não consta na nota) | J86: CLI-0702
A87: 46223 | B87: Gasolina | G87: 20 | H87: Transporte e Entregas | I87: Livro Caixa: Pagamento à vista: GASOLINA (Doc. 1) · Lubrinessa Xvi Comercio de Petroleo Ltda
A88: 46223 | B88: Recarga Cartucho Impressora | G88: 30 | H88: Transporte e Entregas | I88: Livro Caixa: Pagamento à vista: RECARGA CARTUCHO IMPRESSORA (Doc. 1) · Centralmix Solucoes Integradas Ltda
A89: 46223 | B89: Everest Refrigeracao e Industria | G89: 856.35 | H89: Fornecedores / Mercadoria | I89: NF 377739 de 19/05/2026 · parcela 2/5 (venc. 18/07/2026) · compra total R$ 4.281,74: Purificador Everest Slim Branco + Purificador Everest Slim Preto + Purificador Everest Plus Branco + Purificador Everest Star Branco + Purificador Everest Fit Branco + Purificador Everest Plus Prata · Livro Caixa
A90: 46223 | B90: Everest Refrigeracao e Industria | G90: 865.5 | H90: Fornecedores / Mercadoria | I90: NF 377738 de 19/05/2026 · parcela 2/5 (venc. 18/07/2026) · compra total R$ 4.327,52: Purificador Everest Plus Branco + Purificador Everest Plus Prata + Purificador Everest Slim Branco + 2x Purificador Everest Fit Prata + Purificador Everest Fit Preto · Livro Caixa
A91: 46223 | B91: Everest Refrigeracao e Industria | G91: 139.31 | H91: Fornecedores / Mercadoria | I91: NF 377737 de 19/05/2026 · parcela 2/5 (venc. 18/07/2026) · compra total R$ 725,16 (IPI R$ 28,60): 12x Conexão T + 30x Registro + 20x Botao Completo Purificador (N) + 30x Suporte · Livro Caixa
A92: 46223 | B92: Guia do Fgts Digital | G92: 136 | H92: Impostos e Taxas | I92: Livro Caixa: Pagamento parcela GUIA DO FGTS DIGITAL (Doc. 1) · Caixa Economica Federal
A93: 46223 | B93: Documento de Arrecadacao de Receitas Fe | G93: 440.22 | H93: Impostos e Taxas | I93: Livro Caixa: Pagamento parcela DOCUMENTO DE ARRECADACAO DE RECEITAS FE · Ministerio da Fazenda
A94: 46223 | B94: Documento de Arrecadação Simples Nacio | G94: 1024.32 | H94: Impostos e Taxas | I94: Livro Caixa: Pagamento parcela DOCUMENTO DE ARRECADAÇÃO SIMPLES NACIO · Ministerio da Fazenda
